Workbook

Sheet Start here
A1: Startup idea research | B1: Which pre-seed ideas are incubators funding, and where can two founders from India apply?
A3: How to read this file
A4: Themes overview | B4: All themes on one page with how many companies YC funded in each of its last 5 batches. Start here to see what is rising.
A5: Incubators | B5: Each program: money, equity taken, who can apply, timing, and how far to trust the row.
A6: One tab per theme | B6: Each theme tab lists funded startups with the idea in one plain sentence. Rows based in India are shaded yellow.
A7: India-based | B7: Every funded startup in this file that is based in India, across all themes.
A8: YC all 900 | B8: Every YC company from Fall 2025 to Fall 2026 with YC's own one-line description and its theme. Use the filters.
A10: What the columns mean
A11: Funding | B11: The program's standard cheque unless the startup's own round was reported. The next column says which.
A12: India / USA / Other | B12: Where the company is based, not where the founders are from. 'Unknown' means the source did not say.
A13: Indian founders? | B13: yes = source says so or company is in India. reported = a newsletter lists them as Indian-origin, not verified. unknown = not checked.
A14: Confidence | B14: high = official directory or the program's own page. medium = news report. low = third-party list.
A16: Where the data lives | B16: This file is generated from the CSV files in data/ by scripts/build_workbook.py. Edit the CSVs, not this file.
A17: Research date | B17: 2026-10-13

Sheet Themes overview
A1: Theme | B1: What it means in simple words | C1: Tab name | D1: Startups listed in this file | E1: YC Fall 2025 | F1: YC Winter 2026 | G1: YC Spring 2026 | H1: YC Summer 2026 | I1: YC Fall 2026 | J1: YC total (5 batches) | K1: Share of Fall 2025 batch | L1: Share of Summer 2026 batch
A2: AI-native service companies | B2: Instead of selling software to a law firm or an accounting firm, the startup IS the firm. It sells the finished work (a filed tax return, an insurance policy, a collected debt) and uses AI internally so it needs far fewer people. | C2: AI service firms | D2: =COUNTA('AI service firms'!$B:$B)-1 -> 18 | E2: =COUNTIFS('YC all 900'!$A:$A,$C2,'YC all 900'!$E:$E,"Fall 2025") -> 4 | F2: =COUNTIFS('YC all 900'!$A:$A,$C2,'YC all 900'!$E:$E,"Winter 2026") -> 8 | G2: =COUNTIFS('YC all 900'!$A:$A,$C2,'YC all 900'!$E:$E,"Spring 2026") -> 9 | H2: =COUNTIFS('YC all 900'!$A:$A,$C2,'YC all 900'!$E:$E,"Summer 2026") -> 20 | I2: =COUNTIFS('YC all 900'!$A:$A,$C2,'YC all 900'!$E:$E,"Fall 2026") -> 6 | J2: =SUM(E2:I2) -> 47 | K2: =IF(E$25=0,0,E2/E$25) -> 0.027586207 | L2: =IF(H$25=0,0,H2/H$25) -> 0.086956522
A3: AI for traditional industries | B3: An "AI employee" or "AI operating system" for one old-school industry: hotels, restaurants, auto repair shops, construction, trucking, wholesale distributors, property managers. | C3: Old-industry AI | D3: =COUNTA('Old-industry AI'!$B:$B)-1 -> 21 | E3: =COUNTIFS('YC all 900'!$A:$A,$C3,'YC all 900'!$E:$E,"Fall 2025") -> 10 | F3: =COUNTIFS('YC all 900'!$A:$A,$C3,'YC all 900'!$E:$E,"Winter 2026") -> 13 | G3: =COUNTIFS('YC all 900'!$A:$A,$C3,'YC all 900'!$E:$E,"Spring 2026") -> 11 | H3: =COUNTIFS('YC all 900'!$A:$A,$C3,'YC all 900'!$E:$E,"Summer 2026") -> 13 | I3: =COUNTIFS('YC all 900'!$A:$A,$C3,'YC all 900'!$E:$E,"Fall 2026") -> 3 | J3: =SUM(E3:I3) -> 50 | K3: =IF(E$25=0,0,E3/E$25) -> 0.068965517 | L3: =IF(H$25=0,0,H3/H$25) -> 0.056521739
A4: AI for finance and back-office teams | B4: AI agents that do the boring finance work inside companies, banks, lenders and insurers: bookkeeping, invoices, audits, loan files, claims, compliance checks, investment research. | C4: Finance back-office | D4: =COUNTA('Finance back-office'!$B:$B)-1 -> 18 | E4: =COUNTIFS('YC all 900'!$A:$A,$C4,'YC all 900'!$E:$E,"Fall 2025") -> 8 | F4: =COUNTIFS('YC all 900'!$A:$A,$C4,'YC all 900'!$E:$E,"Winter 2026") -> 12 | G4: =COUNTIFS('YC all 900'!$A:$A,$C4,'YC all 900'!$E:$E,"Spring 2026") -> 6 | H4: =COUNTIFS('YC all 900'!$A:$A,$C4,'YC all 900'!$E:$E,"Summer 2026") -> 5 | I4: =COUNTIFS('YC all 900'!$A:$A,$C4,'YC all 900'!$E:$E,"Fall 2026") -> 9 | J4: =SUM(E4:I4) -> 40 | K4: =IF(E$25=0,0,E4/E$25) -> 0.055172414 | L4: =IF(H$25=0,0,H4/H$25) -> 0.02173913
A5: Healthcare AI | B5: AI for clinics, hospitals and patients: medical billing, insurance approvals, front-desk calls, AI doctors and health assistants, medical imaging. | C5: Healthcare AI | D5: =COUNTA('Healthcare AI'!$B:$B)-1 -> 26 | E5: =COUNTIFS('YC all 900'!$A:$A,$C5,'YC all 900'!$E:$E,"Fall 2025") -> 8 | F5: =COUNTIFS('YC all 900'!$A:$A,$C5,'YC all 900'!$E:$E,"Winter 2026") -> 11 | G5: =COUNTIFS('YC all 900'!$A:$A,$C5,'YC all 900'!$E:$E,"Spring 2026") -> 10 | H5: =COUNTIFS('YC all 900'!$A:$A,$C5,'YC all 900'!$E:$E,"Summer 2026") -> 8 | I5: =COUNTIFS('YC all 900'!$A:$A,$C5,'YC all 900'!$E:$E,"Fall 2026") -> 6 | J5: =SUM(E5:I5) -> 43 | K5: =IF(E$25=0,0,E5/E$25) -> 0.055172414 | L5: =IF(H$25=0,0,H5/H$25) -> 0.034782609
A6: Enterprise AI workers and company brain | B6: General-purpose AI employees for any company, a "company brain" that remembers everything the company knows, customer-support agents, and teams that go into a big company and automate its work for it. | C6: AI workforce | D6: =COUNTA('AI workforce'!$B:$B)-1 -> 20 | E6: =COUNTIFS('YC all 900'!$A:$A,$C6,'YC all 900'!$E:$E,"Fall 2025") -> 12 | F6: =COUNTIFS('YC all 900'!$A:$A,$C6,'YC all 900'!$E:$E,"Winter 2026") -> 9 | G6: =COUNTIFS('YC all 900'!$A:$A,$C6,'YC all 900'!$E:$E,"Spring 2026") -> 17 | H6: =COUNTIFS('YC all 900'!$A:$A,$C6,'YC all 900'!$E:$E,"Summer 2026") -> 14 | I6: =COUNTIFS('YC all 900'!$A:$A,$C6,'YC all 900'!$E:$E,"Fall 2026") -> 5 | J6: =SUM(E6:I6) -> 57 | K6: =IF(E$25=0,0,E6/E$25) -> 0.082758621 | L6: =IF(H$25=0,0,H6/H$25) -> 0.060869565
A7: Sales, marketing and growth AI | B7: AI that finds customers, runs ads, writes marketing content, coaches sales calls, and helps a product get recommended by ChatGPT-style assistants. | C7: Sales and marketing | D7: =COUNTA('Sales and marketing'!$B:$B)-1 -> 20 | E7: =COUNTIFS('YC all 900'!$A:$A,$C7,'YC all 900'!$E:$E,"Fall 2025") -> 11 | F7: =COUNTIFS('YC all 900'!$A:$A,$C7,'YC all 900'!$E:$E,"Winter 2026") -> 12 | G7: =COUNTIFS('YC all 900'!$A:$A,$C7,'YC all 900'!$E:$E,"Spring 2026") -> 18 | H7: =COUNTIFS('YC all 900'!$A:$A,$C7,'YC all 900'!$E:$E,"Summer 2026") -> 8 | I7: =COUNTIFS('YC all 900'!$A:$A,$C7,'YC all 900'!$E:$E,"Fall 2026") -> 5 | J7: =SUM(E7:I7) -> 54 | K7: =IF(E$25=0,0,E7/E$25) -> 0.075862069 | L7: =IF(H$25=0,0,H7/H$25) -> 0.034782609
A8: Recruiting and hiring | B8: AI recruiters, hiring marketplaces, tools that test candidates, and agents that apply to jobs for you. | C8: Hiring | D8: =COUNTA(Hiring!$B:$B)-1 -> 8 | E8: =COUNTIFS('YC all 900'!$A:$A,$C8,'YC all 900'!$E:$E,"Fall 2025") -> 1 | F8: =COUNTIFS('YC all 900'!$A:$A,$C8,'YC all 900'!$E:$E,"Winter 2026") -> 2 | G8: =COUNTIFS('YC all 900'!$A:$A,$C8,'YC all 900'!$E:$E,"Spring 2026") -> 5 | H8: =COUNTIFS('YC all 900'!$A:$A,$C8,'YC all 900'!$E:$E,"Summer 2026") -> 2 | I8: =COUNTIFS('YC all 900'!$A:$A,$C8,'YC all 900'!$E:$E,"Fall 2026") -> 1 | J8: =SUM(E8:I8) -> 11 | K8: =IF(E$25=0,0,E8/E$25) -> 0.0068965517 | L8: =IF(H$25=0,0,H8/H$25) -> 0.0086956522
A9: Legal, compliance and government | B9: Software (not a law firm) for lawyers, compliance teams, patent work, product certifications, and government offices. | C9: Legal and gov | D9: =COUNTA('Legal and gov'!$B:$B)-1 -> 13 | E9: =COUNTIFS('YC all 900'!$A:$A,$C9,'YC all 900'!$E:$E,"Fall 2025") -> 6 | F9: =COUNTIFS('YC all 900'!$A:$A,$C9,'YC all 900'!$E:$E,"Winter 2026") -> 5 | G9: =COUNTIFS('YC all 900'!$A:$A,$C9,'YC all 900'!$E:$E,"Spring 2026") -> 5 | H9: =COUNTIFS('YC all 900'!$A:$A,$C9,'YC all 900'!$E:$E,"Summer 2026") -> 5 | I9: =COUNTIFS('YC all 900'!$A:$A,$C9,'YC all 900'!$E:$E,"Fall 2026") -> 3 | J9: =SUM(E9:I9) -> 24 | K9: =IF(E$25=0,0,E9/E$25) -> 0.04137931 | L9: =IF(H$25=0,0,H9/H$25) -> 0.02173913
A10: Infrastructure for AI agents | B10: The plumbing AI agents need to work on their own: a computer to run on, a wallet to pay with, a phone number, an identity, memory, web access, and cheaper model usage. | C10: Agent infrastructure | D10: =COUNTA('Agent infrastructure'!$B:$B)-1 -> 19 | E10: =COUNTIFS('YC all 900'!$A:$A,$C10,'YC all 900'!$E:$E,"Fall 2025") -> 7 | F10: =COUNTIFS('YC all 900'!$A:$A,$C10,'YC all 900'!$E:$E,"Winter 2026") -> 13 | G10: =COUNTIFS('YC all 900'!$A:$A,$C10,'YC all 900'!$E:$E,"Spring 2026") -> 9 | H10: =COUNTIFS('YC all 900'!$A:$A,$C10,'YC all 900'!$E:$E,"Summer 2026") -> 14 | I10: =COUNTIFS('YC all 900'!$A:$A,$C10,'YC all 900'!$E:$E,"Fall 2026") -> 12 | J10: =SUM(E10:I10) -> 55 | K10: =IF(E$25=0,0,E10/E$25) -> 0.048275862 | L10: =IF(H$25=0,0,H10/H$25) -> 0.060869565
A11: Agent reliability, testing and security | B11: Tools that check whether AI agents work correctly and safely: monitoring, testing in fake environments, guardrails, permission control, plus classic cybersecurity done by AI. | C11: Agent safety | D11: =COUNTA('Agent safety'!$B:$B)-1 -> 22 | E11: =COUNTIFS('YC all 900'!$A:$A,$C11,'YC all 900'!$E:$E,"Fall 2025") -> 6 | F11: =COUNTIFS('YC all 900'!$A:$A,$C11,'YC all 900'!$E:$E,"Winter 2026") -> 15 | G11: =COUNTIFS('YC all 900'!$A:$A,$C11,'YC all 900'!$E:$E,"Spring 2026") -> 9 | H11: =COUNTIFS('YC all 900'!$A:$A,$C11,'YC all 900'!$E:$E,"Summer 2026") -> 9 | I11: =COUNTIFS('YC all 900'!$A:$A,$C11,'YC all 900'!$E:$E,"Fall 2026") -> 11 | J11: =SUM(E11:I11) -> 50 | K11: =IF(E$25=0,0,E11/E$25) -> 0.04137931 | L11: =IF(H$25=0,0,H11/H$25) -> 0.039130435
A12: Coding agents and developer tools | B12: AI that writes, reviews, tests and operates software, and the tools around it: new code hosting, cloud dev machines, on-call agents that fix outages. | C12: Coding and dev tools | D12: =COUNTA('Coding and dev tools'!$B:$B)-1 -> 17 | E12: =COUNTIFS('YC all 900'!$A:$A,$C12,'YC all 900'!$E:$E,"Fall 2025") -> 14 | F12: =COUNTIFS('YC all 900'!$A:$A,$C12,'YC all 900'!$E:$E,"Winter 2026") -> 14 | G12: =COUNTIFS('YC all 900'!$A:$A,$C12,'YC all 900'!$E:$E,"Spring 2026") -> 16 | H12: =COUNTIFS('YC all 900'!$A:$A,$C12,'YC all 900'!$E:$E,"Summer 2026") -> 10 | I12: =COUNTIFS('YC all 900'!$A:$A,$C12,'YC all 900'!$E:$E,"Fall 2026") -> 7 | J12: =SUM(E12:I12) -> 61 | K12: =IF(E$25=0,0,E12/E$25) -> 0.096551724 | L12: =IF(H$25=0,0,H12/H$25) -> 0.043478261
A13: Training data and practice environments for AI | B13: Companies that sell data to AI labs: expert-written answers, recordings of people doing computer work, robot and human-movement data, practice "gyms" and benchmarks for models. | C13: Training data | D13: =COUNTA('Training data'!$B:$B)-1 -> 12 | E13: =COUNTIFS('YC all 900'!$A:$A,$C13,'YC all 900'!$E:$E,"Fall 2025") -> 5 | F13: =COUNTIFS('YC all 900'!$A:$A,$C13,'YC all 900'!$E:$E,"Winter 2026") -> 8 | G13: =COUNTIFS('YC all 900'!$A:$A,$C13,'YC all 900'!$E:$E,"Spring 2026") -> 5 | H13: =COUNTIFS('YC all 900'!$A:$A,$C13,'YC all 900'!$E:$E,"Summer 2026") -> 17 | I13: =COUNTIFS('YC all 900'!$A:$A,$C13,'YC all 900'!$E:$E,"Fall 2026") -> 3 | J13: =SUM(E13:I13) -> 38 | K13: =IF(E$25=0,0,E13/E$25) -> 0.034482759 | L13: =IF(H$25=0,0,H13/H$25) -> 0.073913043
A14: AI models, research labs and compute | B14: New AI models, small research labs, cheaper and faster clouds for running models, and GPU marketplaces. | C14: Models and compute | D14: =COUNTA('Models and compute'!$B:$B)-1 -> 18 | E14: =COUNTIFS('YC all 900'!$A:$A,$C14,'YC all 900'!$E:$E,"Fall 2025") -> 2 | F14: =COUNTIFS('YC all 900'!$A:$A,$C14,'YC all 900'!$E:$E,"Winter 2026") -> 10 | G14: =COUNTIFS('YC all 900'!$A:$A,$C14,'YC all 900'!$E:$E,"Spring 2026") -> 6 | H14: =COUNTIFS('YC all 900'!$A:$A,$C14,'YC all 900'!$E:$E,"Summer 2026") -> 9 | I14: =COUNTIFS('YC all 900'!$A:$A,$C14,'YC all 900'!$E:$E,"Fall 2026") -> 6 | J14: =SUM(E14:I14) -> 33 | K14: =IF(E$25=0,0,E14/E$25) -> 0.013793103 | L14: =IF(H$25=0,0,H14/H$25) -> 0.039130435
A15: Voice AI | B15: AI that talks and listens: voice agents for phone calls, speech models for many languages, voice infrastructure. | C15: Voice AI | D15: =COUNTA('Voice AI'!$B:$B)-1 -> 11 | E15: =COUNTIFS('YC all 900'!$A:$A,$C15,'YC all 900'!$E:$E,"Fall 2025") -> 3 | F15: =COUNTIFS('YC all 900'!$A:$A,$C15,'YC all 900'!$E:$E,"Winter 2026") -> 2 | G15: =COUNTIFS('YC all 900'!$A:$A,$C15,'YC all 900'!$E:$E,"Spring 2026") -> 3 | H15: =COUNTIFS('YC all 900'!$A:$A,$C15,'YC all 900'!$E:$E,"Summer 2026") -> 1 | I15: =COUNTIFS('YC all 900'!$A:$A,$C15,'YC all 900'!$E:$E,"Fall 2026") -> 1 | J15: =SUM(E15:I15) -> 10 | K15: =IF(E$25=0,0,E15/E$25) -> 0.020689655 | L15: =IF(H$25=0,0,H15/H$25) -> 0.0043478261
A16: Robotics and physical AI | B16: Humanoids, warehouse and farm robots, robot parts, and software that lets robots learn and be deployed. | C16: Robotics | D16: =COUNTA(Robotics!$B:$B)-1 -> 17 | E16: =COUNTIFS('YC all 900'!$A:$A,$C16,'YC all 900'!$E:$E,"Fall 2025") -> 6 | F16: =COUNTIFS('YC all 900'!$A:$A,$C16,'YC all 900'!$E:$E,"Winter 2026") -> 8 | G16: =COUNTIFS('YC all 900'!$A:$A,$C16,'YC all 900'!$E:$E,"Spring 2026") -> 9 | H16: =COUNTIFS('YC all 900'!$A:$A,$C16,'YC all 900'!$E:$E,"Summer 2026") -> 18 | I16: =COUNTIFS('YC all 900'!$A:$A,$C16,'YC all 900'!$E:$E,"Fall 2026") -> 11 | J16: =SUM(E16:I16) -> 52 | K16: =IF(E$25=0,0,E16/E$25) -> 0.04137931 | L16: =IF(H$25=0,0,H16/H$25) -> 0.07826087
A17: Defense, drones, aviation and space | B17: Counter-drone systems, interceptors, military drones, satellites, rockets, aviation software. | C17: Defense and space | D17: =COUNTA('Defense and space'!$B:$B)-1 -> 15 | E17: =COUNTIFS('YC all 900'!$A:$A,$C17,'YC all 900'!$E:$E,"Fall 2025") -> 5 | F17: =COUNTIFS('YC all 900'!$A:$A,$C17,'YC all 900'!$E:$E,"Winter 2026") -> 9 | G17: =COUNTIFS('YC all 900'!$A:$A,$C17,'YC all 900'!$E:$E,"Spring 2026") -> 7 | H17: =COUNTIFS('YC all 900'!$A:$A,$C17,'YC all 900'!$E:$E,"Summer 2026") -> 11 | I17: =COUNTIFS('YC all 900'!$A:$A,$C17,'YC all 900'!$E:$E,"Fall 2026") -> 9 | J17: =SUM(E17:I17) -> 41 | K17: =IF(E$25=0,0,E17/E$25) -> 0.034482759 | L17: =IF(H$25=0,0,H17/H$25) -> 0.047826087
A18: Manufacturing, hardware, chips and energy | B18: Factories and factory software, chip design and chip making, design tools for hardware engineers, data-center power and cooling, nuclear and grid. | C18: Industrial and hardware | D18: =COUNTA('Industrial and hardware'!$B:$B)-1 -> 28 | E18: =COUNTIFS('YC all 900'!$A:$A,$C18,'YC all 900'!$E:$E,"Fall 2025") -> 3 | F18: =COUNTIFS('YC all 900'!$A:$A,$C18,'YC all 900'!$E:$E,"Winter 2026") -> 10 | G18: =COUNTIFS('YC all 900'!$A:$A,$C18,'YC all 900'!$E:$E,"Spring 2026") -> 11 | H18: =COUNTIFS('YC all 900'!$A:$A,$C18,'YC all 900'!$E:$E,"Summer 2026") -> 30 | I18: =COUNTIFS('YC all 900'!$A:$A,$C18,'YC all 900'!$E:$E,"Fall 2026") -> 15 | J18: =SUM(E18:I18) -> 69 | K18: =IF(E$25=0,0,E18/E$25) -> 0.020689655 | L18: =IF(H$25=0,0,H18/H$25) -> 0.13043478
A19: Fintech, trading and markets | B19: Prediction-market tools, trading apps, AI hedge funds, stablecoin payments, insurance for AI risks, cross-border payments. | C19: Fintech and markets | D19: =COUNTA('Fintech and markets'!$B:$B)-1 -> 20 | E19: =COUNTIFS('YC all 900'!$A:$A,$C19,'YC all 900'!$E:$E,"Fall 2025") -> 7 | F19: =COUNTIFS('YC all 900'!$A:$A,$C19,'YC all 900'!$E:$E,"Winter 2026") -> 11 | G19: =COUNTIFS('YC all 900'!$A:$A,$C19,'YC all 900'!$E:$E,"Spring 2026") -> 13 | H19: =COUNTIFS('YC all 900'!$A:$A,$C19,'YC all 900'!$E:$E,"Summer 2026") -> 15 | I19: =COUNTIFS('YC all 900'!$A:$A,$C19,'YC all 900'!$E:$E,"Fall 2026") -> 2 | J19: =SUM(E19:I19) -> 48 | K19: =IF(E$25=0,0,E19/E$25) -> 0.048275862 | L19: =IF(H$25=0,0,H19/H$25) -> 0.065217391
A20: Biotech, drug discovery and AI for science | B20: AI scientists, drug discovery, lab automation, new materials, regulatory paperwork for life sciences. | C20: Bio and science | D20: =COUNTA('Bio and science'!$B:$B)-1 -> 10 | E20: =COUNTIFS('YC all 900'!$A:$A,$C20,'YC all 900'!$E:$E,"Fall 2025") -> 5 | F20: =COUNTIFS('YC all 900'!$A:$A,$C20,'YC all 900'!$E:$E,"Winter 2026") -> 9 | G20: =COUNTIFS('YC all 900'!$A:$A,$C20,'YC all 900'!$E:$E,"Spring 2026") -> 7 | H20: =COUNTIFS('YC all 900'!$A:$A,$C20,'YC all 900'!$E:$E,"Summer 2026") -> 9 | I20: =COUNTIFS('YC all 900'!$A:$A,$C20,'YC all 900'!$E:$E,"Fall 2026") -> 6 | J20: =SUM(E20:I20) -> 36 | K20: =IF(E$25=0,0,E20/E$25) -> 0.034482759 | L20: =IF(H$25=0,0,H20/H$25) -> 0.039130435
A21: Consumer apps and consumer hardware | B21: Apps and gadgets for normal people: learning, games, health coaching, social, shopping, wearables. | C21: Consumer apps | D21: =COUNTA('Consumer apps'!$B:$B)-1 -> 19 | E21: =COUNTIFS('YC all 900'!$A:$A,$C21,'YC all 900'!$E:$E,"Fall 2025") -> 11 | F21: =COUNTIFS('YC all 900'!$A:$A,$C21,'YC all 900'!$E:$E,"Winter 2026") -> 8 | G21: =COUNTIFS('YC all 900'!$A:$A,$C21,'YC all 900'!$E:$E,"Spring 2026") -> 8 | H21: =COUNTIFS('YC all 900'!$A:$A,$C21,'YC all 900'!$E:$E,"Summer 2026") -> 7 | I21: =COUNTIFS('YC all 900'!$A:$A,$C21,'YC all 900'!$E:$E,"Fall 2026") -> 4 | J21: =SUM(E21:I21) -> 38 | K21: =IF(E$25=0,0,E21/E$25) -> 0.075862069 | L21: =IF(H$25=0,0,H21/H$25) -> 0.030434783
A22: Personal AI assistants and AI devices | B22: An AI assistant that does your own work and errands, AI-first browsers and desktops, and new devices (earbuds, glasses, pins, phones) built around AI. | C22: Personal AI | D22: =COUNTA('Personal AI'!$B:$B)-1 -> 12 | E22: =COUNTIFS('YC all 900'!$A:$A,$C22,'YC all 900'!$E:$E,"Fall 2025") -> 3 | F22: =COUNTIFS('YC all 900'!$A:$A,$C22,'YC all 900'!$E:$E,"Winter 2026") -> 5 | G22: =COUNTIFS('YC all 900'!$A:$A,$C22,'YC all 900'!$E:$E,"Spring 2026") -> 7 | H22: =COUNTIFS('YC all 900'!$A:$A,$C22,'YC all 900'!$E:$E,"Summer 2026") -> 3 | I22: =COUNTIFS('YC all 900'!$A:$A,$C22,'YC all 900'!$E:$E,"Fall 2026") -> 7 | J22: =SUM(E22:I22) -> 25 | K22: =IF(E$25=0,0,E22/E$25) -> 0.020689655 | L22: =IF(H$25=0,0,H22/H$25) -> 0.013043478
A23: Creative and media tools | B23: AI video editors, AI film making, design tools, avatars. | C23: Creative tools | D23: =COUNTA('Creative tools'!$B:$B)-1 -> 10 | E23: =COUNTIFS('YC all 900'!$A:$A,$C23,'YC all 900'!$E:$E,"Fall 2025") -> 7 | F23: =COUNTIFS('YC all 900'!$A:$A,$C23,'YC all 900'!$E:$E,"Winter 2026") -> 3 | G23: =COUNTIFS('YC all 900'!$A:$A,$C23,'YC all 900'!$E:$E,"Spring 2026") -> 1 | H23: =COUNTIFS('YC all 900'!$A:$A,$C23,'YC all 900'!$E:$E,"Summer 2026") -> 2 | I23: =COUNTIFS('YC all 900'!$A:$A,$C23,'YC all 900'!$E:$E,"Fall 2026") -> 2 | J23: =SUM(E23:I23) -> 15 | K23: =IF(E$25=0,0,E23/E$25) -> 0.048275862 | L23: =IF(H$25=0,0,H23/H$25) -> 0.0086956522
A24: Other or unclear | B24: Companies with no public description yet. | C24: Other | D24: =COUNTA(Other!$B:$B)-1 -> 0 | E24: =COUNTIFS('YC all 900'!$A:$A,$C24,'YC all 900'!$E:$E,"Fall 2025") -> 1 | F24: =COUNTIFS('YC all 900'!$A:$A,$C24,'YC all 900'!$E:$E,"Winter 2026") -> 1 | G24: =COUNTIFS('YC all 900'!$A:$A,$C24,'YC all 900'!$E:$E,"Spring 2026") -> 1 | H24: =COUNTIFS('YC all 900'!$A:$A,$C24,'YC all 900'!$E:$E,"Summer 2026") -> 0 | I24: =COUNTIFS('YC all 900'!$A:$A,$C24,'YC all 900'!$E:$E,"Fall 2026") -> 0 | J24: =SUM(E24:I24) -> 3 | K24: =IF(E$25=0,0,E24/E$25) -> 0.0068965517 | L24: =IF(H$25=0,0,H24/H$25) -> 0
A25: Total | D25: =SUM(D2:D24) -> 374 | E25: =SUM(E2:E24) -> 145 | F25: =SUM(F2:F24) -> 198 | G25: =SUM(G2:G24) -> 193 | H25: =SUM(H2:H24) -> 230 | I25: =SUM(I2:I24) -> 134 | J25: =SUM(J2:J24) -> 900
A27: YC counts are formulas over the 'YC all 900' tab (source: yc-oss.github.io/api, read 2026-10-13). Themes were assigned by hand from each company's description; see data/yc_bracket_assignments.csv.

Sheet Incubators
A1: Program | B1: Type | C1: Based in | D1: Can founders in India apply? | E1: Money | F1: Equity taken | G1: Stage and who they want | H1: Format | I1: Student friendly? | J1: Timing / next date | K1: Notes | L1: Source | M1: Confidence
A2: Y Combinator | B2: Accelerator | C2: San Francisco, USA | D2: Yes. Any country can apply. If accepted, the company needs a parent company in the US, Canada, Singapore or Cayman Islands. | E2: $500K | F2: 7% for the first $125K; the other $375K is an uncapped SAFE that converts at the terms of your next round | G2: Any stage, idea to revenue. Wants a founding team and an idea. Non-technical teams need a technical co-founder. | H2: 3 months in person in San Francisco. Four batches a year (Winter, Spring, Summer, Fall). | I2: Yes. Students can apply and can ask to join a batch after they graduate (Early Decision). Founders must work full-time during the batch. | J2: Winter 2027 deadline reported as 2026-11-02, 8pm PT, decisions by 2026-12-11. Confirm on ycombinator.com/apply. | K2: Only 9 of the last 900 YC companies are based in India, while a community estimate says about 20% of Summer 2026 founders are of Indian origin. Most Indian founders in YC run US-based companies. | L2: https://www.ycombinator.com/deal ; https://www.ycombinator.com/faq | M2: high
A3: a16z Speedrun | B3: Accelerator | C3: San Francisco, USA | D3: Not stated in the sources read. The program is in person in San Francisco. | E3: Up to $1M | F3: 10% for the first $500K; a further $500K goes into your next round within 18 months | G3: Pre-seed. Very selective, under 1% accepted (one source: 19,000 applicants for SR006). | H3: About 11 weeks in San Francisco. Two cohorts a year, roughly 50 to 80 startups each. | I3: Not stated. | J3: SR008 runs late January to April 2027. Application dates not found yet. | K3: No board seat. Money is wired on acceptance. Over $5M in partner credits. | L3: https://foundedceo.substack.com/p/a16z-speedruns-sr007-demo-day-is ; https://www.frontrun.vc/blog/a16z-speedrun-cohort-007-companies/ | M3: medium
A4: South Park Commons Founder Fellowship | B4: Fellowship | C4: San Francisco, New York and Bengaluru | D4: Yes. Bengaluru is one of the three bootcamp locations. | E4: Up to $1M | F4: 7% for $400K up front; a further $600K is guaranteed in your next outside-led round | G4: Very early. You do not need an idea to apply. Strong preference for people who can build the product themselves. | H4: 8-week in-person bootcamp. No demo day. | I4: Not stated. | J4: Fall 2026 applications closed 2026-08-02. Next cycle not announced. | K4: A good fit for "we have skills but are still choosing the idea". The size of the India fund is not confirmed. | L4: https://x.com/southpkcommons/status/2074942309599224190 ; https://www.southparkcommons.com/faq | M4: medium
A5: Antler India | B5: Residency + direct investment | C5: Bengaluru, India | D5: Yes, it is the India program. | E5: Up to ₹4 crore (about $425K-$470K) | F5: 11% | G5: Pre-launch, pre-product or pre-revenue teams working full-time. Focus on AI-first startups. | H5: 3-week AI Residency, first 2 weeks in person in Bengaluru, with a one-time ₹2 lakh expense grant. About half of Antler India's investments happen outside the residency. | I5: Not stated. Requires full-time commitment. | J5: Next residency "to be announced soon" (page read 2026-10-13). | K5: Funding decision in 3 weeks. The page claims 50-75% of residency teams get funded. | L5: https://www.antler.co/india | M5: high
A6: Entrepreneur First | B6: Talent investor | C6: London; cohorts in Bangalore and other cities | D6: Yes, runs a Bangalore cohort. | E6: Not confirmed. A 2026 guide says $250K on the US pathway; older Bangalore reports say about $55K plus a monthly stipend. | F6: US pathway reported as 8% for $125K plus a $125K uncapped SAFE. Bangalore terms not confirmed. | G6: Individuals. You join before you have a co-founder or an idea. | H6: Cohort program in Bangalore. | I6: Not stated. | J6: Bangalore Winter 2027: early deadline was 2026-10-05; start reported as January or February 2027. | K6: EF also took part in the $1M pre-seed of ByteAsk (two IIT Delhi graduates, YC Fall 2026). Check terms on EF's own site. | L6: https://hub.causo.ai/guides/how-to-apply-to-entrepreneur-first-2026 | M6: low
A7: Peak XV Surge | B7: Seed program | C7: India and Southeast Asia | D7: Yes. The cohort mixes India-based companies and companies abroad. | E7: Up to $5M per startup (raised from $3M with Surge 12) | F7: Not disclosed | G7: Seed, larger than pre-seed. Most Surge 12 companies had already raised money. | H7: Cohort program. Surge 12 had 18 startups. | I7: Not stated. | J7: Surge 12 was announced 2026-09-28/29. | K7: Peak XV says it put over $50M into Surge 12. Better as a second step than a first cheque. | L7: https://inc42.com/buzz/meet-the-startups-from-peak-xvs-surge-12/ | M7: medium
A8: Accel Atoms (AI Cohort, with Google AI Futures Fund) | B8: Pre-seed program | C8: India | D8: Yes. Built for Indian and Indian-origin founders building AI startups anywhere. | E8: Up to $2M co-investment plus up to $350K compute credits | F8: Not disclosed | G8: Pre-seed AI-first startups. | H8: 3 months, starts in Bengaluru, ends with a visit to Mountain View. | I8: Not stated. | J8: 2026 cohort ran March to June 2026. 5 startups chosen from 4,000+ applicants. Applications currently closed. | K8: Sources disagree on whether $2M is per investor or total. About 0.1% acceptance. | L8: https://www.outlookbusiness.com/deeptech/five-startups-to-join-accel-atoms-and-googles-ai-futures-fund-ai-cohort-2026 | M8: medium
A9: 100X.VC | B9: Pre-seed fund with classes | C9: Mumbai, India | D9: Yes. | E9: ₹1.25 crore | F9: 15% through an iSAFE note | G9: Early-stage Indian startups. | H9: Two classes a year, about 15-22 startups each, ending in a pitch day. | I9: Not stated. | J9: Latest class found: Class 12, early 2025 (18 startups, $2.7M). No 2026 class found yet. | K9: The ₹1.25 crore for 15% terms are from 2022-2023 reports. Confirm on 100x.vc. | L9: https://yourstory.com/2025/01/100xvc-invests-27m-18-startups-12th-cohort | M9: medium
A10: AJVC | B10: Pre-seed fund | C10: India | D10: Yes. | E10: ₹1.5 crore (about $180K) | F10: 9%. The same terms for every startup. | G10: Pre-seed, any sector. | H10: Direct investment, not a cohort. About 12-15 startups a year. | I10: Not stated. | J10: Rolling. | K10: Fixed terms mean no negotiation. Reported to have backed 35+ companies by September 2026. | L10: https://india.entrepreneur.com/news-and-trends/aviral-bhatnagars-ajvc-closes-inr-100-cr-fund-to-back/487821 | M10: medium
A11: All In Capital | B11: Pre-seed and seed fund | C11: Mumbai and Bengaluru, India | D11: Yes. | E11: $100K to $300K | F11: Not disclosed | G11: Pre-seed and seed. | H11: Direct investment. | I11: Not stated. | J11: Rolling. Fund II of ₹200 crore launched. | K11: Fund I put $11M into 51 startups. | L11: https://india.entrepreneur.com/news-and-trends/all-in-capital-launches-inr-200-cr-fund-ii-eyes-inr-300-cr/488785 | M11: medium
A12: Campus Fund | B12: Student-focused VC | C12: India | D12: Yes. | E12: ₹1 crore to ₹8 crore first cheque | F12: Not disclosed | G12: Startups founded by students, recent graduates and dropouts. | H12: Direct investment. "Build In India" sets aside up to $10M for first pre-seed cheques. | I12: Yes. This is the whole point of the fund. | J12: Rolling. Plans 60-80 startups over four years from a $100M fund. | K12: Portfolio leans deep tech, space and climate (Digantara, EtherealX). | L12: https://india.entrepreneur.com/?p=99916 | M12: medium
... A23: FITT, IIT Delhi (with government schemes NIDHI and Startup India Seed Fund) | B23: University incubator | C23: New Delhi, India | D23: Yes. | E23: Not verified. One aggregator shows ₹25 lakh to ₹1 crore for one FITT program. | F23: Not verified | G23: Technology startups, often linked to IIT Delhi. | H23: Incubation at IIT Delhi. | I23: Yes. Akshit can ask FITT directly. | J23: Not found. | K23: Open question: get exact scheme amounts and eligibility from FITT. | L23: https://www.startupgrantsindia.com/providers/fitt-iit-delhi/government-funding-schemes-fitt-implements | M23: low

Sheet AI service firms
A1: Idea in simple words | B1: Startup | C1: Funded by | D1: Batch / cohort | E1: Funding | F1: What the funding number means | G1: Based in | H1: India / USA / Other | I1: Indian founders? | J1: Website | K1: Source | L1: Confidence
A2: A customs broker (the firm that clears imported goods at the border) that runs mostly on AI. | B2: Alchemize | C2: Y Combinator | D2: YC Spring 2026 | E2: $500K | F2: standard YC deal ($125K for 7% + $375K uncapped SAFE); the startup's own round is not public | G2: San Francisco, CA, USA | H2: USA | I2: unknown | J2: https://tryalchemize.com | K2: https://www.ycombinator.com/companies/alchemize | L2: high
A3: A debt collection company where AI, not call-centre staff, contacts people who owe money. | B3: Audun | C3: Y Combinator | D3: YC Summer 2026 | E3: $500K | F3: standard YC deal ($125K for 7% + $375K uncapped SAFE); the startup's own round is not public | G3: Oslo, Oslo, Norway | H3: Other | I3: unknown | J3: https://audun.co | K3: https://www.ycombinator.com/companies/audun | L3: high
A4: An accounting firm that does a client's books with AI and wants to undercut the big accounting firms. | B4: Billow AI Labs | C4: Y Combinator | D4: YC Summer 2026 | E4: $500K | F4: standard YC deal ($125K for 7% + $375K uncapped SAFE); the startup's own round is not public | G4: San Francisco, CA, USA | H4: USA | I4: unknown | J4: https://thebillow.ai/ | K4: https://www.ycombinator.com/companies/billow-ai-labs | L4: high
A5: An insurance broker for businesses where AI does most of the paperwork a human broker would do. | B5: Casey | C5: Y Combinator | D5: YC Fall 2025 | E5: $500K | F5: standard YC deal ($125K for 7% + $375K uncapped SAFE); the startup's own round is not public | G5: San Francisco, CA, USA | H5: USA | I5: unknown | J5: https://caseyinsure.com/ | K5: https://www.ycombinator.com/companies/casey | L5: high
A6: An audit firm that checks a company's financial accounts using AI instead of big teams of junior auditors. | B6: Denki | C6: Y Combinator | D6: YC Fall 2025 | E6: $500K | F6: standard YC deal ($125K for 7% + $375K uncapped SAFE); the startup's own round is not public | G6: San Francisco, CA, USA | H6: USA | I6: unknown | J6: https://denki.ai | K6: https://www.ycombinator.com/companies/denki | L6: high
A7: An insurance company with no human underwriters. AI decides the risk and the price. | B7: Florin | C7: Y Combinator | D7: YC Summer 2026 | E7: $500K | F7: standard YC deal ($125K for 7% + $375K uncapped SAFE); the startup's own round is not public | G7: San Francisco, CA, USA | H7: USA | I7: reported | J7: https://florin.inc | K7: https://www.ycombinator.com/companies/florin | L7: high
A8: A law firm for fast-growing startups where AI drafts the legal work and lawyers review it. | B8: General Legal | C8: Y Combinator | D8: YC Winter 2026 | E8: $500K | F8: standard YC deal ($125K for 7% + $375K uncapped SAFE); the startup's own round is not public | G8: not stated | H8: Other | I8: unknown | J8: https://general.legal | K8: https://www.ycombinator.com/companies/general-legal | L8: high
A9: A firm that runs clinical trials for drug companies and uses AI for the day-to-day trial operations. | B9: Harbor | C9: Y Combinator | D9: YC Spring 2026 | E9: $500K | F9: standard YC deal ($125K for 7% + $375K uncapped SAFE); the startup's own round is not public | G9: San Francisco, CA, USA | H9: USA | I9: unknown | J9: https://runharbor.com/ | K9: https://www.ycombinator.com/companies/runharbor | L9: high
A10: An immigration law firm that uses AI to prepare visa applications faster. | B10: LegalOS | C10: Y Combinator | D10: YC Winter 2026 | E10: $500K | F10: standard YC deal ($125K for 7% + $375K uncapped SAFE); the startup's own round is not public | G10: San Francisco, CA, USA; Remote | H10: USA | I10: unknown | J10: https://www.legalos.ai | K10: https://www.ycombinator.com/companies/legalos | L10: high
A11: An engineering firm that designs data centers and uses AI to do the design work faster. | B11: Marengo | C11: Y Combinator | D11: YC Summer 2026 | E11: $500K | F11: standard YC deal ($125K for 7% + $375K uncapped SAFE); the startup's own round is not public | G11: San Francisco, CA, USA | H11: USA | I11: unknown | J11: https://marengox.com | K11: https://www.ycombinator.com/companies/marengo | L11: high
A12: A freight broker (it matches companies that ship goods with trucks) run by AI. | B12: Peer | C12: Y Combinator | D12: YC Summer 2026 | E12: $500K | F12: standard YC deal ($125K for 7% + $375K uncapped SAFE); the startup's own round is not public | G12: San Francisco, CA, USA | H12: USA | I12: unknown | J12: https://peer-freight.com | K12: https://www.ycombinator.com/companies/peer | L12: high
... A16: An outsourcing firm for banks and finance companies where AI agents operate the computer screens instead of people. | B16: Zomma | C16: Y Combinator | D16: YC Summer 2026 | E16: $500K | F16: standard YC deal ($125K for 7% + $375K uncapped SAFE); the startup's own round is not public | G16: San Francisco, CA, USA | H16: USA | I16: reported | J16: https://zommalabs.com | K16: https://www.ycombinator.com/companies/zomma | L16: high
A17: AI-run home insurance for areas with high climate risk. | B17: Rhino | C17: Antler US | D17: US Spring 2026 Showcase | E17: not disclosed | F17: taken from a third-party list that was not verified against Antler | G17: USA | H17: USA | I17: unknown | K17: https://agentjesse.ai/lists/antler-2026-cohort-companies | L17: low
A18: A tech-enabled insurance broker for small and mid-sized US businesses. | B18: Rosella | C18: Peak XV Surge | D18: Surge 12 (Sep 2026) | E18: $3.7M | F18: Surge invests up to $5M per startup; the figure shown is funding as listed by Inc42, the Surge share is not disclosed | G18: Sydney, Australia | H18: Other | I18: unknown | K18: https://inc42.com/buzz/meet-the-startups-from-peak-xvs-surge-12/ | L18: medium
A19: An AI-built law firm for mergers and commercial real estate deals. | B19: Athena | C19: a16z Speedrun | D19: SR007 (Jul-Oct 2026) | E19: up to $1M | F19: standard Speedrun deal: $500K for 10% now + $500K in the next round | G19: not stated (program runs in San Francisco) | H19: Unknown | I19: unknown | K19: https://www.frontrun.vc/blog/a16z-speedrun-cohort-007-companies/ | L19: medium

Sheet Old-industry AI
A1: Idea in simple words | B1: Startup | C1: Funded by | D1: Batch / cohort | E1: Funding | F1: What the funding number means | G1: Based in | H1: India / USA / Other | I1: Indian founders? | J1: Website | K1: Source | L1: Confidence
A2: Turns the text-message orders that food distributors get into entries in their order system automatically. | B2: Asakana | C2: Y Combinator | D2: YC Fall 2026 | E2: $500K | F2: standard YC deal ($125K for 7% + $375K uncapped SAFE); the startup's own round is not public | G2: San Francisco, CA, USA | H2: USA | I2: unknown | J2: https://www.asakana.co/ | K2: https://www.ycombinator.com/companies/asakana | L2: high
A3: AI employees that take calls, book visits and send technicians for appliance repair companies. | B3: Bernard | C3: Y Combinator | D3: YC Summer 2026 | E3: $500K | F3: standard YC deal ($125K for 7% + $375K uncapped SAFE); the startup's own round is not public | G3: New York City, NY, USA | H3: USA | I3: unknown | J3: https://bernardhq.com/ | K3: https://www.ycombinator.com/companies/bernard | L3: high
A4: AI that reads building drawings and counts the materials, so electrical contractors can price a job quickly. | B4: Bidflow | C4: Y Combinator | D4: YC Winter 2026 | E4: $500K | F4: standard YC deal ($125K for 7% + $375K uncapped SAFE); the startup's own round is not public | G4: New York City, NY, USA | H4: USA | I4: unknown | J4: https://usebidflow.com | K4: https://www.ycombinator.com/companies/bidflow | L4: high
A5: An AI property manager that handles tenants and maintenance for landlords. | B5: Brickwise | C5: Y Combinator | D5: YC Fall 2025 | E5: $500K | F5: standard YC deal ($125K for 7% + $375K uncapped SAFE); the startup's own round is not public | G5: London, England, United Kingdom | H5: Other | I5: unknown | J5: https://www.brickwiseai.com | K5: https://www.ycombinator.com/companies/brickwise | L5: high
A6: AI that answers booking calls and emails for hotel groups. | B6: Codyco | C6: Y Combinator | D6: YC Fall 2025 | E6: $500K | F6: standard YC deal ($125K for 7% + $375K uncapped SAFE); the startup's own round is not public | G6: BY, Germany | H6: Other | I6: unknown | J6: https://www.codyco.ai/en | K6: https://www.ycombinator.com/companies/codyco | L6: high
A7: AI that plans the daily schedule for short-distance trucks. | B7: Dayjob | C7: Y Combinator | D7: YC Spring 2026 | E7: $500K | F7: standard YC deal ($125K for 7% + $375K uncapped SAFE); the startup's own round is not public | G7: London, England, United Kingdom | H7: Other | I7: unknown | J7: https://www.getdayjob.ai | K7: https://www.ycombinator.com/companies/dayjob | L7: high
A8: AI that takes table reservations for restaurants by phone and chat. | B8: Elyra | C8: Y Combinator | D8: YC Spring 2026 | E8: $500K | F8: standard YC deal ($125K for 7% + $375K uncapped SAFE); the startup's own round is not public | G8: Stockholm, Stockholm County, Sweden | H8: Other | I8: unknown | J8: https://www.elyrasystems.com/ | K8: https://www.ycombinator.com/companies/elyra | L8: high
A9: One system with AI that runs a restaurant's kitchen-side admin: ordering stock, tracking inventory, cutting waste. | B9: Marble | C9: Y Combinator | D9: YC Summer 2026 | E9: $500K | F9: standard YC deal ($125K for 7% + $375K uncapped SAFE); the startup's own round is not public | G9: New York City, NY, USA | H9: USA | I9: reported | J9: https://joinmarble.ai/ | K9: https://www.ycombinator.com/companies/joinmarble | L9: high
A10: AI software that runs the paperwork and deals of real-estate brokerages. | B10: RealPact | C10: Y Combinator | D10: YC Summer 2026 | E10: $500K | F10: standard YC deal ($125K for 7% + $375K uncapped SAFE); the startup's own round is not public | G10: San Francisco, CA, USA | H10: USA | I10: reported | J10: https://realpact.ai | K10: https://www.ycombinator.com/companies/realpact | L10: high
A11: AI agents that answer calls and win more jobs for home-service businesses such as plumbers and electricians. | B11: Robby | C11: Y Combinator | D11: YC Winter 2026 | E11: $500K | F11: standard YC deal ($125K for 7% + $375K uncapped SAFE); the startup's own round is not public | G11: New York City, NY, USA | H11: USA | I11: unknown | J11: https://tryrobby.com | K11: https://www.ycombinator.com/companies/robby | L11: high
A12: Uses a restaurant's existing CCTV cameras to watch operations and alert managers in real time. | B12: Shire Intelligence | C12: Y Combinator | D12: YC Fall 2026 | E12: $500K | F12: standard YC deal ($125K for 7% + $375K uncapped SAFE); the startup's own round is not public | G12: Myrtle Beach, SC, USA | H12: USA | I12: unknown | J12: https://shireintelligence.com/ | K12: https://www.ycombinator.com/companies/shire-intelligence | L12: high
A13: AI software that runs daily operations for wholesale distributors. | B13: Whitespace | C13: Y Combinator | D13: YC Summer 2026 | E13: $500K | F13: standard YC deal ($125K for 7% + $375K uncapped SAFE); the startup's own round is not public | G13: San Francisco, CA, USA | H13: USA | I13: unknown | J13: https://whitespacehq.ai/ | K13: https://www.ycombinator.com/companies/whitespace | L13: high
A14: An electric-vehicle fleet platform for ride-hailing drivers. | B14: Milo Drive | C14: Antler India | D14: Portfolio shown on antler.co/india (read 2026-10-13) | E14: up to ₹4 crore (~$425K-$470K) | F14: standard Antler India deal for 11%; amount per startup not disclosed | G14: India | H14: India | I14: yes | K14: https://www.antler.co/india | L14: high
A15: A marketplace that connects kirana stores with nearby distributors for same-day delivery. | B15: Tradeface | C15: Antler India | D15: Portfolio shown on antler.co/india (read 2026-10-13) | E15: up to ₹4 crore (~$425K-$470K) | F15: standard Antler India deal for 11%; amount per startup not disclosed | G15: India | H15: India | I15: yes | K15: https://www.antler.co/india | L15: high
A16: An AI voice agent that answers hotel calls and turns them into bookings. | B16: withQ | C16: Antler US | D16: US Spring 2026 Showcase | E16: not disclosed | F16: taken from a third-party list that was not verified against Antler | G16: USA | H16: USA | I16: unknown | K16: https://agentjesse.ai/lists/antler-2026-cohort-companies | L16: low
A17: An AI employee that does property management work. | B17: Alven | C17: a16z Speedrun | D17: SR007 (Jul-Oct 2026) | E17: up to $1M | F17: standard Speedrun deal: $500K for 10% now + $500K in the next round | G17: not stated (program runs in San Francisco) | H17: Unknown | I17: unknown | K17: https://www.frontrun.vc/blog/a16z-speedrun-cohort-007-companies/ | L17: medium
A18: AI agents for companies that handle hazardous waste. | B18: Colmez | C18: a16z Speedrun | D18: SR007 (Jul-Oct 2026) | E18: up to $1M | F18: standard Speedrun deal: $500K for 10% now + $500K in the next round | G18: not stated (program runs in San Francisco) | H18: Unknown | I18: unknown | K18: https://www.frontrun.vc/blog/a16z-speedrun-cohort-007-companies/ | L18: medium
A19: AI software for the daily work of freight forwarders. | B19: Nimble | C19: a16z Speedrun | D19: SR007 (Jul-Oct 2026) | E19: up to $1M | F19: standard Speedrun deal: $500K for 10% now + $500K in the next round | G19: not stated (program runs in San Francisco) | H19: Unknown | I19: unknown | K19: https://www.frontrun.vc/blog/a16z-speedrun-cohort-007-companies/ | L19: medium
A20: AI that does the pre-construction and land-buying work for home builders. | B20: Parca | C20: a16z Speedrun | D20: SR007 (Jul-Oct 2026) | E20: up to $1M | F20: standard Speedrun deal: $500K for 10% now + $500K in the next round | G20: not stated (program runs in San Francisco) | H20: Unknown | I20: unknown | K20: https://www.frontrun.vc/blog/a16z-speedrun-cohort-007-companies/ | L20: medium
A21: An operating system for freight forwarders. | B21: Rumbo | C21: a16z Speedrun | D21: SR007 (Jul-Oct 2026) | E21: up to $1M | F21: standard Speedrun deal: $500K for 10% now + $500K in the next round | G21: not stated (program runs in San Francisco) | H21: Unknown | I21: unknown | K21: https://www.frontrun.vc/blog/a16z-speedrun-cohort-007-companies/ | L21: medium
A22: AI crews for messy supply-chain operations. | B22: Sotant | C22: a16z Speedrun | D22: SR007 (Jul-Oct 2026) | E22: up to $1M | F22: standard Speedrun deal: $500K for 10% now + $500K in the next round | G22: not stated (program runs in San Francisco) | H22: Unknown | I22: unknown | K22: https://www.frontrun.vc/blog/a16z-speedrun-cohort-007-companies/ | L22: medium

Sheet Finance back-office
A1: Idea in simple words | B1: Startup | C1: Funded by | D1: Batch / cohort | E1: Funding | F1: What the funding number means | G1: Based in | H1: India / USA / Other | I1: Indian founders? | J1: Website | K1: Source | L1: Confidence
A2: AI employees that chase unpaid customer invoices for a company's finance team. | B2: Alder | C2: Y Combinator | D2: YC Fall 2025 | E2: $500K | F2: standard YC deal ($125K for 7% + $375K uncapped SAFE); the startup's own round is not public | G2: San Francisco, CA, USA | H2: USA | I2: unknown | J2: https://meetalder.com/ | K2: https://www.ycombinator.com/companies/alder | L2: high
A3: AI clerks that process the bills a company has to pay. | B3: Clerked | C3: Y Combinator | D3: YC Fall 2025 | E3: $500K | F3: standard YC deal ($125K for 7% + $375K uncapped SAFE); the startup's own round is not public | G3: San Francisco, CA, USA | H3: USA | I3: unknown | J3: https://clerked.ai | K3: https://www.ycombinator.com/companies/clerked | L3: high
A4: AI that processes home-loan applications from start to finish. | B4: Copperlane | C4: Y Combinator | D4: YC Winter 2026 | E4: $500K | F4: standard YC deal ($125K for 7% + $375K uncapped SAFE); the startup's own round is not public | G4: San Francisco, CA, USA | H4: USA | I4: unknown | J4: https://www.copperlane.ai | K4: https://www.ycombinator.com/companies/copperlane | L4: high
A5: AI that prepares tax returns and does bookkeeping for accounting firms. | B5: Cranston AI | C5: Y Combinator | D5: YC Fall 2025 | E5: $500K | F5: standard YC deal ($125K for 7% + $375K uncapped SAFE); the startup's own round is not public | G5: San Francisco, CA, USA | H5: USA | I5: unknown | J5: https://www.cranston.ai | K5: https://www.ycombinator.com/companies/cranston-ai | L5: high
A6: An AI assistant inside Excel for finance analysts who build heavy spreadsheets. | B6: Crunched | C6: Y Combinator | D6: YC Fall 2025 | E6: $500K | F6: standard YC deal ($125K for 7% + $375K uncapped SAFE); the startup's own round is not public | G6: Oslo, Oslo, Norway | H6: Other | I6: unknown | J6: https://usecrunched.com/ | K6: https://www.ycombinator.com/companies/crunched | L6: high
A7: AI that matches payment records for companies that process a very large number of payments. | B7: End Close | C7: Y Combinator | D7: YC Winter 2026 | E7: $500K | F7: standard YC deal ($125K for 7% + $375K uncapped SAFE); the startup's own round is not public | G7: not stated | H7: Other | I7: unknown | J7: https://endclose.com | K7: https://www.ycombinator.com/companies/end-close | L7: high
A8: AI that investigates insurance claims to catch fraud and errors. | B8: Hesper AI | C8: Y Combinator | D8: YC Fall 2026 | E8: $500K | F8: standard YC deal ($125K for 7% + $375K uncapped SAFE); the startup's own round is not public | G8: New York City, NY, USA | H8: USA | I8: unknown | J8: https://gethesperai.com | K8: https://www.ycombinator.com/companies/hesper-ai | L8: high
A9: Reads a borrower's documents (bank statements, bills, e-wallet records) so lenders in emerging markets can approve loans in minutes. | B9: Kita | C9: Y Combinator | D9: YC Winter 2026 | E9: $500K | F9: standard YC deal ($125K for 7% + $375K uncapped SAFE); the startup's own round is not public | G9: San Francisco, CA, USA | H9: USA | I9: unknown | J9: https://www.kita.ai/ | K9: https://www.ycombinator.com/companies/kita | L9: high
A10: An AI platform that credit funds use to analyse and track loans. Reports about $1B of receivables on the platform. | B10: Levocred AI | C10: Y Combinator | D10: YC Summer 2026 | E10: $500K | F10: standard YC deal ($125K for 7% + $375K uncapped SAFE); the startup's own round is not public | G10: San Francisco, CA, USA | H10: USA | I10: yes | J10: https://levocred.com/ | K10: https://www.ycombinator.com/companies/levocred-ai | L10: high
A11: AI that does the checking work of a company's internal audit team. | B11: Oxus | C11: Y Combinator | D11: YC Winter 2026 | E11: $500K | F11: standard YC deal ($125K for 7% + $375K uncapped SAFE); the startup's own round is not public | G11: San Francisco, CA, USA | H11: USA | I11: unknown | J11: https://oxus-ai.com/ | K11: https://www.ycombinator.com/companies/oxus | L11: high
A12: AI that does the back-office work of banks and fintech companies. | B12: Rapidfolio | C12: Y Combinator | D12: YC Summer 2026 | E12: $500K | F12: standard YC deal ($125K for 7% + $375K uncapped SAFE); the startup's own round is not public | G12: San Francisco, CA, USA | H12: USA | I12: reported | J12: https://rapidfolio.com/ | K12: https://www.ycombinator.com/companies/rapidfolio | L12: high
A13: AI junior analysts for private equity firms that buy mid-sized companies. | B13: Zarna | C13: Y Combinator | D13: YC Fall 2025 | E13: $500K | F13: standard YC deal ($125K for 7% + $375K uncapped SAFE); the startup's own round is not public | G13: San Francisco, CA, USA | H13: USA | I13: unknown | J13: https://www.zarnaai.com/ | K13: https://www.ycombinator.com/companies/zarna | L13: high
A14: AI that helps property insurers assess risk. | B14: VelociSure | C14: Antler US | D14: US Spring 2026 Showcase | E14: not disclosed | F14: taken from a third-party list that was not verified against Antler | G14: USA | H14: USA | I14: unknown | K14: https://agentjesse.ai/lists/antler-2026-cohort-companies | L14: low
A15: AI that does due-diligence and financial research for companies and investors. | B15: Binocs | C15: Google for Startups Accelerator: India | D15: 2026 cohort (announced 2026-07-08) | E15: no cash | F15: equity-free 3-month program with mentoring and credits; most companies here already have a product and earlier funding | G15: Bengaluru, India | H15: India | I15: yes | K15: https://inc42.com/buzz/meet-the-20-startups-selected-for-googles-india-startup-accelerator-2026/ | L15: medium
A16: AI agents that do compliance, risk and audit work for financial institutions. | B16: OnFinanceAI | C16: Google for Startups Accelerator: India | D16: 2026 cohort (announced 2026-07-08) | E16: no cash | F16: equity-free 3-month program with mentoring and credits; most companies here already have a product and earlier funding | G16: Bengaluru, India | H16: India | I16: yes | K16: https://inc42.com/buzz/meet-the-20-startups-selected-for-googles-india-startup-accelerator-2026/ | L16: medium
A17: Tools that verify identity and income and automate onboarding checks. | B17: TartanHQ | C17: Google for Startups Accelerator: India | D17: 2026 cohort (announced 2026-07-08) | E17: no cash | F17: equity-free 3-month program with mentoring and credits; most companies here already have a product and earlier funding | G17: Delhi NCR, India | H17: India | I17: yes | K17: https://inc42.com/buzz/meet-the-20-startups-selected-for-googles-india-startup-accelerator-2026/ | L17: medium
A18: Loan processing for commercial real estate that runs by itself. | B18: Corlen | C18: a16z Speedrun | D18: SR007 (Jul-Oct 2026) | E18: up to $1M | F18: standard Speedrun deal: $500K for 10% now + $500K in the next round | G18: not stated (program runs in San Francisco) | H18: Unknown | I18: unknown | K18: https://www.frontrun.vc/blog/a16z-speedrun-cohort-007-companies/ | L18: medium
A19: Turns unpaid customer invoices into cash for service businesses. | B19: Ontem | C19: a16z Speedrun | D19: SR007 (Jul-Oct 2026) | E19: up to $1M | F19: standard Speedrun deal: $500K for 10% now + $500K in the next round | G19: not stated (program runs in San Francisco) | H19: Unknown | I19: unknown | K19: https://www.frontrun.vc/blog/a16z-speedrun-cohort-007-companies/ | L19: medium

Sheet Healthcare AI
A1: Idea in simple words | B1: Startup | C1: Funded by | D1: Batch / cohort | E1: Funding | F1: What the funding number means | G1: Based in | H1: India / USA / Other | I1: Indian founders? | J1: Website | K1: Source | L1: Confidence
A2: Small MRI machines that fit on a truck, so mobile clinics can offer cancer screening for about $250 a scan. | B2: Adialante | C2: Y Combinator | D2: YC Spring 2026 | E2: $500K | F2: standard YC deal ($125K for 7% + $375K uncapped SAFE); the startup's own round is not public | G2: San Francisco, CA, USA | H2: USA | I2: unknown | J2: http://www.adialante.com | K2: https://www.ycombinator.com/companies/adialante | L2: high
A3: Automates how health insurance companies process claims. | B3: Amera | C3: Y Combinator | D3: YC Fall 2025 | E3: $500K | F3: standard YC deal ($125K for 7% + $375K uncapped SAFE); the startup's own round is not public | G3: New York City, NY, USA | H3: USA | I3: unknown | J3: https://amerahealthsolutions.com/ | K3: https://www.ycombinator.com/companies/amera | L3: high
A4: Software that helps nursing homes track and understand their residents' clinical condition. | B4: Ascenix | C4: Y Combinator | D4: YC Fall 2026 | E4: $500K | F4: standard YC deal ($125K for 7% + $375K uncapped SAFE); the startup's own round is not public | G4: Toronto, ON, Canada | H4: Other | I4: unknown | J4: https://www.ascenix.co/ | K4: https://www.ycombinator.com/companies/ascenix | L4: high
A5: AI that fills in insurance pre-approval requests for small medical practices. | B5: ClaimGlide | C5: Y Combinator | D5: YC Winter 2026 | E5: $500K | F5: standard YC deal ($125K for 7% + $375K uncapped SAFE); the startup's own round is not public | G5: Seattle, WA, USA | H5: USA | I5: unknown | J5: https://claimglide.com/ | K5: https://www.ycombinator.com/companies/claimglide | L5: high
A6: AI voice agents that answer every patient call for a clinic and finish the task (booking, refills, billing) in the clinic's records system. | B6: Elite | C6: Y Combinator | D6: YC Summer 2026 | E6: $500K | F6: standard YC deal ($125K for 7% + $375K uncapped SAFE); the startup's own round is not public | G6: New York City, NY, USA | H6: USA | I6: reported | J6: https://elitehq.ai/ | K6: https://www.ycombinator.com/companies/elite | L6: high
A7: AI search over medical records. Reports seven-figure revenue in its first year. | B7: Hubble | C7: Y Combinator | D7: YC Summer 2026 | E7: $500K | F7: standard YC deal ($125K for 7% + $375K uncapped SAFE); the startup's own round is not public | G7: Seattle, WA, USA | H7: USA | I7: reported | J7: https://hubble.ai/ | K7: https://www.ycombinator.com/companies/hubble-ai | L7: high
A8: A cheap 3D ultrasound device that people without specialist training can use. | B8: Lumius | C8: Y Combinator | D8: YC Spring 2026 | E8: $500K | F8: standard YC deal ($125K for 7% + $375K uncapped SAFE); the startup's own round is not public | G8: Durham, NC, USA | H8: USA | I8: unknown | J8: https://www.lumius-imaging.com | K8: https://www.ycombinator.com/companies/lumius | L8: high
A9: AI that phones insurance companies on behalf of hospital billing teams. | B9: LunaBill | C9: Y Combinator | D9: YC Fall 2025 | E9: $500K | F9: standard YC deal ($125K for 7% + $375K uncapped SAFE); the startup's own round is not public | G9: San Francisco, CA, USA | H9: USA | I9: unknown | J9: https://lunabill.com/ | K9: https://www.ycombinator.com/companies/lunabill | L9: high
A10: An AI receptionist and back office for dental clinics. | B10: Patientdesk.ai | C10: Y Combinator | D10: YC Winter 2026 | E10: $500K | F10: standard YC deal ($125K for 7% + $375K uncapped SAFE); the startup's own round is not public | G10: not stated | H10: Other | I10: unknown | J10: https://patientdesk.ai/ | K10: https://www.ycombinator.com/companies/patientdeskai | L10: high
A11: An AI primary-care doctor in a phone app. | B11: Prana | C11: Y Combinator | D11: YC Winter 2026 | E11: $500K | F11: standard YC deal ($125K for 7% + $375K uncapped SAFE); the startup's own round is not public | G11: San Francisco, CA, USA | H11: USA | I11: unknown | J11: https://pranadoc.com | K11: https://www.ycombinator.com/companies/prana-health | L11: high
A12: AI agents that handle calls and routine work for pharmacies. | B12: Remedy | C12: Y Combinator | D12: YC Fall 2025 | E12: $500K | F12: standard YC deal ($125K for 7% + $375K uncapped SAFE); the startup's own round is not public | G12: not stated | H12: Other | I12: unknown | J12: http://www.useremedy.co | K12: https://www.ycombinator.com/companies/remedy | L12: high
... A14: Patient-record software with AI for medical spas and wellness clinics. | B14: Tepali | C14: Y Combinator | D14: YC Winter 2026 | E14: $500K | F14: standard YC deal ($125K for 7% + $375K uncapped SAFE); the startup's own round is not public | G14: New York City, NY, USA | H14: USA | I14: unknown | J14: https://tepali.com | K14: https://www.ycombinator.com/companies/tepali | L14: high
A15: Helps dental practices bring back patients who still need treatment. | B15: Healink | C15: Antler US | D15: US Spring 2026 Showcase | E15: not disclosed | F15: taken from a third-party list that was not verified against Antler | G15: USA | H15: USA | I15: unknown | K15: https://agentjesse.ai/lists/antler-2026-cohort-companies | L15: low
A16: A smartphone-based system that detects eye damage from high blood pressure; used in 18+ Indian villages. | B16: Hypertensight | C16: Emergent Ventures India | D16: 2026 cohorts 16-19 | E16: not disclosed | F16: grant to an individual or project; amounts are not published | G16: India | H16: India | I16: yes | K16: https://marginalrevolution.com/marginalrevolution/2026/09/emergent-ventures-india-19th-cohort.html | L16: medium
A17: Links ordinary eye photos with retinal scans to diagnose eye disease. | B17: Project Lumen AI | C17: Emergent Ventures India | D17: 2026 cohorts 16-19 | E17: not disclosed | F17: grant to an individual or project; amounts are not published | G17: India | H17: India | I17: yes | K17: https://marginalrevolution.com/marginalrevolution/2026/08/emergent-ventures-india-18th-cohort.html | L17: medium
A18: AI tools for radiology: faster MRI scans and disease detection for hospitals. | B18: Aikenist | C18: Google for Startups Accelerator: India | D18: 2026 cohort (announced 2026-07-08) | E18: no cash | F18: equity-free 3-month program with mentoring and credits; most companies here already have a product and earlier funding | G18: Bengaluru, India | H18: India | I18: yes | K18: https://inc42.com/buzz/meet-the-20-startups-selected-for-googles-india-startup-accelerator-2026/ | L18: medium
A19: An app that uses AI to deliver therapy programs for chronic back and joint pain. | B19: FlexifyMe | C19: Google for Startups Accelerator: India | D19: 2026 cohort (announced 2026-07-08) | E19: no cash | F19: equity-free 3-month program with mentoring and credits; most companies here already have a product and earlier funding | G19: Pune, India | H19: India | I19: yes | K19: https://inc42.com/buzz/meet-the-20-startups-selected-for-googles-india-startup-accelerator-2026/ | L19: medium
A20: An AI health assistant that explains symptoms, lab reports and prescriptions. | B20: August AI | C20: Peak XV Surge | D20: Surge 12 (Sep 2026) | E20: $3M | F20: Surge invests up to $5M per startup; the figure shown is funding as listed by Inc42, the Surge share is not disclosed | G20: Bengaluru, India | H20: India | I20: yes | K20: https://inc42.com/buzz/meet-the-startups-from-peak-xvs-surge-12/ | L20: medium
A21: Clinics for children's healthcare: consultations, vaccines and therapies. | B21: Hoola Health | C21: Peak XV Surge | D21: Surge 12 (Sep 2026) | E21: $5M | F21: Surge invests up to $5M per startup; the figure shown is funding as listed by Inc42, the Surge share is not disclosed | G21: Bengaluru, India | H21: India | I21: yes | K21: https://inc42.com/buzz/meet-the-startups-from-peak-xvs-surge-12/ | L21: medium
A22: A low-cost, needle-free test to screen for oral cancer in places with few doctors. | B22: Astraeus Innovus | C22: WTFund (Nikhil Kamath) | D22: Cohort 3, Class of 2026 | E22: ₹20 lakh | F22: grant, no equity taken | G22: India (city not stated) | H22: India | I22: yes | K22: https://odisha.plus/2026/01/nikhil-kamath-wtfund-young-founders-deeptech-healthcare-india/ | L22: medium
A23: Affordable portable robots that help stroke patients do rehab exercises at home. | B23: Bloom Rehab | C23: WTFund (Nikhil Kamath) | D23: Cohort 3, Class of 2026 | E23: ₹20 lakh | F23: grant, no equity taken | G23: India (city not stated) | H23: India | I23: yes | K23: https://odisha.plus/2026/01/nikhil-kamath-wtfund-young-founders-deeptech-healthcare-india/ | L23: medium
A24: An AI device that attaches to a microscope to digitise and analyse pathology slides. | B24: Turocrates AI | C24: WTFund (Nikhil Kamath) | D24: Cohort 3, Class of 2026 | E24: ₹20 lakh | F24: grant, no equity taken | G24: India (city not stated) | H24: India | I24: yes | K24: https://odisha.plus/2026/01/nikhil-kamath-wtfund-young-founders-deeptech-healthcare-india/ | L24: medium
A25: An AI clinician based on functional medicine. | B25: Coherence Health | C25: a16z Speedrun | D25: SR007 (Jul-Oct 2026) | E25: up to $1M | F25: standard Speedrun deal: $500K for 10% now + $500K in the next round | G25: not stated (program runs in San Francisco) | H25: Unknown | I25: unknown | K25: https://www.frontrun.vc/blog/a16z-speedrun-cohort-007-companies/ | L25: medium
A26: AI that handles intake calls and preventive care for Medicare clinics. | B26: Rhema Health | C26: a16z Speedrun | D26: SR007 (Jul-Oct 2026) | E26: up to $1M | F26: standard Speedrun deal: $500K for 10% now + $500K in the next round | G26: not stated (program runs in San Francisco) | H26: Unknown | I26: unknown | K26: https://www.frontrun.vc/blog/a16z-speedrun-cohort-007-companies/ | L26: medium
A27: An AI advocate for people with chronic illness. | B27: Vene Health | C27: a16z Speedrun | D27: SR007 (Jul-Oct 2026) | E27: up to $1M | F27: standard Speedrun deal: $500K for 10% now + $500K in the next round | G27: not stated (program runs in San Francisco) | H27: Unknown | I27: unknown | K27: https://www.frontrun.vc/blog/a16z-speedrun-cohort-007-companies/ | L27: medium

Sheet AI workforce
A1: Idea in simple words | B1: Startup | C1: Funded by | D1: Batch / cohort | E1: Funding | F1: What the funding number means | G1: Based in | H1: India / USA / Other | I1: Indian founders? | J1: Website | K1: Source | L1: Confidence
A2: Organises everything a company knows in one place for people and AI. | B2: Almanac | C2: Y Combinator | D2: YC Summer 2026 | E2: $500K | F2: standard YC deal ($125K for 7% + $375K uncapped SAFE); the startup's own round is not public | G2: San Francisco, CA, USA | H2: USA | I2: yes | J2: https://usealmanac.com | K2: https://www.ycombinator.com/companies/almanac | L2: high
A3: AI agents that small businesses (law firms, clinics, real-estate offices) hire to do work they could never afford staff for. | B3: Async | C3: Y Combinator | D3: YC Summer 2026 | E3: $500K | F3: standard YC deal ($125K for 7% + $375K uncapped SAFE); the startup's own round is not public | G3: New York City, NY, USA | H3: USA | I3: unknown | J3: https://withasync.com | K3: https://www.ycombinator.com/companies/withasync | L3: high
A4: AI customer support for very large companies. | B4: Cignara | C4: Y Combinator | D4: YC Spring 2026 | E4: $500K | F4: standard YC deal ($125K for 7% + $375K uncapped SAFE); the startup's own round is not public | G4: San Francisco, CA, USA | H4: USA | I4: unknown | J4: https://cignara.com/ | K4: https://www.ycombinator.com/companies/cignara | L4: high
A5: A customer contact centre run by AI. | B5: Dialogus | C5: Y Combinator | D5: YC Summer 2026 | E5: $500K | F5: standard YC deal ($125K for 7% + $375K uncapped SAFE); the startup's own round is not public | G5: San Francisco, CA, USA | H5: USA | I5: unknown | J5: https://www.dialoguslabs.com/ | K5: https://www.ycombinator.com/companies/dialogus | L5: high
A6: A shared workspace where a team of AI agents work together like a department, with humans supervising. | B6: Dock | C6: Y Combinator | D6: YC Summer 2026 | E6: $500K | F6: standard YC deal ($125K for 7% + $375K uncapped SAFE); the startup's own round is not public | G6: San Francisco, CA, USA | H6: USA | I6: reported | J6: https://trydock.ai | K6: https://www.ycombinator.com/companies/dock | L6: high
A7: A "company brain": it connects all of a company's documents and chats so AI assistants can answer using what the company knows. | B7: Hyperspell | C7: Y Combinator | D7: YC Fall 2025 | E7: $500K | F7: standard YC deal ($125K for 7% + $375K uncapped SAFE); the startup's own round is not public | G7: San Francisco, CA, USA | H7: USA | I7: unknown | J7: https://hyperspell.com | K7: https://www.ycombinator.com/companies/hyperspell | L7: high
A8: Lets non-technical teams build their own AI agents without engineers. | B8: Nexus | C8: Y Combinator | D8: YC Fall 2025 | E8: $500K | F8: standard YC deal ($125K for 7% + $375K uncapped SAFE); the startup's own round is not public | G8: Brussels, Brussels, Belgium | H8: Other | I8: unknown | J8: https://agent.nexus | K8: https://www.ycombinator.com/companies/gpt | L8: high
A9: AI that interviews every employee about how they work, so the company's AI tools have the missing context. | B9: Ontora | C9: Y Combinator | D9: YC Spring 2026 | E9: $500K | F9: standard YC deal ($125K for 7% + $375K uncapped SAFE); the startup's own round is not public | G9: Berlin, Berlin, Germany | H9: Other | I9: unknown | J9: https://ontora.com | K9: https://www.ycombinator.com/companies/ontora | L9: high
A10: An always-on AI "operations brain" that takes over complex day-to-day operations for a company. | B10: Redapto | C10: Y Combinator | D10: YC Fall 2025 | E10: $500K | F10: standard YC deal ($125K for 7% + $375K uncapped SAFE); the startup's own round is not public | G10: Bengaluru, KA, India | H10: India | I10: yes | J10: https://www.redapto.com/ | K10: https://www.ycombinator.com/companies/redapto | L10: high
A11: Records the computer work employees do and turns it into AI agents that can repeat that work. | B11: screenpipe | C11: Y Combinator | D11: YC Summer 2026 | E11: $500K | F11: standard YC deal ($125K for 7% + $375K uncapped SAFE); the startup's own round is not public | G11: San Francisco, CA, USA | H11: USA | I11: unknown | J11: https://screenpipe.com | K11: https://www.ycombinator.com/companies/screenpipe | L11: high
A12: An AI agent that connects to your work apps and keeps doing tasks from plain-English instructions. | B12: Tasklet | C12: Y Combinator | D12: YC Spring 2026 | E12: $500K | F12: standard YC deal ($125K for 7% + $375K uncapped SAFE); the startup's own round is not public | G12: San Francisco, CA, USA | H12: USA | I12: unknown | J12: https://tasklet.ai | K12: https://www.ycombinator.com/companies/tasklet-2 | L12: high
... A14: Sets up custom AI agents inside a company's ERP (its core business software). | B14: Trope | C14: Y Combinator | D14: YC Summer 2026 | E14: $500K | F14: standard YC deal ($125K for 7% + $375K uncapped SAFE); the startup's own round is not public | G14: San Francisco, CA, USA | H14: USA | I14: unknown | J14: https://trope.ai | K14: https://www.ycombinator.com/companies/trope | L14: high
A15: AI agents that modernise ERP systems (a company's core business software), starting with SAP. Also backed by Antler India. | B15: Dodge.ai | C15: Accel Atoms + Google AI Futures Fund | D15: Atoms AI Cohort 2026 (Mar-Jun 2026) | E15: up to $2M | F15: co-investment by Accel and Google AI Futures Fund, plus up to $350K compute credits; per-startup amount not disclosed | G15: not stated (program is for Indian and Indian-origin founders anywhere) | H15: Unknown | I15: yes | K15: https://www.outlookbusiness.com/deeptech/five-startups-to-join-accel-atoms-and-googles-ai-futures-fund-ai-cohort-2026 | L15: medium
A16: AI agents that keep a team aligned on company goals. | B16: Alia | C16: a16z Speedrun | D16: SR007 (Jul-Oct 2026) | E16: up to $1M | F16: standard Speedrun deal: $500K for 10% now + $500K in the next round | G16: not stated (program runs in San Francisco) | H16: Unknown | I16: unknown | K16: https://www.frontrun.vc/blog/a16z-speedrun-cohort-007-companies/ | L16: medium
A17: A virtual chief AI officer that is judged on profit and loss. | B17: Codos | C17: a16z Speedrun | D17: SR007 (Jul-Oct 2026) | E17: up to $1M | F17: standard Speedrun deal: $500K for 10% now + $500K in the next round | G17: not stated (program runs in San Francisco) | H17: Unknown | I17: unknown | K17: https://www.frontrun.vc/blog/a16z-speedrun-cohort-007-companies/ | L17: medium
A18: Learns how work gets done in a company and suggests what to automate. | B18: Infragrid | C18: a16z Speedrun | D18: SR007 (Jul-Oct 2026) | E18: up to $1M | F18: standard Speedrun deal: $500K for 10% now + $500K in the next round | G18: not stated (program runs in San Francisco) | H18: Unknown | I18: unknown | K18: https://www.frontrun.vc/blog/a16z-speedrun-cohort-007-companies/ | L18: medium
A19: Dictation that runs on the device, for teams that will not send audio to the cloud. | B19: OpenWhispr | C19: a16z Speedrun | D19: SR007 (Jul-Oct 2026) | E19: up to $1M | F19: standard Speedrun deal: $500K for 10% now + $500K in the next round | G19: not stated (program runs in San Francisco) | H19: Unknown | I19: unknown | K19: https://www.frontrun.vc/blog/a16z-speedrun-cohort-007-companies/ | L19: medium
A20: AI that learns how a company's employees work and completes business tasks, starting with mergers. | B20: Phyvant | C20: a16z Speedrun | D20: SR007 (Jul-Oct 2026) | E20: up to $1M | F20: standard Speedrun deal: $500K for 10% now + $500K in the next round | G20: not stated (program runs in San Francisco) | H20: Unknown | I20: unknown | K20: https://www.frontrun.vc/blog/a16z-speedrun-cohort-007-companies/ | L20: medium
A21: AI on your own device that watches screen workflows and learns to do them. | B21: Sonder | C21: a16z Speedrun | D21: SR007 (Jul-Oct 2026) | E21: up to $1M | F21: standard Speedrun deal: $500K for 10% now + $500K in the next round | G21: not stated (program runs in San Francisco) | H21: Unknown | I21: unknown | K21: https://www.frontrun.vc/blog/a16z-speedrun-cohort-007-companies/ | L21: medium

Sheet Sales and marketing
A1: Idea in simple words | B1: Startup | C1: Funded by | D1: Batch / cohort | E1: Funding | F1: What the funding number means | G1: Based in | H1: India / USA / Other | I1: Indian founders? | J1: Website | K1: Source | L1: Confidence
A2: Helps a software product get chosen when AI coding assistants pick tools. | B2: Armature | C2: Y Combinator | D2: YC Spring 2026 | E2: $500K | F2: standard YC deal ($125K for 7% + $375K uncapped SAFE); the startup's own round is not public | G2: Paris, Île-de-France, France | H2: Other | I2: unknown | J2: https://armature.tech | K2: https://www.ycombinator.com/companies/armature | L2: high
A3: Listens to a sales call live and tells the salesperson what to say next. | B3: Caretta | C3: Y Combinator | D3: YC Winter 2026 | E3: $500K | F3: standard YC deal ($125K for 7% + $375K uncapped SAFE); the startup's own round is not public | G3: San Francisco, CA, USA | H3: USA | I3: unknown | J3: https://www.caretta.so | K3: https://www.ycombinator.com/companies/caretta | L3: high
A4: Tells sales teams exactly when a target company is ready to buy. | B4: Clean | C4: Y Combinator | D4: YC Fall 2026 | E4: $500K | F4: standard YC deal ($125K for 7% + $375K uncapped SAFE); the startup's own round is not public | G4: San Francisco, CA, USA | H4: USA | I4: unknown | J4: http://www.tryclean.ai | K4: https://www.ycombinator.com/companies/clean | L4: high
A5: An AI sales agent for packaged consumer goods brands. | B5: Corvera | C5: Y Combinator | D5: YC Winter 2026 | E5: $500K | F5: standard YC deal ($125K for 7% + $375K uncapped SAFE); the startup's own round is not public | G5: San Francisco, CA, USA | H5: USA | I5: unknown | J5: https://corvera.ai/ | K5: https://www.ycombinator.com/companies/corvera | L5: high
A6: Simulated shoppers that packaged-goods brands can test new products on, instead of running surveys. | B6: Foresight | C6: Y Combinator | D6: YC Spring 2026 | E6: $500K | F6: standard YC deal ($125K for 7% + $375K uncapped SAFE); the startup's own round is not public | G6: New York City, NY, USA | H6: USA | I6: unknown | J6: https://foresight.tt/ | K6: https://www.ycombinator.com/companies/foresight | L6: high
A7: AI that creates ads and runs the ad campaigns from start to finish. | B7: Lapis | C7: Y Combinator | D7: YC Fall 2025 | E7: $500K | F7: standard YC deal ($125K for 7% + $375K uncapped SAFE); the startup's own round is not public | G7: San Francisco, CA, USA | H7: USA | I7: unknown | J7: https://www.trylapis.com/ | K7: https://www.ycombinator.com/companies/lapis | L7: high
A8: A free, open-source alternative to paid SEO tools such as Semrush and Ahrefs. | B8: OpenSEO | C8: Y Combinator | D8: YC Fall 2026 | E8: $500K | F8: standard YC deal ($125K for 7% + $375K uncapped SAFE); the startup's own round is not public | G8: Boston, MA, USA | H8: USA | I8: unknown | J8: https://openseo.so/ | K8: https://www.ycombinator.com/companies/openseo | L8: high
A9: Builds and runs a company's website, landing pages and marketing automatically. | B9: Ploy | C9: Y Combinator | D9: YC Spring 2026 | E9: $27M | F9: seed round led by First Round and YC (TechCrunch, 2026-06-18) | G9: San Francisco, CA, USA | H9: USA | I9: unknown | J9: https://ploy.ai | K9: https://www.ycombinator.com/companies/ploy ; https://techcrunch.com/2026/06/18/the-11-standout-startups-from-ycs-demo-day-according-to-vcs/ | L9: high
A10: Lets online brands sell to customers again through iMessage. | B10: Signals | C10: Y Combinator | D10: YC Winter 2026 | E10: $500K | F10: standard YC deal ($125K for 7% + $375K uncapped SAFE); the startup's own round is not public | G10: San Francisco, CA, USA | H10: USA | I10: unknown | J10: https://www.returnsignals.com | K10: https://www.ycombinator.com/companies/signals | L10: high
A11: Connects local businesses with local content creators. | B11: TryNearby | C11: Y Combinator | D11: YC Summer 2026 | E11: $500K | F11: standard YC deal ($125K for 7% + $375K uncapped SAFE); the startup's own round is not public | G11: Los Angeles, CA, USA | H11: USA | I11: unknown | J11: https://trynearby.com | K11: https://www.ycombinator.com/companies/trynearby | L11: high
A12: AI that replaces a marketing agency. | B12: Uplane | C12: Y Combinator | D12: YC Fall 2025 | E12: $500K | F12: standard YC deal ($125K for 7% + $375K uncapped SAFE); the startup's own round is not public | G12: San Francisco, CA, USA | H12: USA | I12: unknown | J12: https://uplane.com | K12: https://www.ycombinator.com/companies/uplane | L12: high
A13: Finds and warms up likely customers before the sales team reaches out. | B13: Kindling | C13: Peak XV Surge | D13: Surge 12 (Sep 2026) | E13: $500K | F13: Surge invests up to $5M per startup; the figure shown is funding as listed by Inc42, the Surge share is not disclosed | G13: Sydney, Australia | H13: Other | I13: unknown | K13: https://inc42.com/buzz/meet-the-startups-from-peak-xvs-surge-12/ | L13: medium
A14: An AI general manager for consumer brands. | B14: Baro | C14: a16z Speedrun | D14: SR007 (Jul-Oct 2026) | E14: up to $1M | F14: standard Speedrun deal: $500K for 10% now + $500K in the next round | G14: not stated (program runs in San Francisco) | H14: Unknown | I14: unknown | K14: https://www.frontrun.vc/blog/a16z-speedrun-cohort-007-companies/ | L14: medium
A15: Infrastructure for AI sales and marketing agents. | B15: Cluster | C15: a16z Speedrun | D15: SR007 (Jul-Oct 2026) | E15: up to $1M | F15: standard Speedrun deal: $500K for 10% now + $500K in the next round | G15: not stated (program runs in San Francisco) | H15: Unknown | I15: unknown | K15: https://www.frontrun.vc/blog/a16z-speedrun-cohort-007-companies/ | L15: medium
A16: AI that lets a growth team ship more experiments. | B16: Lazyweb | C16: a16z Speedrun | D16: SR007 (Jul-Oct 2026) | E16: up to $1M | F16: standard Speedrun deal: $500K for 10% now + $500K in the next round | G16: not stated (program runs in San Francisco) | H16: Unknown | I16: unknown | K16: https://www.frontrun.vc/blog/a16z-speedrun-cohort-007-companies/ | L16: medium
A17: Infrastructure for AI revenue agents. | B17: Nexor AI | C17: a16z Speedrun | D17: SR007 (Jul-Oct 2026) | E17: up to $1M | F17: standard Speedrun deal: $500K for 10% now + $500K in the next round | G17: not stated (program runs in San Francisco) | H17: Unknown | I17: unknown | K17: https://www.frontrun.vc/blog/a16z-speedrun-cohort-007-companies/ | L17: medium
A18: Coaches salespeople live during B2B sales calls. | B18: Othello | C18: a16z Speedrun | D18: SR007 (Jul-Oct 2026) | E18: up to $1M | F18: standard Speedrun deal: $500K for 10% now + $500K in the next round | G18: not stated (program runs in San Francisco) | H18: Unknown | I18: unknown | K18: https://www.frontrun.vc/blog/a16z-speedrun-cohort-007-companies/ | L18: medium
A19: Models of human behaviour that preview how people will react before a launch. | B19: Primitive Labs | C19: a16z Speedrun | D19: SR007 (Jul-Oct 2026) | E19: up to $1M | F19: standard Speedrun deal: $500K for 10% now + $500K in the next round | G19: not stated (program runs in San Francisco) | H19: Unknown | I19: unknown | K19: https://www.frontrun.vc/blog/a16z-speedrun-cohort-007-companies/ | L19: medium
A20: AI agents that talk to each customer one by one in the brand's voice. | B20: Saru | C20: a16z Speedrun | D20: SR007 (Jul-Oct 2026) | E20: up to $1M | F20: standard Speedrun deal: $500K for 10% now + $500K in the next round | G20: not stated (program runs in San Francisco) | H20: Unknown | I20: unknown | K20: https://www.frontrun.vc/blog/a16z-speedrun-cohort-007-companies/ | L20: medium
A21: A data layer for AI revenue agents that work on long tasks. | B21: Sterling | C21: a16z Speedrun | D21: SR007 (Jul-Oct 2026) | E21: up to $1M | F21: standard Speedrun deal: $500K for 10% now + $500K in the next round | G21: not stated (program runs in San Francisco) | H21: Unknown | I21: unknown | K21: https://www.frontrun.vc/blog/a16z-speedrun-cohort-007-companies/ | L21: medium

Sheet Hiring
A1: Idea in simple words | B1: Startup | C1: Funded by | D1: Batch / cohort | E1: Funding | F1: What the funding number means | G1: Based in | H1: India / USA / Other | I1: Indian founders? | J1: Website | K1: Source | L1: Confidence
A2: AI recruiters that staffing agencies use to find and screen candidates. | B2: Asendia AI | C2: Y Combinator | D2: YC Spring 2026 | E2: $500K | F2: standard YC deal ($125K for 7% + $375K uncapped SAFE); the startup's own round is not public | G2: San Francisco, CA, USA | H2: USA | I2: unknown | J2: https://asendia.ai/ | K2: https://www.ycombinator.com/companies/asendia-ai | L2: high
A3: Tests that measure how capable a person really is, starting with software engineers. Reports about $60K yearly revenue. | B3: Litmus | C3: Y Combinator | D3: YC Summer 2026 | E3: $500K | F3: standard YC deal ($125K for 7% + $375K uncapped SAFE); the startup's own round is not public | G3: San Francisco, CA, USA | H3: USA | I3: reported | J3: https://litmushiring.com/ | K3: https://www.ycombinator.com/companies/litmus-hiring | L3: high
A4: A recruiting agency where AI does the sourcing and screening. | B4: Prism | C4: Y Combinator | D4: YC Spring 2026 | E4: $500K | F4: standard YC deal ($125K for 7% + $375K uncapped SAFE); the startup's own round is not public | G4: London, England, United Kingdom | H4: Other | I4: unknown | J4: https://tryprism.com/ | K4: https://www.ycombinator.com/companies/tryprism | L4: high
A5: A swipe-to-apply job app, like Tinder for jobs. | B5: Sorce | C5: Y Combinator | D5: YC Fall 2025 | E5: $500K | F5: standard YC deal ($125K for 7% + $375K uncapped SAFE); the startup's own round is not public | G5: San Francisco, CA, USA | H5: USA | I5: unknown | J5: https://sorce.jobs | K5: https://www.ycombinator.com/companies/sorce | L5: high
A6: A hiring marketplace where AI agents match candidates and companies. | B6: Standout | C6: Y Combinator | D6: YC Spring 2026 | E6: $500K | F6: standard YC deal ($125K for 7% + $375K uncapped SAFE); the startup's own round is not public | G6: San Francisco, CA, USA | H6: USA | I6: unknown | J6: https://standout.work | K6: https://www.ycombinator.com/companies/standout | L6: high
A7: An AI career agent that finds matching jobs and applies for you. Reports about $3M yearly revenue rate within three months. | B7: Tsenta | C7: Y Combinator | D7: YC Summer 2026 | E7: $500K | F7: standard YC deal ($125K for 7% + $375K uncapped SAFE); the startup's own round is not public | G7: San Francisco, CA, USA | H7: USA | I7: reported | J7: https://tsenta.com | K7: https://www.ycombinator.com/companies/tsenta | L7: high
A8: AI agents that research talent pools and explain why a candidate fits. | B8: Kello | C8: Peak XV Surge | D8: Surge 12 (Sep 2026) | E8: not disclosed | F8: Surge invests up to $5M per startup; the figure shown is funding as listed by Inc42, the Surge share is not disclosed | G8: Bengaluru, India | H8: India | I8: yes | K8: https://inc42.com/buzz/meet-the-startups-from-peak-xvs-surge-12/ | L8: medium
A9: An AI recruiting tool that searches large candidate databases by real skills. | B9: Juicebox | C9: Thiel Fellowship | D9: 2026 class (announced 2026-04-21) | E9: $250K | F9: grant paid over two years, no equity taken | G9: fellow is from Kanpur, India; company base not stated in source | H9: Unknown | I9: yes | K9: https://insights.tryspecter.com/thiel-fellows-2026/ | L9: medium

Sheet Legal and gov
A1: Idea in simple words | B1: Startup | C1: Funded by | D1: Batch / cohort | E1: Funding | F1: What the funding number means | G1: Based in | H1: India / USA / Other | I1: Indian founders? | J1: Website | K1: Source | L1: Confidence
A2: Helps startups win government contracts. | B2: Capto | C2: Y Combinator | D2: YC Summer 2026 | E2: $500K | F2: standard YC deal ($125K for 7% + $375K uncapped SAFE); the startup's own round is not public | G2: San Francisco, CA, USA | H2: USA | I2: unknown | J2: https://gocapto.com/ | K2: https://www.ycombinator.com/companies/capto | L2: high
A3: Handles the compliance, labels and documents needed to sell a physical product in other countries. | B3: Complir | C3: Y Combinator | D3: YC Spring 2026 | E3: $500K | F3: standard YC deal ($125K for 7% + $375K uncapped SAFE); the startup's own round is not public | G3: Copenhagen, Denmark | H3: Other | I3: unknown | J3: https://complir.io/ | K3: https://www.ycombinator.com/companies/complir | L3: high
A4: Automates how government offices answer public-records requests. | B4: GovGuard | C4: Y Combinator | D4: YC Spring 2026 | E4: $500K | F4: standard YC deal ($125K for 7% + $375K uncapped SAFE); the startup's own round is not public | G4: not stated | H4: Other | I4: unknown | J4: https://govguard.com | K4: https://www.ycombinator.com/companies/govguard | L4: high
A5: AI software for a company's in-house legal team. | B5: Lexi | C5: Y Combinator | D5: YC Fall 2025 | E5: $500K | F5: standard YC deal ($125K for 7% + $375K uncapped SAFE); the startup's own round is not public | G5: San Francisco, CA, USA | H5: USA | I5: unknown | J5: https://getlexi.io/ | K5: https://www.ycombinator.com/companies/lexi | L5: high
A6: Automates immigration checks and paperwork for HR teams. | B6: Mayflower | C6: Y Combinator | D6: YC Fall 2025 | E6: $500K | F6: standard YC deal ($125K for 7% + $375K uncapped SAFE); the startup's own round is not public | G6: San Francisco, CA, USA | H6: USA | I6: unknown | J6: https://mayflowervisa.com | K6: https://www.ycombinator.com/companies/mayflower | L6: high
A7: AI that spots when someone is infringing your patent. | B7: Patent Watch | C7: Y Combinator | D7: YC Fall 2025 | E7: $500K | F7: standard YC deal ($125K for 7% + $375K uncapped SAFE); the startup's own round is not public | G7: San Francisco, CA, USA | H7: USA | I7: unknown | J7: https://www.patentwatch.ai/ | K7: https://www.ycombinator.com/companies/patent-watch | L7: high
A8: AI that does police officers' paperwork. | B8: Reconero | C8: Y Combinator | D8: YC Fall 2026 | E8: $500K | F8: standard YC deal ($125K for 7% + $375K uncapped SAFE); the startup's own round is not public | G8: San Francisco, CA, USA | H8: USA | I8: unknown | J8: https://reconero.com | K8: https://www.ycombinator.com/companies/reconero | L8: high
A9: AI agents that make local government offices work faster. | B9: Verdant | C9: Y Combinator | D9: YC Summer 2026 | E9: $500K | F9: standard YC deal ($125K for 7% + $375K uncapped SAFE); the startup's own round is not public | G9: San Francisco, CA, USA | H9: USA | I9: unknown | J9: https://www.verdantapp.com/ | K9: https://www.ycombinator.com/companies/verdant | L9: high
A10: AI research on court cases for trial lawyers. | B10: OurFirm.ai | C10: Antler US | D10: US Spring 2026 Showcase | E10: not disclosed | F10: taken from a third-party list that was not verified against Antler | G10: USA | H10: USA | I10: unknown | K10: https://agentjesse.ai/lists/antler-2026-cohort-companies | L10: low
A11: Speech-to-text and workflow tools that help Indian courts and lawyers clear case backlogs. | B11: Adalat AI | C11: Google for Startups Accelerator: India | D11: 2026 cohort (announced 2026-07-08) | E11: no cash | F11: equity-free 3-month program with mentoring and credits; most companies here already have a product and earlier funding | G11: Delhi NCR, India | H11: India | I11: yes | K11: https://inc42.com/buzz/meet-the-20-startups-selected-for-googles-india-startup-accelerator-2026/ | L11: medium
A12: Uses AI and investigative journalism to uncover government fraud. | B12: The Antifraud Company | C12: Thiel Fellowship | D12: 2026 class (announced 2026-04-21) | E12: $250K | F12: grant paid over two years, no equity taken | G12: New Hampshire, USA (fellow's location) | H12: USA | I12: unknown | K12: https://insights.tryspecter.com/thiel-fellows-2026/ | L12: medium
A13: AI-based legal operations for startups. | B13: OneGC | C13: a16z Speedrun | D13: SR007 (Jul-Oct 2026) | E13: up to $1M | F13: standard Speedrun deal: $500K for 10% now + $500K in the next round | G13: not stated (program runs in San Francisco) | H13: Unknown | I13: unknown | K13: https://www.frontrun.vc/blog/a16z-speedrun-cohort-007-companies/ | L13: medium
A14: Checks that consumer-goods labels follow the rules. | B14: Truli | C14: a16z Speedrun | D14: SR007 (Jul-Oct 2026) | E14: up to $1M | F14: standard Speedrun deal: $500K for 10% now + $500K in the next round | G14: not stated (program runs in San Francisco) | H14: Unknown | I14: unknown | K14: https://www.frontrun.vc/blog/a16z-speedrun-cohort-007-companies/ | L14: medium

Sheet Agent infrastructure
A1: Idea in simple words | B1: Startup | C1: Funded by | D1: Batch / cohort | E1: Funding | F1: What the funding number means | G1: Based in | H1: India / USA / Other | I1: Indian founders? | J1: Website | K1: Source | L1: Confidence
A2: Payment cards for AI agents. | B2: Agentcard | C2: Y Combinator | D2: YC Summer 2026 | E2: $500K | F2: standard YC deal ($125K for 7% + $375K uncapped SAFE); the startup's own round is not public | G2: San Francisco, CA, USA | H2: USA | I2: unknown | J2: https://agentcard.sh | K2: https://www.ycombinator.com/companies/agentcard | L2: high
A3: Gives AI agents their own phone numbers so they can call and text. | B3: AgentPhone | C3: Y Combinator | D3: YC Spring 2026 | E3: $500K | F3: standard YC deal ($125K for 7% + $375K uncapped SAFE); the startup's own round is not public | G3: San Francisco, CA, USA | H3: USA | I3: unknown | J3: https://agentphone.ai/ | K3: https://www.ycombinator.com/companies/agentphone | L3: high
A4: Sends each AI request to the cheapest model that can handle it, to cut AI bills by a claimed 70%+. | B4: Conifer | C4: Y Combinator | D4: YC Summer 2026 | E4: $500K | F4: standard YC deal ($125K for 7% + $375K uncapped SAFE); the startup's own round is not public | G4: San Francisco, CA, USA | H4: USA | I4: unknown | J4: https://www.conifer.build | K4: https://www.ycombinator.com/companies/conifer | L4: high
A5: Lets an AI agent call a human expert within seconds when it gets stuck. | B5: Humwork | C5: Y Combinator | D5: YC Spring 2026 | E5: $500K | F5: standard YC deal ($125K for 7% + $375K uncapped SAFE); the startup's own round is not public | G5: San Francisco, CA, USA | H5: USA | I5: unknown | J5: https://humwork.ai | K5: https://www.ycombinator.com/companies/humwork | L5: high
A6: Gives AI agents an identity (email, phone number) so they can communicate. | B6: Inkbox | C6: Y Combinator | D6: YC Summer 2026 | E6: $500K | F6: standard YC deal ($125K for 7% + $375K uncapped SAFE); the startup's own round is not public | G6: San Francisco, CA, USA | H6: USA | I6: unknown | J6: https://inkbox.ai | K6: https://www.ycombinator.com/companies/inkbox | L6: high
A7: Lets AI agents make payments. | B7: Locus | C7: Y Combinator | D7: YC Fall 2025 | E7: $500K | F7: standard YC deal ($125K for 7% + $375K uncapped SAFE); the startup's own round is not public | G7: San Francisco, CA, USA | H7: USA | I7: unknown | J7: https://paywithlocus.com | K7: https://www.ycombinator.com/companies/locus | L7: high
A8: Turns any website into something software can talk to directly. | B8: Parse | C8: Y Combinator | D8: YC Fall 2025 | E8: $500K | F8: standard YC deal ($125K for 7% + $375K uncapped SAFE); the startup's own round is not public | G8: San Francisco, CA, USA | H8: USA | I8: unknown | J8: https://parse.bot | K8: https://www.ycombinator.com/companies/parse-bot | L8: high
A9: Makes any website usable as a tool by AI agents in minutes. | B9: Pomerado | C9: Y Combinator | D9: YC Fall 2026 | E9: $500K | F9: standard YC deal ($125K for 7% + $375K uncapped SAFE); the startup's own round is not public | G9: San Francisco, CA, USA | H9: USA | I9: unknown | J9: https://www.pomerado.ai | K9: https://www.ycombinator.com/companies/pomerado | L9: high
A10: A marketplace where AI agents hire humans to do real-world tasks. | B10: RentAHuman | C10: Y Combinator | D10: YC Spring 2026 | E10: $500K | F10: standard YC deal ($125K for 7% + $375K uncapped SAFE); the startup's own round is not public | G10: San Francisco, CA, USA | H10: USA | I10: unknown | J10: https://rentahuman.ai | K10: https://www.ycombinator.com/companies/rentahuman | L10: high
A11: Very fast web browsers in the cloud that AI agents use and that websites cannot block. | B11: Tilion | C11: Y Combinator | D11: YC Fall 2026 | E11: $500K | F11: standard YC deal ($125K for 7% + $375K uncapped SAFE); the startup's own round is not public | G11: San Francisco, CA, USA | H11: USA | I11: unknown | J11: https://tilion.com | K11: https://www.ycombinator.com/companies/tilion | L11: high
A12: Reads messy documents (PDFs, scans, tables) and turns them into clean data. | B12: Unsiloed AI | C12: Y Combinator | D12: YC Fall 2025 | E12: $500K | F12: standard YC deal ($125K for 7% + $375K uncapped SAFE); the startup's own round is not public | G12: San Francisco, CA, USA | H12: USA | I12: unknown | J12: https://www.unsiloed.ai/ | K12: https://www.ycombinator.com/companies/unsiloed-ai | L12: high
A13: Lets AI agents make purchases on behalf of brands. | B13: Parleo | C13: Antler US | D13: US Spring 2026 Showcase | E13: not disclosed | F13: taken from a third-party list that was not verified against Antler | G13: USA | H13: USA | I13: unknown | K13: https://agentjesse.ai/lists/antler-2026-cohort-companies | L13: low
A14: Payment infrastructure that lets AI agents pay safely on a user's behalf. | B14: Prava | C14: WTFund (Nikhil Kamath) | D14: Cohort 3, Class of 2026 | E14: ₹20 lakh | F14: grant, no equity taken | G14: India (city not stated) | H14: India | I14: yes | K14: https://odisha.plus/2026/01/nikhil-kamath-wtfund-young-founders-deeptech-healthcare-india/ | L14: medium
A15: Post a task, AI agents and human specialists do it, and you pay when it is done. | B15: Bounty | C15: a16z Speedrun | D15: SR007 (Jul-Oct 2026) | E15: up to $1M | F15: standard Speedrun deal: $500K for 10% now + $500K in the next round | G15: not stated (program runs in San Francisco) | H15: Unknown | I15: unknown | K15: https://www.frontrun.vc/blog/a16z-speedrun-cohort-007-companies/ | L15: medium
A16: A network where AI agents learn from other AI agents. | B16: ChatOverflow | C16: a16z Speedrun | D16: SR007 (Jul-Oct 2026) | E16: up to $1M | F16: standard Speedrun deal: $500K for 10% now + $500K in the next round | G16: not stated (program runs in San Francisco) | H16: Unknown | I16: unknown | K16: https://www.frontrun.vc/blog/a16z-speedrun-cohort-007-companies/ | L16: medium
A17: A data warehouse that AI agents build and run. | B17: Embrasure | C17: a16z Speedrun | D17: SR007 (Jul-Oct 2026) | E17: up to $1M | F17: standard Speedrun deal: $500K for 10% now + $500K in the next round | G17: not stated (program runs in San Francisco) | H17: Unknown | I17: unknown | K17: https://www.frontrun.vc/blog/a16z-speedrun-cohort-007-companies/ | L17: medium
A18: Infrastructure that keeps a product running when AI agents use it heavily. | B18: PreMan | C18: a16z Speedrun | D18: SR007 (Jul-Oct 2026) | E18: up to $1M | F18: standard Speedrun deal: $500K for 10% now + $500K in the next round | G18: not stated (program runs in San Francisco) | H18: Unknown | I18: unknown | K18: https://www.frontrun.vc/blog/a16z-speedrun-cohort-007-companies/ | L18: medium
A19: File storage built for AI workloads. | B19: Space | C19: a16z Speedrun | D19: SR007 (Jul-Oct 2026) | E19: up to $1M | F19: standard Speedrun deal: $500K for 10% now + $500K in the next round | G19: not stated (program runs in San Francisco) | H19: Unknown | I19: unknown | K19: https://www.frontrun.vc/blog/a16z-speedrun-cohort-007-companies/ | L19: medium
A20: Lets AI agents use everyday web tools. | B20: Switchfrog | C20: a16z Speedrun | D20: SR007 (Jul-Oct 2026) | E20: up to $1M | F20: standard Speedrun deal: $500K for 10% now + $500K in the next round | G20: not stated (program runs in San Francisco) | H20: Unknown | I20: unknown | K20: https://www.frontrun.vc/blog/a16z-speedrun-cohort-007-companies/ | L20: medium

Sheet Agent safety
A1: Idea in simple words | B1: Startup | C1: Funded by | D1: Batch / cohort | E1: Funding | F1: What the funding number means | G1: Based in | H1: India / USA / Other | I1: Indian founders? | J1: Website | K1: Source | L1: Confidence
A2: Finds where a company's AI agents fail, then trains better models to run them. | B2: Agnost AI | C2: Y Combinator | D2: YC Summer 2026 | E2: $500K | F2: standard YC deal ($125K for 7% + $375K uncapped SAFE); the startup's own round is not public | G2: San Francisco, CA, USA | H2: USA | I2: yes | J2: https://agnost.ai | K2: https://www.ycombinator.com/companies/agnost-ai | L2: high
A3: Realistic copies of real software so AI agents can be tested safely before going live. | B3: Arga Labs | C3: Y Combinator | D3: YC Spring 2026 | E3: $500K | F3: standard YC deal ($125K for 7% + $375K uncapped SAFE); the startup's own round is not public | G3: San Francisco, CA, USA | H3: USA | I3: unknown | J3: https://www.argalabs.com/ | K3: https://www.ycombinator.com/companies/arga-labs | L3: high
A4: Watches long-running AI agents, spots when they quietly fail or drift from the goal, and suggests the fix. | B4: BentoLabs AI | C4: Y Combinator | D4: YC Spring 2026 | E4: $500K | F4: standard YC deal ($125K for 7% + $375K uncapped SAFE); the startup's own round is not public | G4: Bengaluru, KA, India | H4: India | I4: yes | J4: https://bentolabs.ai/ | K4: https://www.ycombinator.com/companies/bentolabs-ai | L4: high
A5: Trains models specific to a company that approve or block what its AI agents do. | B5: Decawork | C5: Y Combinator | D5: YC Summer 2026 | E5: $500K | F5: standard YC deal ($125K for 7% + $375K uncapped SAFE); the startup's own round is not public | G5: San Francisco, CA, USA | H5: USA | I5: yes | J5: https://decawork.ai/ | K5: https://www.ycombinator.com/companies/decawork | L5: high
A6: A hidden watermark inside AI-generated voice that survives a phone call, so fake voices can be detected. | B6: DeepMark | C6: Y Combinator | D6: YC Fall 2026 | E6: $500K | F6: standard YC deal ($125K for 7% + $375K uncapped SAFE); the startup's own round is not public | G6: San Francisco, CA, USA | H6: USA | I6: unknown | J6: https://www.deepmark.me | K6: https://www.ycombinator.com/companies/deepmark | L6: high
A7: Monitors AI agents after launch and shows when they fail. | B7: Lemma | C7: Y Combinator | D7: YC Fall 2025 | E7: $500K | F7: standard YC deal ($125K for 7% + $375K uncapped SAFE); the startup's own round is not public | G7: San Francisco, CA, USA | H7: USA | I7: unknown | J7: https://www.uselemma.ai/ | K7: https://www.ycombinator.com/companies/uselemma | L7: high
A8: Login, permissions and audit logs for AI agents. | B8: Multifactor | C8: Y Combinator | D8: YC Fall 2025 | E8: $500K | F8: standard YC deal ($125K for 7% + $375K uncapped SAFE); the startup's own round is not public | G8: San Francisco, CA, USA | H8: USA | I8: unknown | J8: https://multifactor.com | K8: https://www.ycombinator.com/companies/multifactor | L8: high
A9: A platform to train, test and launch AI agents that work inside real business systems. | B9: Ressl AI | C9: Y Combinator | D9: YC Winter 2026 | E9: $500K | F9: standard YC deal ($125K for 7% + $375K uncapped SAFE); the startup's own round is not public | G9: Bengaluru, KA, India | H9: India | I9: yes | J9: https://ressl.ai | K9: https://www.ycombinator.com/companies/ressl-ai | L9: high
A10: Checks an AI agent's action before it is carried out. | B10: Salus | C10: Y Combinator | D10: YC Winter 2026 | E10: $500K | F10: standard YC deal ($125K for 7% + $375K uncapped SAFE); the startup's own round is not public | G10: San Francisco, CA, USA | H10: USA | I10: unknown | J10: https://www.usesalus.ai/ | K10: https://www.ycombinator.com/companies/salus | L10: high
A11: Protects AI agents from being tricked by malicious instructions, and keeps learning from new attacks. | B11: Silmaril | C11: Y Combinator | D11: YC Spring 2026 | E11: $500K | F11: standard YC deal ($125K for 7% + $375K uncapped SAFE); the startup's own round is not public | G11: San Francisco, CA, USA | H11: USA | I11: unknown | J11: https://silmaril.dev | K11: https://www.ycombinator.com/companies/silmaril | L11: high
A12: Security software that watches AI agents the way antivirus watches laptops. Reports $3M yearly revenue across pilots (unverified). | B12: Traceforce | C12: Y Combinator | D12: YC Summer 2026 | E12: $500K | F12: standard YC deal ($125K for 7% + $375K uncapped SAFE); the startup's own round is not public | G12: San Francisco, CA, USA | H12: USA | I12: reported | J12: https://www.traceforce.ai | K12: https://www.ycombinator.com/companies/traceforce | L12: high
A13: AI that keeps trying to hack your own systems and fixes the holes it finds. | B13: Veria Labs | C13: Y Combinator | D13: YC Fall 2025 | E13: $500K | F13: standard YC deal ($125K for 7% + $375K uncapped SAFE); the startup's own round is not public | G13: San Francisco, CA, USA | H13: USA | I13: unknown | J13: https://verialabs.com | K13: https://www.ycombinator.com/companies/veria-labs | L13: high
A14: AI agents that handle trust-and-safety cases for online platforms. | B14: Precognition Labs | C14: Antler US | D14: US Spring 2026 Showcase | E14: not disclosed | F14: taken from a third-party list that was not verified against Antler | G14: USA | H14: USA | I14: unknown | K14: https://agentjesse.ai/lists/antler-2026-cohort-companies | L14: low
A15: Tests and monitors voice AI agents before companies put them in front of customers. | B15: SuperBryn | C15: Google for Startups Accelerator: India | D15: 2026 cohort (announced 2026-07-08) | E15: no cash | F15: equity-free 3-month program with mentoring and credits; most companies here already have a product and earlier funding | G15: Bengaluru, India | H15: India | I15: yes | K15: https://inc42.com/buzz/meet-the-20-startups-selected-for-googles-india-startup-accelerator-2026/ | L15: medium
A16: Helps companies measure and manage their cyber-security risk in money terms. | B16: Zeron | C16: Google for Startups Accelerator: India | D16: 2026 cohort (announced 2026-07-08) | E16: no cash | F16: equity-free 3-month program with mentoring and credits; most companies here already have a product and earlier funding | G16: Mumbai, India | H16: India | I16: yes | K16: https://inc42.com/buzz/meet-the-20-startups-selected-for-googles-india-startup-accelerator-2026/ | L16: medium
A17: Tests AI agents against thousands of simulated situations to check they follow company policy. | B17: Reinforce Labs | C17: Peak XV Surge | D17: Surge 12 (Sep 2026) | E17: not disclosed | F17: Surge invests up to $5M per startup; the figure shown is funding as listed by Inc42, the Surge share is not disclosed | G17: Palo Alto, USA | H17: USA | I17: unknown | K17: https://inc42.com/buzz/meet-the-startups-from-peak-xvs-surge-12/ | L17: medium
A18: Software that turns existing CCTV cameras into live AI alerts for falls, fires and unauthorised entry. | B18: Aeyi | C18: WTFund (Nikhil Kamath) | D18: Cohort 3, Class of 2026 | E18: ₹20 lakh | F18: grant, no equity taken | G18: India (city not stated) | H18: India | I18: yes | K18: https://odisha.plus/2026/01/nikhil-kamath-wtfund-young-founders-deeptech-healthcare-india/ | L18: medium
A19: One security platform that protects a company's AI and software supply chain. | B19: O3 Security | C19: WTFund (Nikhil Kamath) | D19: Cohort 3, Class of 2026 | E19: ₹20 lakh | F19: grant, no equity taken | G19: India (city not stated) | H19: India | I19: yes | K19: https://odisha.plus/2026/01/nikhil-kamath-wtfund-young-founders-deeptech-healthcare-india/ | L19: medium
A20: AI models without the usual refusals, for security testing. | B20: Abliteration.ai | C20: a16z Speedrun | D20: SR007 (Jul-Oct 2026) | E20: up to $1M | F20: standard Speedrun deal: $500K for 10% now + $500K in the next round | G20: not stated (program runs in San Francisco) | H20: Unknown | I20: unknown | K20: https://www.frontrun.vc/blog/a16z-speedrun-cohort-007-companies/ | L20: medium
A21: Replay and monitoring of what an AI agent did in a session. | B21: AgentCat | C21: a16z Speedrun | D21: SR007 (Jul-Oct 2026) | E21: up to $1M | F21: standard Speedrun deal: $500K for 10% now + $500K in the next round | G21: not stated (program runs in San Francisco) | H21: Unknown | I21: unknown | K21: https://www.frontrun.vc/blog/a16z-speedrun-cohort-007-companies/ | L21: medium
A22: Always-on security for AI agents that catches flaws before release. | B22: Kairo | C22: a16z Speedrun | D22: SR007 (Jul-Oct 2026) | E22: up to $1M | F22: standard Speedrun deal: $500K for 10% now + $500K in the next round | G22: not stated (program runs in San Francisco) | H22: Unknown | I22: unknown | K22: https://www.frontrun.vc/blog/a16z-speedrun-cohort-007-companies/ | L22: medium
A23: Keeps AI agents learning after they are launched. | B23: Proper Motion | C23: a16z Speedrun | D23: SR007 (Jul-Oct 2026) | E23: up to $1M | F23: standard Speedrun deal: $500K for 10% now + $500K in the next round | G23: not stated (program runs in San Francisco) | H23: Unknown | I23: unknown | K23: https://www.frontrun.vc/blog/a16z-speedrun-cohort-007-companies/ | L23: medium

Sheet Coding and dev tools
A1: Idea in simple words | B1: Startup | C1: Funded by | D1: Batch / cohort | E1: Funding | F1: What the funding number means | G1: Based in | H1: India / USA / Other | I1: Indian founders? | J1: Website | K1: Source | L1: Confidence
A2: A place to host code (like GitHub) rebuilt for AI-written code. | B2: /dev/fast | C2: Y Combinator | D2: YC Winter 2026 | E2: $500K | F2: standard YC deal ($125K for 7% + $375K uncapped SAFE); the startup's own round is not public | G2: San Francisco, CA, USA | H2: USA | I2: unknown | J2: https://dev.fast | K2: https://www.ycombinator.com/companies/devfast | L2: high
A3: An AI coding agent for C and C++. Founded by two IIT Delhi computer science graduates whose earlier legal-AI startup was acquired. | B3: ByteAsk | C3: Y Combinator | D3: YC Fall 2026 | E3: $1M | F3: pre-seed led by YC with Entrepreneur First and angels (reported 2026-09-27) | G3: San Francisco, CA, USA | H3: USA | I3: yes | J3: https://byteask.ai/ | K3: https://www.ycombinator.com/companies/byteask ; https://americanbazaaronline.com/2026/09/27/iit-delhi-graduates-byteask-1-million-funding-488891/ | L3: high
A4: An AI coding agent that asks questions and works with you instead of guessing. | B4: Compyle | C4: Y Combinator | D4: YC Fall 2025 | E4: $500K | F4: standard YC deal ($125K for 7% + $375K uncapped SAFE); the startup's own round is not public | G4: San Francisco, CA, USA | H4: USA | I4: unknown | J4: https://compyle.ai | K4: https://www.ycombinator.com/companies/compyle | L4: high
A5: Build a mobile app by describing it. | B5: Fastshot | C5: Y Combinator | D5: YC Fall 2025 | E5: $500K | F5: standard YC deal ($125K for 7% + $375K uncapped SAFE); the startup's own round is not public | G5: Thessaloniki, Greece | H5: Other | I5: unknown | J5: https://www.fastshot.ai/ | K5: https://www.ycombinator.com/companies/fastshot | L5: high
A6: An AI engineer that debugs and fixes live software problems as they happen. | B6: HyperProbe | C6: Y Combinator | D6: YC Summer 2026 | E6: $500K | F6: standard YC deal ($125K for 7% + $375K uncapped SAFE); the startup's own round is not public | G6: San Francisco, CA, USA | H6: USA | I6: reported | J6: https://hyperprobe.co | K6: https://www.ycombinator.com/companies/hyperprobe | L6: high
A7: AI that investigates and fixes outages for engineering teams. | B7: IncidentFox | C7: Y Combinator | D7: YC Winter 2026 | E7: $500K | F7: standard YC deal ($125K for 7% + $375K uncapped SAFE); the startup's own round is not public | G7: San Francisco, CA, USA | H7: USA | I7: unknown | J7: https://incidentfox.ai | K7: https://www.ycombinator.com/companies/brownie | L7: high
A8: Lets non-engineers build real product features with AI, while engineers review the code. | B8: LightSprint | C8: Y Combinator | D8: YC Spring 2026 | E8: $500K | F8: standard YC deal ($125K for 7% + $375K uncapped SAFE); the startup's own round is not public | G8: San Francisco, CA, USA | H8: USA | I8: unknown | J8: https://lightsprint.ai | K8: https://www.ycombinator.com/companies/lightsprint | L8: high
A9: Finds problems in running software from its logs and proposes fixes inside Slack. | B9: Sazabi | C9: Y Combinator | D9: YC Spring 2026 | E9: $500K | F9: standard YC deal ($125K for 7% + $375K uncapped SAFE); the startup's own round is not public | G9: San Francisco, CA, USA | H9: USA | I9: unknown | J9: https://www.sazabi.com/ | K9: https://www.ycombinator.com/companies/sazabi | L9: high
A10: Search that helps people and AI understand very large codebases. | B10: Sourcebot | C10: Y Combinator | D10: YC Fall 2025 | E10: $500K | F10: standard YC deal ($125K for 7% + $375K uncapped SAFE); the startup's own round is not public | G10: San Francisco, CA, USA | H10: USA | I10: unknown | J10: https://www.sourcebot.dev/ | K10: https://www.ycombinator.com/companies/sourcebot | L10: high
A11: Run and manage 100+ AI coding agents at once. | B11: Superset | C11: Y Combinator | D11: YC Spring 2026 | E11: $500K | F11: standard YC deal ($125K for 7% + $375K uncapped SAFE); the startup's own round is not public | G11: San Francisco, CA, USA | H11: USA | I11: unknown | J11: https://www.superset.sh/ | K11: https://www.ycombinator.com/companies/superset | L11: high
A12: AI that tests your app like a user and catches bugs before release. | B12: TesterArmy | C12: Y Combinator | D12: YC Spring 2026 | E12: $500K | F12: standard YC deal ($125K for 7% + $375K uncapped SAFE); the startup's own round is not public | G12: Warsaw, Masovian Voivodeship, Poland; Remote | H12: Other | I12: unknown | J12: https://tester.army | K12: https://www.ycombinator.com/companies/testerarmy | L12: high
A13: AI that writes the software inside connected devices (firmware). | B13: CraftifAI | C13: Google for Startups Accelerator: India | D13: 2026 cohort (announced 2026-07-08) | E13: no cash | F13: equity-free 3-month program with mentoring and credits; most companies here already have a product and earlier funding | G13: Bengaluru, India | H13: India | I13: yes | K13: https://inc42.com/buzz/meet-the-20-startups-selected-for-googles-india-startup-accelerator-2026/ | L13: medium
A14: AI models and coding tools for low-level system and device software. | B14: H2Loop AI | C14: Google for Startups Accelerator: India | D14: 2026 cohort (announced 2026-07-08) | E14: no cash | F14: equity-free 3-month program with mentoring and credits; most companies here already have a product and earlier funding | G14: Bengaluru, India | H14: India | I14: yes | K14: https://inc42.com/buzz/meet-the-20-startups-selected-for-googles-india-startup-accelerator-2026/ | L14: medium
A15: Maps a large codebase so AI agents can understand it. | B15: PotpieAI | C15: Google for Startups Accelerator: India | D15: 2026 cohort (announced 2026-07-08) | E15: no cash | F15: equity-free 3-month program with mentoring and credits; most companies here already have a product and earlier funding | G15: San Francisco, USA | H15: USA | I15: yes | K15: https://inc42.com/buzz/meet-the-20-startups-selected-for-googles-india-startup-accelerator-2026/ | L15: medium
A16: One-click cloud computers for developers that can be handed over to AI agents. | B16: Cube Computer | C16: a16z Speedrun | D16: SR007 (Jul-Oct 2026) | E16: up to $1M | F16: standard Speedrun deal: $500K for 10% now + $500K in the next round | G16: not stated (program runs in San Francisco) | H16: Unknown | I16: unknown | K16: https://www.frontrun.vc/blog/a16z-speedrun-cohort-007-companies/ | L16: medium
A17: Software that improves itself from how people use it, with AI agents doing the improving. | B17: Elu | C17: a16z Speedrun | D17: SR007 (Jul-Oct 2026) | E17: up to $1M | F17: standard Speedrun deal: $500K for 10% now + $500K in the next round | G17: not stated (program runs in San Francisco) | H17: Unknown | I17: unknown | K17: https://www.frontrun.vc/blog/a16z-speedrun-cohort-007-companies/ | L17: medium
A18: Simulated users that react to your software before you ship it. | B18: Tenera | C18: a16z Speedrun | D18: SR007 (Jul-Oct 2026) | E18: up to $1M | F18: standard Speedrun deal: $500K for 10% now + $500K in the next round | G18: not stated (program runs in San Francisco) | H18: Unknown | I18: unknown | K18: https://www.frontrun.vc/blog/a16z-speedrun-cohort-007-companies/ | L18: medium

Sheet Training data
A1: Idea in simple words | B1: Startup | C1: Funded by | D1: Batch / cohort | E1: Funding | F1: What the funding number means | G1: Based in | H1: India / USA / Other | I1: Indian founders? | J1: Website | K1: Source | L1: Confidence
A2: Recordings of real human movement, sold to companies training humanoid robots. | B2: Asimov | C2: Y Combinator | D2: YC Winter 2026 | E2: $500K | F2: standard YC deal ($125K for 7% + $375K uncapped SAFE); the startup's own round is not public | G2: San Francisco, CA, USA; Remote | H2: USA | I2: unknown | J2: https://tryasimov.ai/ | K2: https://www.ycombinator.com/companies/asimov | L2: high
A3: A crowdsourced test that ranks how well AI models can use a computer. Reports revenue going from zero to $60K in two weeks. | B3: CoArena | C3: Y Combinator | D3: YC Summer 2026 | E3: $500K | F3: standard YC deal ($125K for 7% + $375K uncapped SAFE); the startup's own round is not public | G3: San Francisco, CA, USA | H3: USA | I3: reported | J3: http://coarena.ai | K3: https://www.ycombinator.com/companies/coarena | L3: high
A4: Collects and prepares training data for robot AI under strict security. Reports close to seven-figure revenue within 30 days. | B4: Datoric | C4: Y Combinator | D4: YC Summer 2026 | E4: $500K | F4: standard YC deal ($125K for 7% + $375K uncapped SAFE); the startup's own round is not public | G4: San Francisco, CA, USA | H4: USA | I4: reported | J4: https://www.datoric.com | K4: https://www.ycombinator.com/companies/datoric | L4: high
A5: Practice simulations where robot AI can learn. | B5: Fern | C5: Y Combinator | D5: YC Winter 2026 | E5: $500K | F5: standard YC deal ($125K for 7% + $375K uncapped SAFE); the startup's own round is not public | G5: not stated | H5: Other | I5: unknown | J5: https://fern.bot | K5: https://www.ycombinator.com/companies/fern-bot | L5: high
A6: A wristband that senses force, used to record how hands work so robots can learn it. | B6: Hemlock | C6: Y Combinator | D6: YC Fall 2026 | E6: $500K | F6: standard YC deal ($125K for 7% + $375K uncapped SAFE); the startup's own round is not public | G6: San Francisco, CA, USA | H6: USA | I6: unknown | J6: https://hemlock.inc | K6: https://www.ycombinator.com/companies/hemlock | L6: high
A7: Screen recordings of professionals using design and business software, sold to AI labs to train models that use computers. | B7: Markov | C7: Y Combinator | D7: YC Summer 2026 | E7: $500K | F7: standard YC deal ($125K for 7% + $375K uncapped SAFE); the startup's own round is not public | G7: Bengaluru, KA, India | H7: India | I7: yes | J7: https://www.markovstudios.com/ | K7: https://www.ycombinator.com/companies/markov | L7: high
A8: Pays real businesses to record their work, then sells it as robot training data. | B8: Praxis Robotics | C8: Y Combinator | D8: YC Summer 2026 | E8: $500K | F8: standard YC deal ($125K for 7% + $375K uncapped SAFE); the startup's own round is not public | G8: San Francisco, CA, USA | H8: USA | I8: reported | J8: https://www.praxisrobotics.io | K8: https://www.ycombinator.com/companies/praxis-robotics | L8: high
A9: Expert-written science and maths reasoning examples, sold to AI labs as training data. | B9: Sciloop | C9: Y Combinator | D9: YC Fall 2025 | E9: $500K | F9: standard YC deal ($125K for 7% + $375K uncapped SAFE); the startup's own round is not public | G9: San Francisco, CA, USA | H9: USA | I9: unknown | J9: https://sciloop.dev | K9: https://www.ycombinator.com/companies/sciloop | L9: high
A10: Training data for AI speech models. | B10: The Agentic Data Co. | C10: Y Combinator | D10: YC Fall 2026 | E10: $500K | F10: standard YC deal ($125K for 7% + $375K uncapped SAFE); the startup's own round is not public | G10: San Francisco, CA, USA | H10: USA | I10: unknown | J10: https://theagenticdatacompany.com | K10: https://www.ycombinator.com/companies/the-agentic-data-co | L10: high
A11: Simulated worlds where science and healthcare AI agents can practise. | B11: Delightful AI | C11: a16z Speedrun | D11: SR007 (Jul-Oct 2026) | E11: up to $1M | F11: standard Speedrun deal: $500K for 10% now + $500K in the next round | G11: not stated (program runs in San Francisco) | H11: Unknown | I11: unknown | K11: https://www.frontrun.vc/blog/a16z-speedrun-cohort-007-companies/ | L11: medium
A12: Better data collection for training robots. | B12: Munari | C12: a16z Speedrun | D12: SR007 (Jul-Oct 2026) | E12: up to $1M | F12: standard Speedrun deal: $500K for 10% now + $500K in the next round | G12: not stated (program runs in San Francisco) | H12: Unknown | I12: unknown | K12: https://www.frontrun.vc/blog/a16z-speedrun-cohort-007-companies/ | L12: medium
A13: Turns records of AI agent runs into training data for companies. | B13: SenseLab | C13: a16z Speedrun | D13: SR007 (Jul-Oct 2026) | E13: up to $1M | F13: standard Speedrun deal: $500K for 10% now + $500K in the next round | G13: not stated (program runs in San Francisco) | H13: Unknown | I13: unknown | K13: https://www.frontrun.vc/blog/a16z-speedrun-cohort-007-companies/ | L13: medium

Sheet Models and compute
A1: Idea in simple words | B1: Startup | C1: Funded by | D1: Batch / cohort | E1: Funding | F1: What the funding number means | G1: Based in | H1: India / USA / Other | I1: Indian founders? | J1: Website | K1: Source | L1: Confidence
A2: Puts idle GPU computing power to use. | B2: Expanse | C2: Y Combinator | D2: YC Spring 2026 | E2: $500K | F2: standard YC deal ($125K for 7% + $375K uncapped SAFE); the startup's own round is not public | G2: London, England, United Kingdom | H2: Other | I2: unknown | J2: https://expanse.sh | K2: https://www.ycombinator.com/companies/expanse | L2: high
A3: Builds small, cheap AI models that understand video for one specific job and can run on a company's own machines. | B3: Kailash Labs | C3: Y Combinator | D3: YC Fall 2026 | E3: $500K | F3: standard YC deal ($125K for 7% + $375K uncapped SAFE); the startup's own round is not public | G3: Bengaluru, KA, India | H3: India | I3: yes | J3: https://www.kailashlabs.com/ | K3: https://www.ycombinator.com/companies/kailash-labs | L3: high
A4: Runs open AI models for European customers with data kept private. | B4: Munito AI | C4: Y Combinator | D4: YC Fall 2026 | E4: $500K | F4: standard YC deal ($125K for 7% + $375K uncapped SAFE); the startup's own round is not public | G4: Paris, Île-de-France, France; Remote | H4: Other | I4: unknown | J4: https://munito.ai | K4: https://www.ycombinator.com/companies/munito-ai | L4: high
A5: A very cheap and fast cloud for running AI models. | B5: OneTriangle | C5: Y Combinator | D5: YC Summer 2026 | E5: $500K | F5: standard YC deal ($125K for 7% + $375K uncapped SAFE); the startup's own round is not public | G5: San Francisco, CA, USA | H5: USA | I5: reported | J5: https://onetriangle.ai/ | K5: https://www.ycombinator.com/companies/onetriangle | L5: high
A6: Trains human brain cells in a lab as a low-energy alternative to GPU chips. | B6: Parasma | C6: Y Combinator | D6: YC Summer 2026 | E6: $500K | F6: standard YC deal ($125K for 7% + $375K uncapped SAFE); the startup's own round is not public | G6: San Francisco, CA, USA | H6: USA | I6: unknown | J6: https://parasma.com | K6: https://www.ycombinator.com/companies/parasma | L6: high
A7: Search that helps AI coding agents find the right parts of a codebase before they write code. | B7: Perseus | C7: Y Combinator | D7: YC Fall 2025 | E7: $500K | F7: standard YC deal ($125K for 7% + $375K uncapped SAFE); the startup's own round is not public | G7: Bengaluru, KA, India | H7: India | I7: yes | J7: https://perseus.computer | K7: https://www.ycombinator.com/companies/perseus | L7: high
A8: Runs open AI models fast on a phone, on a company's own servers, or in the cloud. | B8: RunAnywhere | C8: Y Combinator | D8: YC Winter 2026 | E8: $500K | F8: standard YC deal ($125K for 7% + $375K uncapped SAFE); the startup's own round is not public | G8: San Francisco, CA, USA | H8: USA | I8: unknown | J8: https://www.runanywhere.ai/ | K8: https://www.ycombinator.com/companies/runanywhere | L8: high
A9: A decentralised cloud for running AI workloads and blockchain apps. | B9: CreateOS by NodeOps | C9: Google for Startups Accelerator: India | D9: 2026 cohort (announced 2026-07-08) | E9: no cash | F9: equity-free 3-month program with mentoring and credits; most companies here already have a product and earlier funding | G9: Bengaluru, India | H9: India | I9: yes | K9: https://inc42.com/buzz/meet-the-20-startups-selected-for-googles-india-startup-accelerator-2026/ | L9: medium
A10: Infrastructure for running open-source AI models fast. | B10: Pipeshift | C10: Google for Startups Accelerator: India | D10: 2026 cohort (announced 2026-07-08) | E10: no cash | F10: equity-free 3-month program with mentoring and credits; most companies here already have a product and earlier funding | G10: San Francisco, USA and Bengaluru, India | H10: USA | I10: yes | K10: https://inc42.com/buzz/meet-the-20-startups-selected-for-googles-india-startup-accelerator-2026/ | L10: medium
A11: AI agents that run experiments to improve other AI models. | B11: hiloop | C11: Peak XV Surge | D11: Surge 12 (Sep 2026) | E11: not disclosed | F11: Surge invests up to $5M per startup; the figure shown is funding as listed by Inc42, the Surge share is not disclosed | G11: San Francisco, USA | H11: USA | I11: unknown | K11: https://inc42.com/buzz/meet-the-startups-from-peak-xvs-surge-12/ | L11: medium
A12: Software that lets AI run on the small computers inside robots, cars and drones. | B12: Opt32 | C12: Thiel Fellowship | D12: 2026 class (announced 2026-04-21) | E12: $250K | F12: grant paid over two years, no equity taken | G12: New York, USA (fellow's location) | H12: USA | I12: unknown | K12: https://insights.tryspecter.com/thiel-fellows-2026/ | L12: medium
A13: Research on AI models that learn actively from the internet. | B13: Standard Intelligence | C13: Thiel Fellowship | D13: 2026 class (announced 2026-04-21) | E13: $250K | F13: grant paid over two years, no equity taken | G13: North Carolina, USA (fellow's location) | H13: USA | I13: unknown | K13: https://insights.tryspecter.com/thiel-fellows-2026/ | L13: medium
A14: Many small AI models working together, cheaper than one large model. | B14: Banbury Road | C14: a16z Speedrun | D14: SR007 (Jul-Oct 2026) | E14: up to $1M | F14: standard Speedrun deal: $500K for 10% now + $500K in the next round | G14: not stated (program runs in San Francisco) | H14: Unknown | I14: unknown | K14: https://www.frontrun.vc/blog/a16z-speedrun-cohort-007-companies/ | L14: medium
A15: Keeps fleets of GPUs busy and productive. | B15: Harbor AI | C15: a16z Speedrun | D15: SR007 (Jul-Oct 2026) | E15: up to $1M | F15: standard Speedrun deal: $500K for 10% now + $500K in the next round | G15: not stated (program runs in San Francisco) | H15: Unknown | I15: unknown | K15: https://www.frontrun.vc/blog/a16z-speedrun-cohort-007-companies/ | L15: medium
A16: Software that makes AI models run faster and cheaper on existing hardware. | B16: Hoid | C16: a16z Speedrun | D16: SR007 (Jul-Oct 2026) | E16: up to $1M | F16: standard Speedrun deal: $500K for 10% now + $500K in the next round | G16: not stated (program runs in San Francisco) | H16: Unknown | I16: unknown | K16: https://www.frontrun.vc/blog/a16z-speedrun-cohort-007-companies/ | L16: medium
A17: A research lab that puts its own AI models to work in critical industries. | B17: Ripline | C17: a16z Speedrun | D17: SR007 (Jul-Oct 2026) | E17: up to $1M | F17: standard Speedrun deal: $500K for 10% now + $500K in the next round | G17: not stated (program runs in San Francisco) | H17: Unknown | I17: unknown | K17: https://www.frontrun.vc/blog/a16z-speedrun-cohort-007-companies/ | L17: medium
A18: AI models aimed at invention and scientific discovery. | B18: Superintelligence Foundry | C18: a16z Speedrun | D18: SR007 (Jul-Oct 2026) | E18: up to $1M | F18: standard Speedrun deal: $500K for 10% now + $500K in the next round | G18: not stated (program runs in San Francisco) | H18: Unknown | I18: unknown | K18: https://www.frontrun.vc/blog/a16z-speedrun-cohort-007-companies/ | L18: medium
A19: Company-owned AI models meant to beat rented ones. | B19: Zorbe | C19: a16z Speedrun | D19: SR007 (Jul-Oct 2026) | E19: up to $1M | F19: standard Speedrun deal: $500K for 10% now + $500K in the next round | G19: not stated (program runs in San Francisco) | H19: Unknown | I19: unknown | K19: https://www.frontrun.vc/blog/a16z-speedrun-cohort-007-companies/ | L19: medium

Sheet Voice AI
A1: Idea in simple words | B1: Startup | C1: Funded by | D1: Batch / cohort | E1: Funding | F1: What the funding number means | G1: Based in | H1: India / USA / Other | I1: Indian founders? | J1: Website | K1: Source | L1: Confidence
A2: Voice AI for Indian businesses: automated phone calls for sales, support and collections, in Indian languages. | B2: Bolna AI | C2: Y Combinator | D2: YC Fall 2025 | E2: $500K | F2: standard YC deal ($125K for 7% + $375K uncapped SAFE); the startup's own round is not public | G2: Bengaluru, KA, India | H2: India | I2: yes | J2: https://bolna.ai | K2: https://www.ycombinator.com/companies/bolna-ai | L2: high
A3: AI voice agents that plug into a company's own in-house phone system. | B3: Callab AI | C3: Y Combinator | D3: YC Spring 2026 | E3: $500K | F3: standard YC deal ($125K for 7% + $375K uncapped SAFE); the startup's own round is not public | G3: San Francisco, CA, USA | H3: USA | I3: unknown | J3: https://callab.ai | K3: https://www.ycombinator.com/companies/callab-ai | L3: high
A4: Makes voice AI respond faster. | B4: Hopper | C4: Y Combinator | D4: YC Fall 2026 | E4: $500K | F4: standard YC deal ($125K for 7% + $375K uncapped SAFE); the startup's own round is not public | G4: San Francisco, CA, USA | H4: USA | I4: unknown | J4: https://withhopper.com | K4: https://www.ycombinator.com/companies/hopper | L4: high
A5: Builds general-purpose speech AI models. | B5: Kalpa Labs | C5: Y Combinator | D5: YC Fall 2025 | E5: $500K | F5: standard YC deal ($125K for 7% + $375K uncapped SAFE); the startup's own round is not public | G5: San Francisco, CA, USA | H5: USA | I5: unknown | J5: https://kalpalabs.ai/ | K5: https://www.ycombinator.com/companies/kalpa-labs | L5: high
A6: A voice AI model that runs on the customer's own servers and supports 30+ languages. | B6: KugelAudio | C6: Y Combinator | D6: YC Spring 2026 | E6: $500K | F6: standard YC deal ($125K for 7% + $375K uncapped SAFE); the startup's own round is not public | G6: Berlin, Berlin, Germany | H6: Other | I6: unknown | J6: https://kugelaudio.com/en | K6: https://www.ycombinator.com/companies/kugelaudio | L6: high
A7: Voice agents that speak many languages for phone calls. | B7: Samora AI | C7: Y Combinator | D7: YC Winter 2026 | E7: $500K | F7: standard YC deal ($125K for 7% + $375K uncapped SAFE); the startup's own round is not public | G7: not stated | H7: Other | I7: unknown | J7: https://samora.ai/ | K7: https://www.ycombinator.com/companies/samora-ai | L7: high
A8: One connection that sends each phone call to whichever speech model is best for it. | B8: Speko | C8: Y Combinator | D8: YC Summer 2026 | E8: $500K | F8: standard YC deal ($125K for 7% + $375K uncapped SAFE); the startup's own round is not public | G8: San Francisco, CA, USA | H8: USA | I8: unknown | J8: https://speko.ai/?utm_source=ycombinator&utm_medium=profile | K8: https://www.ycombinator.com/companies/speko | L8: high
A9: Voice AI for large call-centre operations. | B9: Persistence Labs | C9: Accel Atoms + Google AI Futures Fund | D9: Atoms AI Cohort 2026 (Mar-Jun 2026) | E9: up to $2M | F9: co-investment by Accel and Google AI Futures Fund, plus up to $350K compute credits; per-startup amount not disclosed | G9: not stated (program is for Indian and Indian-origin founders anywhere) | H9: Unknown | I9: yes | K9: https://www.outlookbusiness.com/deeptech/five-startups-to-join-accel-atoms-and-googles-ai-futures-fund-ai-cohort-2026 | L9: medium
A10: Voice AI workers for US insurance companies. | B10: Infer.so | C10: Antler India | D10: Portfolio shown on antler.co/india (read 2026-10-13) | E10: up to ₹4 crore (~$425K-$470K) | F10: standard Antler India deal for 11%; amount per startup not disclosed | G10: India | H10: India | I10: yes | K10: https://www.antler.co/india | L10: high
A11: Voice AI for enterprises that works across many Indian languages. | B11: Navana.ai | C11: Antler India | D11: Portfolio shown on antler.co/india (read 2026-10-13) | E11: up to ₹4 crore (~$425K-$470K) | F11: standard Antler India deal for 11%; amount per startup not disclosed | G11: India | H11: India | I11: yes | K11: https://www.antler.co/india | L11: high
A12: Speech models that understand tone and intent, not just words. | B12: Oruk | C12: a16z Speedrun | D12: SR007 (Jul-Oct 2026) | E12: up to $1M | F12: standard Speedrun deal: $500K for 10% now + $500K in the next round | G12: not stated (program runs in San Francisco) | H12: Unknown | I12: unknown | K12: https://www.frontrun.vc/blog/a16z-speedrun-cohort-007-companies/ | L12: medium

Sheet Robotics
A1: Idea in simple words | B1: Startup | C1: Funded by | D1: Batch / cohort | E1: Funding | F1: What the funding number means | G1: Based in | H1: India / USA / Other | I1: Indian founders? | J1: Website | K1: Source | L1: Confidence
A2: A network of people who remotely help robots when they get stuck, with operators in India, Mexico and the US. | B2: Aktoria Robotics | C2: Y Combinator | D2: YC Summer 2026 | E2: $500K | F2: standard YC deal ($125K for 7% + $375K uncapped SAFE); the startup's own round is not public | G2: San Francisco, CA, USA | H2: USA | I2: yes | J2: https://aktoria.com/ | K2: https://www.ycombinator.com/companies/aktoria-robotics | L2: high
A3: AI drones that herd cattle. | B3: Brumby (Formerly GrazeMate) | C3: Y Combinator | D3: YC Winter 2026 | E3: $500K | F3: standard YC deal ($125K for 7% + $375K uncapped SAFE); the startup's own round is not public | G3: Sydney, NSW, Australia | H3: Other | I3: unknown | J3: https://brumby | K3: https://www.ycombinator.com/companies/brumby | L3: high
A4: Self-driving heavy construction robots. Reports about $25M in contracts through 2027. | B4: Cosmic Robotics | C4: Y Combinator | D4: YC Summer 2026 | E4: $500K | F4: standard YC deal ($125K for 7% + $375K uncapped SAFE); the startup's own round is not public | G4: San Francisco, CA, USA | H4: USA | I4: unknown | J4: https://www.cosmicrobotics.com/ | K4: https://www.ycombinator.com/companies/cosmic-robotics | L4: high
A5: Robotic arms that pick and pack online orders. | B5: InLoop Robotics | C5: Y Combinator | D5: YC Spring 2026 | E5: $500K | F5: standard YC deal ($125K for 7% + $375K uncapped SAFE); the startup's own round is not public | G5: BY, Germany | H5: Other | I5: unknown | J5: https://inloop-robotics.com/ | K5: https://www.ycombinator.com/companies/inloop-robotics | L5: high
A6: A $1,688 humanoid home robot. Reported nearly $500K in sales six weeks after launch. | B6: Nori | C6: Y Combinator | D6: YC Summer 2026 | E6: $500K | F6: standard YC deal ($125K for 7% + $375K uncapped SAFE); the startup's own round is not public | G6: San Francisco, CA, USA | H6: USA | I6: unknown | J6: http://norirobotics.com | K6: https://www.ycombinator.com/companies/noril1 | L6: high
A7: A humanoid home robot that does chores, aimed at the price of an iPhone. | B7: Piggy Robotics | C7: Y Combinator | D7: YC Fall 2025 | E7: $500K | F7: standard YC deal ($125K for 7% + $375K uncapped SAFE); the startup's own round is not public | G7: London, England, United Kingdom | H7: Other | I7: unknown | J7: https://piggyrobotics.com | K7: https://www.ycombinator.com/companies/piggy-robotics | L7: high
A8: Robots that maintain and assemble data centers. | B8: Proprio Robotics | C8: Y Combinator | D8: YC Summer 2026 | E8: $500K | F8: standard YC deal ($125K for 7% + $375K uncapped SAFE); the startup's own round is not public | G8: San Francisco, CA, USA | H8: USA | I8: reported | J8: https://www.propriorobotics.com/ | K8: https://www.ycombinator.com/companies/proprio-robotics | L8: high
A9: Robots that unload shipping containers in warehouses. | B9: Servo7 | C9: Y Combinator | D9: YC Winter 2026 | E9: $500K | F9: standard YC deal ($125K for 7% + $375K uncapped SAFE); the startup's own round is not public | G9: Amsterdam, NH, Netherlands | H9: Other | I9: unknown | J9: https://servo7.com | K9: https://www.ycombinator.com/companies/servo7 | L9: high
A10: Humanoid robots that restock shop shelves and pick orders. | B10: Theseus Robotics | C10: Y Combinator | D10: YC Fall 2026 | E10: $500K | F10: standard YC deal ($125K for 7% + $375K uncapped SAFE); the startup's own round is not public | G10: ZH, Switzerland | H10: Other | I10: unknown | J10: https://theseus.bot/ | K10: https://www.ycombinator.com/companies/theseus-robotics | L10: high
A11: Lets AI write and test the code that controls a robot from plain-English instructions. | B11: Waddle Labs | C11: Y Combinator | D11: YC Summer 2026 | E11: $500K | F11: standard YC deal ($125K for 7% + $375K uncapped SAFE); the startup's own round is not public | G11: San Francisco, CA, USA | H11: USA | I11: unknown | J11: https://www.waddlelabs.ai/ | K11: https://www.ycombinator.com/companies/waddle-labs | L11: high
A12: Robots that inspect underground pipes with cameras and mapping sensors. | B12: Puralink | C12: Peak XV Surge | D12: Surge 12 (Sep 2026) | E12: $1.7M | F12: Surge invests up to $5M per startup; the figure shown is funding as listed by Inc42, the Surge share is not disclosed | G12: Sydney, Australia | H12: Other | I12: unknown | K12: https://inc42.com/buzz/meet-the-startups-from-peak-xvs-surge-12/ | L12: medium
A13: Self-driving forklifts, as a first step to faster long-distance logistics. | B13: Cavalla | C13: Thiel Fellowship | D13: 2026 class (announced 2026-04-21) | E13: $250K | F13: grant paid over two years, no equity taken | G13: Birmingham, AL, USA (fellow's location) | H13: USA | I13: unknown | K13: https://insights.tryspecter.com/thiel-fellows-2026/ | L13: medium
A14: A research lab building general AI models for robots. | B14: Sentient Machines | C14: Thiel Fellowship | D14: 2026 class (announced 2026-04-21) | E14: $250K | F14: grant paid over two years, no equity taken | G14: Cork, Ireland (fellow's location) | H14: Other | I14: no | K14: https://insights.tryspecter.com/thiel-fellows-2026/ | L14: medium
A15: Robots that run data centers without staff on the floor. | B15: Cybernetic Physics | C15: a16z Speedrun | D15: SR007 (Jul-Oct 2026) | E15: up to $1M | F15: standard Speedrun deal: $500K for 10% now + $500K in the next round | G15: not stated (program runs in San Francisco) | H15: Unknown | I15: unknown | K15: https://www.frontrun.vc/blog/a16z-speedrun-cohort-007-companies/ | L15: medium
A16: Service and upkeep for robots and self-driving machines. | B16: Motherboard Labs | C16: a16z Speedrun | D16: SR007 (Jul-Oct 2026) | E16: up to $1M | F16: standard Speedrun deal: $500K for 10% now + $500K in the next round | G16: not stated (program runs in San Francisco) | H16: Unknown | I16: unknown | K16: https://www.frontrun.vc/blog/a16z-speedrun-cohort-007-companies/ | L16: medium
A17: AI that gets more work out of autonomous robots. | B17: scaledrive.ai | C17: a16z Speedrun | D17: SR007 (Jul-Oct 2026) | E17: up to $1M | F17: standard Speedrun deal: $500K for 10% now + $500K in the next round | G17: not stated (program runs in San Francisco) | H17: Unknown | I17: unknown | K17: https://www.frontrun.vc/blog/a16z-speedrun-cohort-007-companies/ | L17: medium
A18: Data and rollout tools for robot AI. | B18: Vound | C18: a16z Speedrun | D18: SR007 (Jul-Oct 2026) | E18: up to $1M | F18: standard Speedrun deal: $500K for 10% now + $500K in the next round | G18: not stated (program runs in San Francisco) | H18: Unknown | I18: unknown | K18: https://www.frontrun.vc/blog/a16z-speedrun-cohort-007-companies/ | L18: medium

Sheet Defense and space
A1: Idea in simple words | B1: Startup | C1: Funded by | D1: Batch / cohort | E1: Funding | F1: What the funding number means | G1: Based in | H1: India / USA / Other | I1: Indian founders? | J1: Website | K1: Source | L1: Confidence
A2: Low-cost robots that track and shoot down small drones. $1.6M in sales; investors reportedly valued it above $200M. | B2: 9 Mothers | C2: Y Combinator | D2: YC Spring 2026 | E2: $500K | F2: standard YC deal ($125K for 7% + $375K uncapped SAFE); the startup's own round is not public | G2: Austin, TX, USA | H2: USA | I2: unknown | J2: https://9mothers.com | K2: https://www.ycombinator.com/companies/9-mothers-corporation | L2: high
A3: Cargo planes that fly without a pilot. | B3: Aviern | C3: Y Combinator | D3: YC Fall 2026 | E3: $500K | F3: standard YC deal ($125K for 7% + $375K uncapped SAFE); the startup's own round is not public | G3: Los Angeles, CA, USA | H3: USA | I3: unknown | J3: https://aviern.com/ | K3: https://www.ycombinator.com/companies/aviern | L3: high
A4: Reusable satellites that make products in space and bring them back to Earth. | B4: Dispatch | C4: Y Combinator | D4: YC Spring 2026 | E4: $500K | F4: standard YC deal ($125K for 7% + $375K uncapped SAFE); the startup's own round is not public | G4: San Francisco, CA, USA | H4: USA | I4: unknown | J4: https://dispatch.space/ | K4: https://www.ycombinator.com/companies/dispatch | L4: high
A5: Remote control towers to modernise air traffic control. | B5: General Aviation | C5: Y Combinator | D5: YC Spring 2026 | E5: $500K | F5: standard YC deal ($125K for 7% + $375K uncapped SAFE); the startup's own round is not public | G5: New York City, NY, USA | H5: USA | I5: unknown | J5: https://generalaviation.com | K5: https://www.ycombinator.com/companies/general-aviation | L5: high
A6: Mass-produced military strike drones and counter-drone systems, built locally in allied countries. About $10M revenue. | B6: Isengard Industries Inc | C6: Y Combinator | D6: YC Summer 2026 | E6: $500K | F6: standard YC deal ($125K for 7% + $375K uncapped SAFE); the startup's own round is not public | G6: San Francisco, CA, USA | H6: USA | I6: unknown | J6: http://isengardindustries.com/ | K6: https://www.ycombinator.com/companies/isengard-industries-inc | L6: high
A7: Technology that detects and tracks small drones. | B7: Milliray | C7: Y Combinator | D7: YC Winter 2026 | E7: $500K | F7: standard YC deal ($125K for 7% + $375K uncapped SAFE); the startup's own round is not public | G7: London, England, United Kingdom | H7: Other | I7: unknown | J7: https://milliray.com/ | K7: https://www.ycombinator.com/companies/milliray | L7: high
A8: Navigation for drones that works without GPS. | B8: Streamline Systems | C8: Y Combinator | D8: YC Fall 2026 | E8: $500K | F8: standard YC deal ($125K for 7% + $375K uncapped SAFE); the startup's own round is not public | G8: San Francisco, CA, USA | H8: USA | I8: unknown | J8: https://streamlinesystems.ltd/ | K8: https://www.ycombinator.com/companies/streamline-systems | L8: high
A9: Counter-drone defence systems. | B9: Armory | C9: Antler India | D9: Portfolio shown on antler.co/india (read 2026-10-13) | E9: up to ₹4 crore (~$425K-$470K) | F9: standard Antler India deal for 11%; amount per startup not disclosed | G9: India | H9: India | I9: yes | K9: https://www.antler.co/india | L9: high
A10: Self-flying aircraft that can operate on land and water. | B10: Aspera Industries | C10: Antler India | D10: Portfolio shown on antler.co/india (read 2026-10-13) | E10: up to ₹4 crore (~$425K-$470K) | F10: standard Antler India deal for 11%; amount per startup not disclosed | G10: India | H10: India | I10: yes | K10: https://www.antler.co/india | L10: high
A11: Robots in space that extend satellite life and reduce orbital debris. | B11: InspeCity | C11: Antler India | D11: Portfolio shown on antler.co/india (read 2026-10-13) | E11: up to ₹4 crore (~$425K-$470K) | F11: standard Antler India deal for 11%; amount per startup not disclosed | G11: India | H11: India | I11: yes | K11: https://www.antler.co/india | L11: high
A12: Low-cost modular drones for police and public-safety agencies. | B12: TAV Drones | C12: Antler US | D12: US Spring 2026 Showcase | E12: not disclosed | F12: taken from a third-party list that was not verified against Antler | G12: USA | H12: USA | I12: unknown | K12: https://agentjesse.ai/lists/antler-2026-cohort-companies | L12: low
A13: An electric vertical take-off aircraft company. | B13: Vyobha Aerospace | C13: Emergent Ventures India | D13: 2026 cohorts 16-19 | E13: not disclosed | F13: grant to an individual or project; amounts are not published | G13: India | H13: India | I13: yes | K13: https://marginalrevolution.com/marginalrevolution/2026/04/emergent-ventures-india-16th-cohort.html | L13: medium
A14: Groups of small satellites that detect and track radio signals for defence and shipping. | B14: ULOOK | C14: Peak XV Surge | D14: Surge 12 (Sep 2026) | E14: $2.3M | F14: Surge invests up to $5M per startup; the figure shown is funding as listed by Inc42, the Surge share is not disclosed | G14: Bengaluru, India | H14: India | I14: yes | K14: https://inc42.com/buzz/meet-the-startups-from-peak-xvs-surge-12/ | L14: medium
A15: Defense satellites that return usable answers in minutes. | B15: Galileo Space | C15: a16z Speedrun | D15: SR007 (Jul-Oct 2026) | E15: up to $1M | F15: standard Speedrun deal: $500K for 10% now + $500K in the next round | G15: not stated (program runs in San Francisco) | H15: Unknown | I15: unknown | K15: https://www.frontrun.vc/blog/a16z-speedrun-cohort-007-companies/ | L15: medium
A16: Lasers in orbit for missile defense. | B16: PhotonSpear | C16: a16z Speedrun | D16: SR007 (Jul-Oct 2026) | E16: up to $1M | F16: standard Speedrun deal: $500K for 10% now + $500K in the next round | G16: not stated (program runs in San Francisco) | H16: Unknown | I16: unknown | K16: https://www.frontrun.vc/blog/a16z-speedrun-cohort-007-companies/ | L16: medium

Sheet Industrial and hardware
A1: Idea in simple words | B1: Startup | C1: Funded by | D1: Batch / cohort | E1: Funding | F1: What the funding number means | G1: Based in | H1: India / USA / Other | I1: Indian founders? | J1: Website | K1: Source | L1: Confidence
A2: Business-management software with AI for manufacturers. | B2: Arzana | C2: Y Combinator | D2: YC Spring 2026 | E2: $500K | F2: standard YC deal ($125K for 7% + $375K uncapped SAFE); the startup's own round is not public | G2: New York City, NY, USA | H2: USA | I2: unknown | J2: https://www.arzana.com/ | K2: https://www.ycombinator.com/companies/arzana | L2: high
A3: Nuclear-powered data centers on barges at sea, cooled by seawater. Claims over $4B of customer interest in letters of intent. | B3: Atomarine | C3: Y Combinator | D3: YC Summer 2026 | E3: $500K | F3: standard YC deal ($125K for 7% + $375K uncapped SAFE); the startup's own round is not public | G3: San Francisco, CA, USA | H3: USA | I3: unknown | J3: https://atomarine.co | K3: https://www.ycombinator.com/companies/atomarine | L3: high
A4: AI agents that design analog electronic circuits. | B4: Atrisa | C4: Y Combinator | D4: YC Spring 2026 | E4: $500K | F4: standard YC deal ($125K for 7% + $375K uncapped SAFE); the startup's own round is not public | G4: San Francisco, CA, USA | H4: USA | I4: unknown | J4: https://atrisa.ai | K4: https://www.ycombinator.com/companies/atrisa | L4: high
A5: An AI assistant that helps mechanical engineers design parts. | B5: Aurorin CAD | C5: Y Combinator | D5: YC Winter 2026 | E5: $500K | F5: standard YC deal ($125K for 7% + $375K uncapped SAFE); the startup's own round is not public | G5: San Francisco, CA, USA | H5: USA | I5: unknown | J5: https://aurorincad.com | K5: https://www.ycombinator.com/companies/aurorin-cad | L5: high
A6: Hardware that moves data between AI computers as light, which saves power. | B6: Dipole Labs | C6: Y Combinator | D6: YC Summer 2026 | E6: $500K | F6: standard YC deal ($125K for 7% + $375K uncapped SAFE); the startup's own round is not public | G6: Boston, MA, USA | H6: USA | I6: reported | J6: https://dipolelabs.com/ | K6: https://www.ycombinator.com/companies/dipole-labs | L6: high
A7: AI that operates energy equipment in buildings and plants to cut energy waste. Reports 34 sites deployed. | B7: Edviro | C7: Y Combinator | D7: YC Summer 2026 | E7: $500K | F7: standard YC deal ($125K for 7% + $375K uncapped SAFE); the startup's own round is not public | G7: San Francisco, CA, USA | H7: USA | I7: reported | J7: https://edviroenergy.com | K7: https://www.ycombinator.com/companies/edviro | L7: high
A8: Fully automated quality inspection for consumer-electronics parts. | B8: Hundred | C8: Y Combinator | D8: YC Fall 2026 | E8: $500K | F8: standard YC deal ($125K for 7% + $375K uncapped SAFE); the startup's own round is not public | G8: San Francisco, CA, USA | H8: USA | I8: unknown | J8: http://hundred.systems/ | K8: https://www.ycombinator.com/companies/hundred | L8: high
A9: AI chips with one AI model built permanently into the silicon, to run it much faster. | B9: Lamb Labs | C9: Y Combinator | D9: YC Summer 2026 | E9: $500K | F9: standard YC deal ($125K for 7% + $375K uncapped SAFE); the startup's own round is not public | G9: San Francisco, CA, USA | H9: USA | I9: unknown | J9: http://lamb-labs.com | K9: https://www.ycombinator.com/companies/lamb-labs | L9: high
A10: Very efficient cooling units for data centers. | B10: Madrone | C10: Y Combinator | D10: YC Spring 2026 | E10: $500K | F10: standard YC deal ($125K for 7% + $375K uncapped SAFE); the startup's own round is not public | G10: San Francisco, CA, USA | H10: USA | I10: unknown | J10: https://madrone.cool/ | K10: https://www.ycombinator.com/companies/madrone | L10: high
A11: A phone app with AI that helps factory technicians fix broken machines. | B11: Pairio | C11: Y Combinator | D11: YC Spring 2026 | E11: $500K | F11: standard YC deal ($125K for 7% + $375K uncapped SAFE); the startup's own round is not public | G11: BY, Germany | H11: Other | I11: unknown | J11: https://pairio.com | K11: https://www.ycombinator.com/companies/pairio | L11: high
A12: An AI-automated factory that assembles circuit boards. | B12: Tenet Industries | C12: Y Combinator | D12: YC Spring 2026 | E12: $500K | F12: standard YC deal ($125K for 7% + $375K uncapped SAFE); the startup's own round is not public | G12: Stockholm, Stockholm County, Sweden | H12: Other | I12: unknown | J12: https://www.tenetindustries.com | K12: https://www.ycombinator.com/companies/tenet-industries | L12: high
A13: Takes over the whole parts-buying process for hardware teams: quotes, payment, shipping, customs and stock tracking. | B13: Waybill | C13: Y Combinator | D13: YC Summer 2026 | E13: $500K | F13: standard YC deal ($125K for 7% + $375K uncapped SAFE); the startup's own round is not public | G13: Gurugram, HR, India | H13: India | I13: yes | J13: https://www.waybill.to/ | K13: https://www.ycombinator.com/companies/waybill | L13: high
A14: Factory automation for precision car and aerospace manufacturing. | B14: LevelPlane | C14: Accel Atoms + Google AI Futures Fund | D14: Atoms AI Cohort 2026 (Mar-Jun 2026) | E14: up to $2M | F14: co-investment by Accel and Google AI Futures Fund, plus up to $350K compute credits; per-startup amount not disclosed | G14: not stated (program is for Indian and Indian-origin founders anywhere) | H14: Unknown | I14: yes | K14: https://www.outlookbusiness.com/deeptech/five-startups-to-join-accel-atoms-and-googles-ai-futures-fund-ai-cohort-2026 | L14: medium
A15: Green-hydrogen engines for aviation and shipping. | B15: Green Aero Propulsion | C15: Antler India | D15: Portfolio shown on antler.co/india (read 2026-10-13) | E15: up to ₹4 crore (~$425K-$470K) | F15: standard Antler India deal for 11%; amount per startup not disclosed | G15: India | H15: India | I15: yes | K15: https://www.antler.co/india | L15: high
A16: AI that inspects power lines more cheaply than laser scanning. | B16: Kanopy AI | C16: Antler US | D16: US Spring 2026 Showcase | E16: not disclosed | F16: taken from a third-party list that was not verified against Antler | G16: USA | H16: USA | I16: unknown | K16: https://agentjesse.ai/lists/antler-2026-cohort-companies | L16: low
A17: AI-driven heating and cooling controls for commercial buildings. | B17: Simply Agnostic Controls | C17: Antler US | D17: US Spring 2026 Showcase | E17: not disclosed | F17: taken from a third-party list that was not verified against Antler | G17: USA | H17: USA | I17: unknown | K17: https://agentjesse.ai/lists/antler-2026-cohort-companies | L17: low
A18: An AI copilot for mechanical engineers working in CAD. | B18: Tandem | C18: Antler US | D18: US Spring 2026 Showcase | E18: not disclosed | F18: taken from a third-party list that was not verified against Antler | G18: USA | H18: USA | I18: unknown | K18: https://agentjesse.ai/lists/antler-2026-cohort-companies | L18: low
A19: Sensors and AI that monitor air quality and water levels street by street. | B19: Aurassure | C19: Google for Startups Accelerator: India | D19: 2026 cohort (announced 2026-07-08) | E19: no cash | F19: equity-free 3-month program with mentoring and credits; most companies here already have a product and earlier funding | G19: Bhubaneswar, India | H19: India | I19: yes | K19: https://inc42.com/buzz/meet-the-20-startups-selected-for-googles-india-startup-accelerator-2026/ | L19: medium
A20: AI that helps companies measure and cut their carbon emissions. | B20: Fitsol | C20: Google for Startups Accelerator: India | D20: 2026 cohort (announced 2026-07-08) | E20: no cash | F20: equity-free 3-month program with mentoring and credits; most companies here already have a product and earlier funding | G20: Delhi NCR, India | H20: India | I20: yes | K20: https://inc42.com/buzz/meet-the-20-startups-selected-for-googles-india-startup-accelerator-2026/ | L20: medium
A21: Cameras and AI that inspect products for defects on factory lines. | B21: Jidoka | C21: Google for Startups Accelerator: India | D21: 2026 cohort (announced 2026-07-08) | E21: no cash | F21: equity-free 3-month program with mentoring and credits; most companies here already have a product and earlier funding | G21: Chennai, India | H21: India | I21: yes | K21: https://inc42.com/buzz/meet-the-20-startups-selected-for-googles-india-startup-accelerator-2026/ | L21: medium
A22: Smart wearables and safety gear for frontline industrial workers. | B22: Proxgy | C22: Google for Startups Accelerator: India | D22: 2026 cohort (announced 2026-07-08) | E22: no cash | F22: equity-free 3-month program with mentoring and credits; most companies here already have a product and earlier funding | G22: Delhi NCR, India | H22: India | I22: yes | K22: https://inc42.com/buzz/meet-the-20-startups-selected-for-googles-india-startup-accelerator-2026/ | L22: medium
A23: A desktop machine that places components on circuit boards for hardware prototyping. | B23: Placestation | C23: WTFund (Nikhil Kamath) | D23: Cohort 3, Class of 2026 | E23: ₹20 lakh | F23: grant, no equity taken | G23: India (city not stated) | H23: India | I23: yes | K23: https://odisha.plus/2026/01/nikhil-kamath-wtfund-young-founders-deeptech-healthcare-india/ | L23: medium
A24: Real-time control software for industrial chemical reactors. | B24: Acaysia | C24: a16z Speedrun | D24: SR007 (Jul-Oct 2026) | E24: up to $1M | F24: standard Speedrun deal: $500K for 10% now + $500K in the next round | G24: not stated (program runs in San Francisco) | H24: Unknown | I24: unknown | K24: https://www.frontrun.vc/blog/a16z-speedrun-cohort-007-companies/ | L24: medium
A25: Turns a plain-language description of a machine into hardware. | B25: Blueprint | C25: a16z Speedrun | D25: SR007 (Jul-Oct 2026) | E25: up to $1M | F25: standard Speedrun deal: $500K for 10% now + $500K in the next round | G25: not stated (program runs in San Francisco) | H25: Unknown | I25: unknown | K25: https://www.frontrun.vc/blog/a16z-speedrun-cohort-007-companies/ | L25: medium
... A29: AI crews that help get power connected and delivered. | B29: Vela Energy | C29: a16z Speedrun | D29: SR007 (Jul-Oct 2026) | E29: up to $1M | F29: standard Speedrun deal: $500K for 10% now + $500K in the next round | G29: not stated (program runs in San Francisco) | H29: Unknown | I29: unknown | K29: https://www.frontrun.vc/blog/a16z-speedrun-cohort-007-companies/ | L29: medium

Sheet Fintech and markets
A1: Idea in simple words | B1: Startup | C1: Funded by | D1: Batch / cohort | E1: Funding | F1: What the funding number means | G1: Based in | H1: India / USA / Other | I1: Indian founders? | J1: Website | K1: Source | L1: Confidence
A2: An exchange to trade contracts on future computing power. | B2: Computable | C2: Y Combinator | D2: YC Summer 2026 | E2: $500K | F2: standard YC deal ($125K for 7% + $375K uncapped SAFE); the startup's own round is not public | G2: New York City, NY, USA | H2: USA | I2: unknown | J2: https://getcomputable.com | K2: https://www.ycombinator.com/companies/computable | L2: high
A3: One connection to trade on all prediction markets such as Kalshi and Polymarket. | B3: Dome | C3: Y Combinator | D3: YC Fall 2025 | E3: $500K | F3: standard YC deal ($125K for 7% + $375K uncapped SAFE); the startup's own round is not public | G3: not stated | H3: Other | I3: unknown | J3: https://domeapi.io | K3: https://www.ycombinator.com/companies/dome | L3: high
A4: AI research agents that help retail traders decide what to trade. | B4: Ekpa | C4: Y Combinator | D4: YC Summer 2026 | E4: $500K | F4: standard YC deal ($125K for 7% + $375K uncapped SAFE); the startup's own round is not public | G4: Boston, MA, USA | H4: USA | I4: reported | J4: https://goekpa.com/ | K4: https://www.ycombinator.com/companies/ekpa | L4: high
A5: Cross-border payments for exporters of physical goods. | B5: HEVN, inc | C5: Y Combinator | D5: YC Spring 2026 | E5: $500K | F5: standard YC deal ($125K for 7% + $375K uncapped SAFE); the startup's own round is not public | G5: San Francisco, CA, USA | H5: USA | I5: unknown | J5: https://gethevn.com | K5: https://www.ycombinator.com/companies/hevn-inc | L5: high
A6: Liability insurance for companies that deploy AI agents. | B6: Klaimee | C6: Y Combinator | D6: YC Spring 2026 | E6: $500K | F6: standard YC deal ($125K for 7% + $375K uncapped SAFE); the startup's own round is not public | G6: San Francisco, CA, USA | H6: USA | I6: unknown | J6: https://www.klaimee.ai | K6: https://www.ycombinator.com/companies/klaimee | L6: high
A7: Lets people outside the US trade US stocks. | B7: Mochatrade | C7: Y Combinator | D7: YC Spring 2026 | E7: $500K | F7: standard YC deal ($125K for 7% + $375K uncapped SAFE); the startup's own round is not public | G7: New York City, NY, USA | H7: USA | I7: unknown | J7: https://www.mochatrade.com | K7: https://www.ycombinator.com/companies/mochatrade | L7: high
A8: A global bank account built on stablecoins (digital dollars). | B8: SpotPay | C8: Y Combinator | D8: YC Winter 2026 | E8: $500K | F8: standard YC deal ($125K for 7% + $375K uncapped SAFE); the startup's own round is not public | G8: San Francisco, CA, USA | H8: USA | I8: unknown | J8: https://www.spotpay.ai/ | K8: https://www.ycombinator.com/companies/spotpay | L8: high
A9: A hedge fund where AI researches and makes every trade. | B9: Standard Signal | C9: Y Combinator | D9: YC Spring 2026 | E9: $500K | F9: standard YC deal ($125K for 7% + $375K uncapped SAFE); the startup's own round is not public | G9: New York City, NY, USA | H9: USA | I9: unknown | J9: https://standardsignal.com | K9: https://www.ycombinator.com/companies/standard-signal | L9: high
A10: A platform to invest in collectibles such as sports and trading cards. | B10: tash | C10: Y Combinator | D10: YC Summer 2026 | E10: $500K | F10: standard YC deal ($125K for 7% + $375K uncapped SAFE); the startup's own round is not public | G10: San Francisco, CA, USA | H10: USA | I10: unknown | J10: https://www.tradetash.com | K10: https://www.ycombinator.com/companies/tash | L10: high
A11: Handles global payments, billing and tax for software companies selling across borders. Also in Google's 2026 India accelerator. | B11: Dodo Payments | C11: Antler India | D11: Portfolio shown on antler.co/india (read 2026-10-13) | E11: up to ₹4 crore (~$425K-$470K) | F11: standard Antler India deal for 11%; amount per startup not disclosed | G11: India | H11: India | I11: yes | K11: https://www.antler.co/india | L11: high
A12: A social trading app with tournaments and leagues. | B12: GameStock | C12: Peak XV Surge | D12: Surge 12 (Sep 2026) | E12: $2M | F12: Surge invests up to $5M per startup; the figure shown is funding as listed by Inc42, the Surge share is not disclosed | G12: New York, USA | H12: USA | I12: unknown | K12: https://inc42.com/buzz/meet-the-startups-from-peak-xvs-surge-12/ | L12: medium
A13: An AI personal finance app that shows income, spending, investments and loans together. | B13: Tribe Money | C13: Peak XV Surge | D13: Surge 12 (Sep 2026) | E13: $1M | F13: Surge invests up to $5M per startup; the figure shown is funding as listed by Inc42, the Surge share is not disclosed | G13: Delhi NCR, India | H13: India | I13: yes | K13: https://inc42.com/buzz/meet-the-startups-from-peak-xvs-surge-12/ | L13: medium
A14: Infrastructure for leveraged trading of any asset using decentralised finance. | B14: Derpetual | C14: Thiel Fellowship | D14: 2026 class (announced 2026-04-21) | E14: $250K | F14: grant paid over two years, no equity taken | G14: Poland (fellow's location) | H14: Other | I14: no | K14: https://insights.tryspecter.com/thiel-fellows-2026/ | L14: medium
A15: AI research on every US-listed stock, including tiny companies. The founder is 15. | B15: EveryTicker | C15: Thiel Fellowship | D15: 2026 class (announced 2026-04-21) | E15: $250K | F15: grant paid over two years, no equity taken | G15: Sammamish, WA, USA (fellow's location) | H15: USA | I15: unknown | K15: https://insights.tryspecter.com/thiel-fellows-2026/ | L15: medium
A16: Buying, credit and workflow tools for small businesses in underserved parts of Brazil. | B16: Praso | C16: Thiel Fellowship | D16: 2026 class (announced 2026-04-21) | E16: $250K | F16: grant paid over two years, no equity taken | G16: Recife, Brazil (fellow's location) | H16: Other | I16: no | K16: https://insights.tryspecter.com/thiel-fellows-2026/ | L16: medium
A17: Text a money expert instead of using a budgeting app. | B17: Flip | C17: a16z Speedrun | D17: SR007 (Jul-Oct 2026) | E17: up to $1M | F17: standard Speedrun deal: $500K for 10% now + $500K in the next round | G17: not stated (program runs in San Francisco) | H17: Unknown | I17: unknown | K17: https://www.frontrun.vc/blog/a16z-speedrun-cohort-007-companies/ | L17: medium
A18: Insurance for the new risks AI agents create. | B18: Keythorn | C18: a16z Speedrun | D18: SR007 (Jul-Oct 2026) | E18: up to $1M | F18: standard Speedrun deal: $500K for 10% now + $500K in the next round | G18: not stated (program runs in San Francisco) | H18: Unknown | I18: unknown | K18: https://www.frontrun.vc/blog/a16z-speedrun-cohort-007-companies/ | L18: medium
A19: A bank for European defense and security companies. | B19: Leonidas | C19: a16z Speedrun | D19: SR007 (Jul-Oct 2026) | E19: up to $1M | F19: standard Speedrun deal: $500K for 10% now + $500K in the next round | G19: not stated (program runs in San Francisco) | H19: Unknown | I19: unknown | K19: https://www.frontrun.vc/blog/a16z-speedrun-cohort-007-companies/ | L19: medium
A20: Market infrastructure for exchanges that list perpetual futures. | B20: Mecone | C20: a16z Speedrun | D20: SR007 (Jul-Oct 2026) | E20: up to $1M | F20: standard Speedrun deal: $500K for 10% now + $500K in the next round | G20: not stated (program runs in San Francisco) | H20: Unknown | I20: unknown | K20: https://www.frontrun.vc/blog/a16z-speedrun-cohort-007-companies/ | L20: medium
A21: Payment cards and spending controls for creators. | B21: Spun Labs | C21: a16z Speedrun | D21: SR007 (Jul-Oct 2026) | E21: up to $1M | F21: standard Speedrun deal: $500K for 10% now + $500K in the next round | G21: not stated (program runs in San Francisco) | H21: Unknown | I21: unknown | K21: https://www.frontrun.vc/blog/a16z-speedrun-cohort-007-companies/ | L21: medium

Sheet Bio and science
A1: Idea in simple words | B1: Startup | C1: Funded by | D1: Batch / cohort | E1: Funding | F1: What the funding number means | G1: Based in | H1: India / USA / Other | I1: Indian founders? | J1: Website | K1: Source | L1: Confidence
A2: A workspace that helps scientists find and use research papers faster. | B2: AnswerThis | C2: Y Combinator | D2: YC Fall 2025 | E2: $500K | F2: standard YC deal ($125K for 7% + $375K uncapped SAFE); the startup's own round is not public | G2: San Francisco, CA, USA | H2: USA | I2: unknown | J2: https://answerthis.io/ | K2: https://www.ycombinator.com/companies/answerthis | L2: high
A3: Simulates human biology on computers to find new drugs. | B3: CellType | C3: Y Combinator | D3: YC Winter 2026 | E3: $500K | F3: standard YC deal ($125K for 7% + $375K uncapped SAFE); the startup's own round is not public | G3: New York City, NY, USA | H3: USA | I3: unknown | J3: https://www.celltype.com | K3: https://www.ycombinator.com/companies/celltype | L3: high
A4: AI scientists that discover new materials for making chips. | B4: Discovered Materials | C4: Y Combinator | D4: YC Spring 2026 | E4: $500K | F4: standard YC deal ($125K for 7% + $375K uncapped SAFE); the startup's own round is not public | G4: San Francisco, CA, USA | H4: USA | I4: unknown | J4: https://discoveredmaterials.com | K4: https://www.ycombinator.com/companies/discovered-materials | L4: high
A5: A cancer treatment being developed for dogs first, then people. | B5: Gamgee | C5: Y Combinator | D5: YC Summer 2026 | E5: $500K | F5: standard YC deal ($125K for 7% + $375K uncapped SAFE); the startup's own round is not public | G5: San Francisco, CA, USA; Remote | H5: USA | I5: unknown | J5: https://gamgee.io/ | K5: https://www.ycombinator.com/companies/gamgee | L5: high
A6: Lets scientists control lab instruments by typing plain language. | B6: Infera | C6: Y Combinator | D6: YC Spring 2026 | E6: $500K | F6: standard YC deal ($125K for 7% + $375K uncapped SAFE); the startup's own round is not public | G6: San Francisco, CA, USA | H6: USA | I6: unknown | J6: https://www.infera.bio | K6: https://www.ycombinator.com/companies/infera | L6: high
A7: Robots that automate lab experiments. | B7: Neuromorphic | C7: Y Combinator | D7: YC Summer 2026 | E7: $500K | F7: standard YC deal ($125K for 7% + $375K uncapped SAFE); the startup's own round is not public | G7: San Francisco, CA, USA | H7: USA | I7: unknown | J7: https://www.neuromorphic.vision/ | K7: https://www.ycombinator.com/companies/neuromorphic | L7: high
A8: A much faster way to make chemicals. | B8: Rasyn | C8: Y Combinator | D8: YC Summer 2026 | E8: $500K | F8: standard YC deal ($125K for 7% + $375K uncapped SAFE); the startup's own round is not public | G8: San Francisco, CA, USA | H8: USA | I8: reported | J8: https://www.rasyn.ai/ | K8: https://www.ycombinator.com/companies/rasyn | L8: high
A9: Automates the regulatory paperwork drug and medical-device companies must file. | B9: Scoop | C9: Y Combinator | D9: YC Fall 2025 | E9: $500K | F9: standard YC deal ($125K for 7% + $375K uncapped SAFE); the startup's own round is not public | G9: San Francisco, CA, USA | H9: USA | I9: unknown | J9: https://scooplabs.ai | K9: https://www.ycombinator.com/companies/scoop | L9: high
A10: An AI co-scientist that speeds up discovery in life sciences, physics and chemistry. | B10: K-Dense | C10: Accel Atoms + Google AI Futures Fund | D10: Atoms AI Cohort 2026 (Mar-Jun 2026) | E10: up to $2M | F10: co-investment by Accel and Google AI Futures Fund, plus up to $350K compute credits; per-startup amount not disclosed | G10: not stated (program is for Indian and Indian-origin founders anywhere) | H10: Unknown | I10: yes | K10: https://www.outlookbusiness.com/deeptech/five-startups-to-join-accel-atoms-and-googles-ai-futures-fund-ai-cohort-2026 | L10: medium
A11: AI that coordinates lab robots through one software layer. | B11: Cornucopia Biosciences | C11: Antler US | D11: US Spring 2026 Showcase | E11: not disclosed | F11: taken from a third-party list that was not verified against Antler | G11: USA | H11: USA | I11: unknown | K11: https://agentjesse.ai/lists/antler-2026-cohort-companies | L11: low

Sheet Consumer apps
A1: Idea in simple words | B1: Startup | C1: Funded by | D1: Batch / cohort | E1: Funding | F1: What the funding number means | G1: Based in | H1: India / USA / Other | I1: Indian founders? | J1: Website | K1: Source | L1: Confidence
A2: An AI language-practice buddy inside the games kids already play. | B2: Aleph Lab | C2: Y Combinator | D2: YC Fall 2025 | E2: $500K | F2: standard YC deal ($125K for 7% + $375K uncapped SAFE); the startup's own round is not public | G2: San Francisco, CA, USA | H2: USA | I2: unknown | J2: http://alephlab.ai/ | K2: https://www.ycombinator.com/companies/aleph-lab | L2: high
A3: AI-based learning software for schools. | B3: Bloomy | C3: Y Combinator | D3: YC Summer 2026 | E3: $500K | F3: standard YC deal ($125K for 7% + $375K uncapped SAFE); the startup's own round is not public | G3: San Francisco, CA, USA | H3: USA | I3: unknown | J3: https://bloomylearning.com/ | K3: https://www.ycombinator.com/companies/bloomy | L3: high
A4: Learn a language by scrolling short videos. | B4: Doomersion | C4: Y Combinator | D4: YC Winter 2026 | E4: $500K | F4: standard YC deal ($125K for 7% + $375K uncapped SAFE); the startup's own round is not public | G4: San Francisco, CA, USA; Remote | H4: USA | I4: unknown | J4: https://doomersion.com/ | K4: https://www.ycombinator.com/companies/doomersion | L4: high
A5: A wearable that tracks skin health, like a fitness ring for skin. | B5: Lumeria | C5: Y Combinator | D5: YC Summer 2026 | E5: $500K | F5: standard YC deal ($125K for 7% + $375K uncapped SAFE); the startup's own round is not public | G5: San Francisco, CA, USA | H5: USA | I5: unknown | J5: https://lumeria.skin | K5: https://www.ycombinator.com/companies/lumeria | L5: high
A6: An AI health coach in a phone app. | B6: Nori | C6: Y Combinator | D6: YC Fall 2025 | E6: $500K | F6: standard YC deal ($125K for 7% + $375K uncapped SAFE); the startup's own round is not public | G6: New York City, NY, USA | H6: USA | I6: unknown | J6: https://nori.ai | K6: https://www.ycombinator.com/companies/nori | L6: high
A7: An AI-powered world-building strategy game. | B7: Pax Historia | C7: Y Combinator | D7: YC Winter 2026 | E7: $500K | F7: standard YC deal ($125K for 7% + $375K uncapped SAFE); the startup's own round is not public | G7: San Francisco, CA, USA | H7: USA | I7: unknown | J7: https://www.paxhistoria.co | K7: https://www.ycombinator.com/companies/pax-historia | L7: high
A8: Home-care technology for ageing parents and their families. | B8: Rhem Labs | C8: Y Combinator | D8: YC Fall 2026 | E8: $500K | F8: standard YC deal ($125K for 7% + $375K uncapped SAFE); the startup's own round is not public | G8: San Francisco, CA, USA | H8: USA | I8: unknown | J8: https://rhem.ai | K8: https://www.ycombinator.com/companies/rhem-labs | L8: high
A9: An AI agent that prepares tourist visa applications, checks documents and books appointments for people with weak passports. | B9: Veeza AI | C9: Y Combinator | D9: YC Fall 2026 | E9: $500K | F9: standard YC deal ($125K for 7% + $375K uncapped SAFE); the startup's own round is not public | G9: not stated | H9: Other | I9: unknown | J9: https://veeza.ai | K9: https://www.ycombinator.com/companies/veeza-ai | L9: high
A10: A Duolingo-style app for learning any subject. | B10: Wondering | C10: Y Combinator | D10: YC Summer 2026 | E10: $500K | F10: standard YC deal ($125K for 7% + $375K uncapped SAFE); the startup's own round is not public | G10: San Francisco, CA, USA | H10: USA | I10: unknown | J10: https://wondering.app | K10: https://www.ycombinator.com/companies/wondering | L10: high
A11: AI-made entertainment and streaming for consumers. | B11: Zingroll | C11: Accel Atoms + Google AI Futures Fund | D11: Atoms AI Cohort 2026 (Mar-Jun 2026) | E11: up to $2M | F11: co-investment by Accel and Google AI Futures Fund, plus up to $350K compute credits; per-startup amount not disclosed | G11: not stated (program is for Indian and Indian-origin founders anywhere) | H11: Unknown | I11: yes | K11: https://www.outlookbusiness.com/deeptech/five-startups-to-join-accel-atoms-and-googles-ai-futures-fund-ai-cohort-2026 | L11: medium
A12: A digital platform for reselling homes. | B12: HouseEazy | C12: Antler India | D12: Portfolio shown on antler.co/india (read 2026-10-13) | E12: up to ₹4 crore (~$425K-$470K) | F12: standard Antler India deal for 11%; amount per startup not disclosed | G12: India | H12: India | I12: yes | K12: https://www.antler.co/india | L12: high
A13: A wearable that gives on-demand stress relief using sound-based nerve stimulation. | B13: InnerGize | C13: Antler India | D13: Portfolio shown on antler.co/india (read 2026-10-13) | E13: up to ₹4 crore (~$425K-$470K) | F13: standard Antler India deal for 11%; amount per startup not disclosed | G13: India | H13: India | I13: yes | K13: https://www.antler.co/india | L13: high
A14: An AI matchmaker for campus dating that also arranges the date. | B14: Ditto | C14: Peak XV Surge | D14: Surge 12 (Sep 2026) | E14: $9.2M | F14: Surge invests up to $5M per startup; the figure shown is funding as listed by Inc42, the Surge share is not disclosed | G14: Berkeley, USA | H14: USA | I14: unknown | K14: https://inc42.com/buzz/meet-the-startups-from-peak-xvs-surge-12/ | L14: medium
A15: At-home beauty consultations where you pay only for the products you keep. | B15: Wingit | C15: Peak XV Surge | D15: Surge 12 (Sep 2026) | E15: $7M | F15: Surge invests up to $5M per startup; the figure shown is funding as listed by Inc42, the Surge share is not disclosed | G15: Gurugram, India | H15: India | I15: yes | K15: https://inc42.com/buzz/meet-the-startups-from-peak-xvs-surge-12/ | L15: medium
A16: A super app for Africa, starting with food delivery in Nigeria. | B16: Swoop | C16: Thiel Fellowship | D16: 2026 class (announced 2026-04-21) | E16: $250K | F16: grant paid over two years, no equity taken | G16: New York, USA (fellow's location) | H16: USA | I16: unknown | K16: https://insights.tryspecter.com/thiel-fellows-2026/ | L16: medium
A17: Shopping that starts from a video you just watched. | B17: Cartsy | C17: a16z Speedrun | D17: SR007 (Jul-Oct 2026) | E17: up to $1M | F17: standard Speedrun deal: $500K for 10% now + $500K in the next round | G17: not stated (program runs in San Francisco) | H17: Unknown | I17: unknown | K17: https://www.frontrun.vc/blog/a16z-speedrun-cohort-007-companies/ | L17: medium
A18: A studio that builds consumer apps with AI. | B18: DRS | C18: a16z Speedrun | D18: SR007 (Jul-Oct 2026) | E18: up to $1M | F18: standard Speedrun deal: $500K for 10% now + $500K in the next round | G18: not stated (program runs in San Francisco) | H18: Unknown | I18: unknown | K18: https://www.frontrun.vc/blog/a16z-speedrun-cohort-007-companies/ | L18: medium
A19: A consumer app whose characters are AI that remember you. | B19: Fictional | C19: a16z Speedrun | D19: SR007 (Jul-Oct 2026) | E19: up to $1M | F19: standard Speedrun deal: $500K for 10% now + $500K in the next round | G19: not stated (program runs in San Francisco) | H19: Unknown | I19: unknown | K19: https://www.frontrun.vc/blog/a16z-speedrun-cohort-007-companies/ | L19: medium
A20: Explore a real place in a simulated world before moving there, starting with homes. | B20: Mirai | C20: a16z Speedrun | D20: SR007 (Jul-Oct 2026) | E20: up to $1M | F20: standard Speedrun deal: $500K for 10% now + $500K in the next round | G20: not stated (program runs in San Francisco) | H20: Unknown | I20: unknown | K20: https://www.frontrun.vc/blog/a16z-speedrun-cohort-007-companies/ | L20: medium

Sheet Personal AI
A1: Idea in simple words | B1: Startup | C1: Funded by | D1: Batch / cohort | E1: Funding | F1: What the funding number means | G1: Based in | H1: India / USA / Other | I1: Indian founders? | J1: Website | K1: Source | L1: Confidence
A2: A ring and earphones for talking to AI assistants hands-free. Also part of India's WTFund 2026 cohort. | B2: antimattr | C2: Y Combinator | D2: YC Fall 2026 | E2: $500K | F2: standard YC deal ($125K for 7% + $375K uncapped SAFE); the startup's own round is not public | G2: San Francisco, CA, USA | H2: USA | I2: yes | J2: https://www.antimattr.one/project-mnemosyne | K2: https://www.ycombinator.com/companies/antimattr | L2: high
A3: A web browser that does tasks for you. | B3: Aside | C3: Y Combinator | D3: YC Fall 2025 | E3: $500K | F3: standard YC deal ($125K for 7% + $375K uncapped SAFE); the startup's own round is not public | G3: San Francisco, CA, USA | H3: USA | I3: unknown | J3: https://aside.com | K3: https://www.ycombinator.com/companies/aside | L3: high
A4: A tiny computer built only for talking to AI by voice. | B4: Button Computer | C4: Y Combinator | D4: YC Winter 2026 | E4: $500K | F4: standard YC deal ($125K for 7% + $375K uncapped SAFE); the startup's own round is not public | G4: San Francisco, CA, USA | H4: USA | I4: unknown | J4: https://buttoncomputer.com | K4: https://www.ycombinator.com/companies/button-computer | L4: high
A5: A personal AI assistant you talk to through text messages. | B5: Caddy | C5: Y Combinator | D5: YC Fall 2025 | E5: $500K | F5: standard YC deal ($125K for 7% + $375K uncapped SAFE); the startup's own round is not public | G5: New York City, NY, USA | H5: USA | I5: unknown | J5: https://caddy.app/ | K5: https://www.ycombinator.com/companies/caddy | L5: high
A6: AI glasses without a camera. | B6: E1O | C6: Y Combinator | D6: YC Spring 2026 | E6: $500K | F6: standard YC deal ($125K for 7% + $375K uncapped SAFE); the startup's own round is not public | G6: San Francisco, CA, USA | H6: USA | I6: unknown | J6: https://e1o.com | K6: https://www.ycombinator.com/companies/e1o | L6: high
A7: A to-do list that completes the tasks itself. | B7: Roma | C7: Y Combinator | D7: YC Fall 2026 | E7: $500K | F7: standard YC deal ($125K for 7% + $375K uncapped SAFE); the startup's own round is not public | G7: not stated | H7: Other | I7: unknown | J7: https://roma.app | K7: https://www.ycombinator.com/companies/roma | L7: high
A8: AI that runs on your own device, knows your files and history, and does your work overnight. | B8: Sentient OS | C8: Y Combinator | D8: YC Fall 2026 | E8: $500K | F8: standard YC deal ($125K for 7% + $375K uncapped SAFE); the startup's own round is not public | G8: San Francisco, CA, USA | H8: USA | I8: unknown | J8: https://sentient-os.ai | K8: https://www.ycombinator.com/companies/sentient-os | L8: high
A9: Lets you give commands to a computer by silent speech, without talking out loud. | B9: The Subvocal Company | C9: Y Combinator | D9: YC Fall 2026 | E9: $500K | F9: standard YC deal ($125K for 7% + $375K uncapped SAFE); the startup's own round is not public | G9: San Francisco, CA, USA | H9: USA | I9: unknown | J9: https://subvocal.company | K9: https://www.ycombinator.com/companies/the-subvocal-company | L9: high
A10: Lets you tell your computer a goal instead of clicking through apps and menus. | B10: Alma | C10: Peak XV Surge | D10: Surge 12 (Sep 2026) | E10: not disclosed | F10: Surge invests up to $5M per startup; the figure shown is funding as listed by Inc42, the Surge share is not disclosed | G10: San Francisco, USA | H10: USA | I10: unknown | K10: https://inc42.com/buzz/meet-the-startups-from-peak-xvs-surge-12/ | L10: medium
A11: A personal AI agent for busy people, starting with travel. | B11: Maestro | C11: a16z Speedrun | D11: SR007 (Jul-Oct 2026) | E11: up to $1M | F11: standard Speedrun deal: $500K for 10% now + $500K in the next round | G11: not stated (program runs in San Francisco) | H11: Unknown | I11: unknown | K11: https://www.frontrun.vc/blog/a16z-speedrun-cohort-007-companies/ | L11: medium
A12: A chief of staff for your household. | B12: Orbits | C12: a16z Speedrun | D12: SR007 (Jul-Oct 2026) | E12: up to $1M | F12: standard Speedrun deal: $500K for 10% now + $500K in the next round | G12: not stated (program runs in San Francisco) | H12: Unknown | I12: unknown | K12: https://www.frontrun.vc/blog/a16z-speedrun-cohort-007-companies/ | L12: medium
A13: A personal assistant built from years of your own context. | B13: Rollup | C13: a16z Speedrun | D13: SR007 (Jul-Oct 2026) | E13: up to $1M | F13: standard Speedrun deal: $500K for 10% now + $500K in the next round | G13: not stated (program runs in San Francisco) | H13: Unknown | I13: unknown | K13: https://www.frontrun.vc/blog/a16z-speedrun-cohort-007-companies/ | L13: medium

Sheet Creative tools
A1: Idea in simple words | B1: Startup | C1: Funded by | D1: Batch / cohort | E1: Funding | F1: What the funding number means | G1: Based in | H1: India / USA / Other | I1: Indian founders? | J1: Website | K1: Source | L1: Confidence
A2: An AI video editor: give it footage and a goal and it produces a first cut in minutes. | B2: Cardboard | C2: Y Combinator | D2: YC Winter 2026 | E2: $500K | F2: standard YC deal ($125K for 7% + $375K uncapped SAFE); the startup's own round is not public | G2: Bengaluru, KA, India | H2: India | I2: yes | J2: https://cardboard.ai | K2: https://www.ycombinator.com/companies/cardboard | L2: high
A3: Interactive AI avatars that can talk on screen. | B3: Keyframe Labs | C3: Y Combinator | D3: YC Spring 2026 | E3: $500K | F3: standard YC deal ($125K for 7% + $375K uncapped SAFE); the startup's own round is not public | G3: Los Angeles, CA, USA | H3: USA | I3: unknown | J3: https://keyframelabs.com | K3: https://www.ycombinator.com/companies/keyframe-labs | L3: high
A4: A tool for making films with AI. | B4: Koyal | C4: Y Combinator | D4: YC Fall 2025 | E4: $500K | F4: standard YC deal ($125K for 7% + $375K uncapped SAFE); the startup's own round is not public | G4: San Francisco, CA, USA | H4: USA | I4: unknown | J4: https://koyal.ai | K4: https://www.ycombinator.com/companies/koyal | L4: high
A5: An AI video editor. | B5: Narrative | C5: Y Combinator | D5: YC Fall 2025 | E5: $500K | F5: standard YC deal ($125K for 7% + $375K uncapped SAFE); the startup's own round is not public | G5: New York City, NY, USA | H5: USA | I5: unknown | J5: http://www.usenarrative.ai | K5: https://www.ycombinator.com/companies/usenarrative | L5: high
A6: Lets a designer explore dozens of design directions with an AI agent. | B6: Rivet | C6: Y Combinator | D6: YC Fall 2025 | E6: $500K | F6: standard YC deal ($125K for 7% + $375K uncapped SAFE); the startup's own round is not public | G6: San Francisco, CA, USA | H6: USA | I6: unknown | J6: https://rivet.design/ | K6: https://www.ycombinator.com/companies/rivet-design | L6: high
A7: Automatic video editing for people who are not editors. | B7: Vyra | C7: Y Combinator | D7: YC Fall 2026 | E7: $500K | F7: standard YC deal ($125K for 7% + $375K uncapped SAFE); the startup's own round is not public | G7: San Francisco, CA, USA | H7: USA | I7: unknown | J7: https://usevyra.com | K7: https://www.ycombinator.com/companies/vyra | L7: high
A8: AI product photos and virtual models for fashion and online-shopping brands. | B8: Ayna | C8: Google for Startups Accelerator: India | D8: 2026 cohort (announced 2026-07-08) | E8: no cash | F8: equity-free 3-month program with mentoring and credits; most companies here already have a product and earlier funding | G8: Bengaluru, India | H8: India | I8: yes | K8: https://inc42.com/buzz/meet-the-20-startups-selected-for-googles-india-startup-accelerator-2026/ | L8: medium
A9: Make and edit music from text prompts. | B9: Soundverse AI | C9: Google for Startups Accelerator: India | D9: 2026 cohort (announced 2026-07-08) | E9: no cash | F9: equity-free 3-month program with mentoring and credits; most companies here already have a product and earlier funding | G9: New York, USA | H9: USA | I9: yes | K9: https://inc42.com/buzz/meet-the-20-startups-selected-for-googles-india-startup-accelerator-2026/ | L9: medium
A10: A music studio in the browser where people make music together with an AI co-producer. | B10: Riffle | C10: Peak XV Surge | D10: Surge 12 (Sep 2026) | E10: not disclosed | F10: Surge invests up to $5M per startup; the figure shown is funding as listed by Inc42, the Surge share is not disclosed | G10: Bengaluru, India | H10: India | I10: yes | K10: https://inc42.com/buzz/meet-the-startups-from-peak-xvs-surge-12/ | L10: medium
A11: An AI agent that turns raw footage into clips ready to post. | B11: Reelful | C11: a16z Speedrun | D11: SR007 (Jul-Oct 2026) | E11: up to $1M | F11: standard Speedrun deal: $500K for 10% now + $500K in the next round | G11: not stated (program runs in San Francisco) | H11: Unknown | I11: unknown | K11: https://www.frontrun.vc/blog/a16z-speedrun-cohort-007-companies/ | L11: medium

Sheet Other
A1: Idea in simple words | B1: Startup | C1: Funded by | D1: Batch / cohort | E1: Funding | F1: What the funding number means | G1: Based in | H1: India / USA / Other | I1: Indian founders? | J1: Website | K1: Source | L1: Confidence

Sheet India-based
A1: Idea in simple words | B1: Startup | C1: Funded by | D1: Batch / cohort | E1: Funding | F1: What the funding number means | G1: Based in | H1: India / USA / Other | I1: Indian founders? | J1: Website | K1: Source | L1: Confidence
A2: An electric-vehicle fleet platform for ride-hailing drivers. | B2: Milo Drive | C2: Antler India | D2: Portfolio shown on antler.co/india (read 2026-10-13) | E2: up to ₹4 crore (~$425K-$470K) | F2: standard Antler India deal for 11%; amount per startup not disclosed | G2: India | H2: India | I2: yes | K2: https://www.antler.co/india | L2: high
A3: A marketplace that connects kirana stores with nearby distributors for same-day delivery. | B3: Tradeface | C3: Antler India | D3: Portfolio shown on antler.co/india (read 2026-10-13) | E3: up to ₹4 crore (~$425K-$470K) | F3: standard Antler India deal for 11%; amount per startup not disclosed | G3: India | H3: India | I3: yes | K3: https://www.antler.co/india | L3: high
A4: AI that does due-diligence and financial research for companies and investors. | B4: Binocs | C4: Google for Startups Accelerator: India | D4: 2026 cohort (announced 2026-07-08) | E4: no cash | F4: equity-free 3-month program with mentoring and credits; most companies here already have a product and earlier funding | G4: Bengaluru, India | H4: India | I4: yes | K4: https://inc42.com/buzz/meet-the-20-startups-selected-for-googles-india-startup-accelerator-2026/ | L4: medium
A5: AI agents that do compliance, risk and audit work for financial institutions. | B5: OnFinanceAI | C5: Google for Startups Accelerator: India | D5: 2026 cohort (announced 2026-07-08) | E5: no cash | F5: equity-free 3-month program with mentoring and credits; most companies here already have a product and earlier funding | G5: Bengaluru, India | H5: India | I5: yes | K5: https://inc42.com/buzz/meet-the-20-startups-selected-for-googles-india-startup-accelerator-2026/ | L5: medium
A6: Tools that verify identity and income and automate onboarding checks. | B6: TartanHQ | C6: Google for Startups Accelerator: India | D6: 2026 cohort (announced 2026-07-08) | E6: no cash | F6: equity-free 3-month program with mentoring and credits; most companies here already have a product and earlier funding | G6: Delhi NCR, India | H6: India | I6: yes | K6: https://inc42.com/buzz/meet-the-20-startups-selected-for-googles-india-startup-accelerator-2026/ | L6: medium
A7: A smartphone-based system that detects eye damage from high blood pressure; used in 18+ Indian villages. | B7: Hypertensight | C7: Emergent Ventures India | D7: 2026 cohorts 16-19 | E7: not disclosed | F7: grant to an individual or project; amounts are not published | G7: India | H7: India | I7: yes | K7: https://marginalrevolution.com/marginalrevolution/2026/09/emergent-ventures-india-19th-cohort.html | L7: medium
A8: Links ordinary eye photos with retinal scans to diagnose eye disease. | B8: Project Lumen AI | C8: Emergent Ventures India | D8: 2026 cohorts 16-19 | E8: not disclosed | F8: grant to an individual or project; amounts are not published | G8: India | H8: India | I8: yes | K8: https://marginalrevolution.com/marginalrevolution/2026/08/emergent-ventures-india-18th-cohort.html | L8: medium
A9: AI tools for radiology: faster MRI scans and disease detection for hospitals. | B9: Aikenist | C9: Google for Startups Accelerator: India | D9: 2026 cohort (announced 2026-07-08) | E9: no cash | F9: equity-free 3-month program with mentoring and credits; most companies here already have a product and earlier funding | G9: Bengaluru, India | H9: India | I9: yes | K9: https://inc42.com/buzz/meet-the-20-startups-selected-for-googles-india-startup-accelerator-2026/ | L9: medium
A10: An app that uses AI to deliver therapy programs for chronic back and joint pain. | B10: FlexifyMe | C10: Google for Startups Accelerator: India | D10: 2026 cohort (announced 2026-07-08) | E10: no cash | F10: equity-free 3-month program with mentoring and credits; most companies here already have a product and earlier funding | G10: Pune, India | H10: India | I10: yes | K10: https://inc42.com/buzz/meet-the-20-startups-selected-for-googles-india-startup-accelerator-2026/ | L10: medium
A11: An AI health assistant that explains symptoms, lab reports and prescriptions. | B11: August AI | C11: Peak XV Surge | D11: Surge 12 (Sep 2026) | E11: $3M | F11: Surge invests up to $5M per startup; the figure shown is funding as listed by Inc42, the Surge share is not disclosed | G11: Bengaluru, India | H11: India | I11: yes | K11: https://inc42.com/buzz/meet-the-startups-from-peak-xvs-surge-12/ | L11: medium
A12: Clinics for children's healthcare: consultations, vaccines and therapies. | B12: Hoola Health | C12: Peak XV Surge | D12: Surge 12 (Sep 2026) | E12: $5M | F12: Surge invests up to $5M per startup; the figure shown is funding as listed by Inc42, the Surge share is not disclosed | G12: Bengaluru, India | H12: India | I12: yes | K12: https://inc42.com/buzz/meet-the-startups-from-peak-xvs-surge-12/ | L12: medium
A13: A low-cost, needle-free test to screen for oral cancer in places with few doctors. | B13: Astraeus Innovus | C13: WTFund (Nikhil Kamath) | D13: Cohort 3, Class of 2026 | E13: ₹20 lakh | F13: grant, no equity taken | G13: India (city not stated) | H13: India | I13: yes | K13: https://odisha.plus/2026/01/nikhil-kamath-wtfund-young-founders-deeptech-healthcare-india/ | L13: medium
... A15: An AI device that attaches to a microscope to digitise and analyse pathology slides. | B15: Turocrates AI | C15: WTFund (Nikhil Kamath) | D15: Cohort 3, Class of 2026 | E15: ₹20 lakh | F15: grant, no equity taken | G15: India (city not stated) | H15: India | I15: yes | K15: https://odisha.plus/2026/01/nikhil-kamath-wtfund-young-founders-deeptech-healthcare-india/ | L15: medium
A16: An always-on AI "operations brain" that takes over complex day-to-day operations for a company. | B16: Redapto | C16: Y Combinator | D16: YC Fall 2025 | E16: $500K | F16: standard YC deal ($125K for 7% + $375K uncapped SAFE); the startup's own round is not public | G16: Bengaluru, KA, India | H16: India | I16: yes | J16: https://www.redapto.com/ | K16: https://www.ycombinator.com/companies/redapto | L16: high
A17: AI agents that research talent pools and explain why a candidate fits. | B17: Kello | C17: Peak XV Surge | D17: Surge 12 (Sep 2026) | E17: not disclosed | F17: Surge invests up to $5M per startup; the figure shown is funding as listed by Inc42, the Surge share is not disclosed | G17: Bengaluru, India | H17: India | I17: yes | K17: https://inc42.com/buzz/meet-the-startups-from-peak-xvs-surge-12/ | L17: medium
A18: Speech-to-text and workflow tools that help Indian courts and lawyers clear case backlogs. | B18: Adalat AI | C18: Google for Startups Accelerator: India | D18: 2026 cohort (announced 2026-07-08) | E18: no cash | F18: equity-free 3-month program with mentoring and credits; most companies here already have a product and earlier funding | G18: Delhi NCR, India | H18: India | I18: yes | K18: https://inc42.com/buzz/meet-the-20-startups-selected-for-googles-india-startup-accelerator-2026/ | L18: medium
A19: Payment infrastructure that lets AI agents pay safely on a user's behalf. | B19: Prava | C19: WTFund (Nikhil Kamath) | D19: Cohort 3, Class of 2026 | E19: ₹20 lakh | F19: grant, no equity taken | G19: India (city not stated) | H19: India | I19: yes | K19: https://odisha.plus/2026/01/nikhil-kamath-wtfund-young-founders-deeptech-healthcare-india/ | L19: medium
A20: Watches long-running AI agents, spots when they quietly fail or drift from the goal, and suggests the fix. | B20: BentoLabs AI | C20: Y Combinator | D20: YC Spring 2026 | E20: $500K | F20: standard YC deal ($125K for 7% + $375K uncapped SAFE); the startup's own round is not public | G20: Bengaluru, KA, India | H20: India | I20: yes | J20: https://bentolabs.ai/ | K20: https://www.ycombinator.com/companies/bentolabs-ai | L20: high
A21: A platform to train, test and launch AI agents that work inside real business systems. | B21: Ressl AI | C21: Y Combinator | D21: YC Winter 2026 | E21: $500K | F21: standard YC deal ($125K for 7% + $375K uncapped SAFE); the startup's own round is not public | G21: Bengaluru, KA, India | H21: India | I21: yes | J21: https://ressl.ai | K21: https://www.ycombinator.com/companies/ressl-ai | L21: high
A22: Tests and monitors voice AI agents before companies put them in front of customers. | B22: SuperBryn | C22: Google for Startups Accelerator: India | D22: 2026 cohort (announced 2026-07-08) | E22: no cash | F22: equity-free 3-month program with mentoring and credits; most companies here already have a product and earlier funding | G22: Bengaluru, India | H22: India | I22: yes | K22: https://inc42.com/buzz/meet-the-20-startups-selected-for-googles-india-startup-accelerator-2026/ | L22: medium
A23: Helps companies measure and manage their cyber-security risk in money terms. | B23: Zeron | C23: Google for Startups Accelerator: India | D23: 2026 cohort (announced 2026-07-08) | E23: no cash | F23: equity-free 3-month program with mentoring and credits; most companies here already have a product and earlier funding | G23: Mumbai, India | H23: India | I23: yes | K23: https://inc42.com/buzz/meet-the-20-startups-selected-for-googles-india-startup-accelerator-2026/ | L23: medium
A24: Software that turns existing CCTV cameras into live AI alerts for falls, fires and unauthorised entry. | B24: Aeyi | C24: WTFund (Nikhil Kamath) | D24: Cohort 3, Class of 2026 | E24: ₹20 lakh | F24: grant, no equity taken | G24: India (city not stated) | H24: India | I24: yes | K24: https://odisha.plus/2026/01/nikhil-kamath-wtfund-young-founders-deeptech-healthcare-india/ | L24: medium
A25: One security platform that protects a company's AI and software supply chain. | B25: O3 Security | C25: WTFund (Nikhil Kamath) | D25: Cohort 3, Class of 2026 | E25: ₹20 lakh | F25: grant, no equity taken | G25: India (city not stated) | H25: India | I25: yes | K25: https://odisha.plus/2026/01/nikhil-kamath-wtfund-young-founders-deeptech-healthcare-india/ | L25: medium
A26: AI that writes the software inside connected devices (firmware). | B26: CraftifAI | C26: Google for Startups Accelerator: India | D26: 2026 cohort (announced 2026-07-08) | E26: no cash | F26: equity-free 3-month program with mentoring and credits; most companies here already have a product and earlier funding | G26: Bengaluru, India | H26: India | I26: yes | K26: https://inc42.com/buzz/meet-the-20-startups-selected-for-googles-india-startup-accelerator-2026/ | L26: medium
A27: AI models and coding tools for low-level system and device software. | B27: H2Loop AI | C27: Google for Startups Accelerator: India | D27: 2026 cohort (announced 2026-07-08) | E27: no cash | F27: equity-free 3-month program with mentoring and credits; most companies here already have a product and earlier funding | G27: Bengaluru, India | H27: India | I27: yes | K27: https://inc42.com/buzz/meet-the-20-startups-selected-for-googles-india-startup-accelerator-2026/ | L27: medium
A28: Screen recordings of professionals using design and business software, sold to AI labs to train models that use computers. | B28: Markov | C28: Y Combinator | D28: YC Summer 2026 | E28: $500K | F28: standard YC deal ($125K for 7% + $375K uncapped SAFE); the startup's own round is not public | G28: Bengaluru, KA, India | H28: India | I28: yes | J28: https://www.markovstudios.com/ | K28: https://www.ycombinator.com/companies/markov | L28: high
A29: Builds small, cheap AI models that understand video for one specific job and can run on a company's own machines. | B29: Kailash Labs | C29: Y Combinator | D29: YC Fall 2026 | E29: $500K | F29: standard YC deal ($125K for 7% + $375K uncapped SAFE); the startup's own round is not public | G29: Bengaluru, KA, India | H29: India | I29: yes | J29: https://www.kailashlabs.com/ | K29: https://www.ycombinator.com/companies/kailash-labs | L29: high
A30: Search that helps AI coding agents find the right parts of a codebase before they write code. | B30: Perseus | C30: Y Combinator | D30: YC Fall 2025 | E30: $500K | F30: standard YC deal ($125K for 7% + $375K uncapped SAFE); the startup's own round is not public | G30: Bengaluru, KA, India | H30: India | I30: yes | J30: https://perseus.computer | K30: https://www.ycombinator.com/companies/perseus | L30: high
A31: A decentralised cloud for running AI workloads and blockchain apps. | B31: CreateOS by NodeOps | C31: Google for Startups Accelerator: India | D31: 2026 cohort (announced 2026-07-08) | E31: no cash | F31: equity-free 3-month program with mentoring and credits; most companies here already have a product and earlier funding | G31: Bengaluru, India | H31: India | I31: yes | K31: https://inc42.com/buzz/meet-the-20-startups-selected-for-googles-india-startup-accelerator-2026/ | L31: medium
A32: Voice AI for Indian businesses: automated phone calls for sales, support and collections, in Indian languages. | B32: Bolna AI | C32: Y Combinator | D32: YC Fall 2025 | E32: $500K | F32: standard YC deal ($125K for 7% + $375K uncapped SAFE); the startup's own round is not public | G32: Bengaluru, KA, India | H32: India | I32: yes | J32: https://bolna.ai | K32: https://www.ycombinator.com/companies/bolna-ai | L32: high
A33: Voice AI workers for US insurance companies. | B33: Infer.so | C33: Antler India | D33: Portfolio shown on antler.co/india (read 2026-10-13) | E33: up to ₹4 crore (~$425K-$470K) | F33: standard Antler India deal for 11%; amount per startup not disclosed | G33: India | H33: India | I33: yes | K33: https://www.antler.co/india | L33: high
A34: Voice AI for enterprises that works across many Indian languages. | B34: Navana.ai | C34: Antler India | D34: Portfolio shown on antler.co/india (read 2026-10-13) | E34: up to ₹4 crore (~$425K-$470K) | F34: standard Antler India deal for 11%; amount per startup not disclosed | G34: India | H34: India | I34: yes | K34: https://www.antler.co/india | L34: high
A35: Counter-drone defence systems. | B35: Armory | C35: Antler India | D35: Portfolio shown on antler.co/india (read 2026-10-13) | E35: up to ₹4 crore (~$425K-$470K) | F35: standard Antler India deal for 11%; amount per startup not disclosed | G35: India | H35: India | I35: yes | K35: https://www.antler.co/india | L35: high
A36: Self-flying aircraft that can operate on land and water. | B36: Aspera Industries | C36: Antler India | D36: Portfolio shown on antler.co/india (read 2026-10-13) | E36: up to ₹4 crore (~$425K-$470K) | F36: standard Antler India deal for 11%; amount per startup not disclosed | G36: India | H36: India | I36: yes | K36: https://www.antler.co/india | L36: high
A37: Robots in space that extend satellite life and reduce orbital debris. | B37: InspeCity | C37: Antler India | D37: Portfolio shown on antler.co/india (read 2026-10-13) | E37: up to ₹4 crore (~$425K-$470K) | F37: standard Antler India deal for 11%; amount per startup not disclosed | G37: India | H37: India | I37: yes | K37: https://www.antler.co/india | L37: high
A38: An electric vertical take-off aircraft company. | B38: Vyobha Aerospace | C38: Emergent Ventures India | D38: 2026 cohorts 16-19 | E38: not disclosed | F38: grant to an individual or project; amounts are not published | G38: India | H38: India | I38: yes | K38: https://marginalrevolution.com/marginalrevolution/2026/04/emergent-ventures-india-16th-cohort.html | L38: medium
A39: Groups of small satellites that detect and track radio signals for defence and shipping. | B39: ULOOK | C39: Peak XV Surge | D39: Surge 12 (Sep 2026) | E39: $2.3M | F39: Surge invests up to $5M per startup; the figure shown is funding as listed by Inc42, the Surge share is not disclosed | G39: Bengaluru, India | H39: India | I39: yes | K39: https://inc42.com/buzz/meet-the-startups-from-peak-xvs-surge-12/ | L39: medium
A40: Takes over the whole parts-buying process for hardware teams: quotes, payment, shipping, customs and stock tracking. | B40: Waybill | C40: Y Combinator | D40: YC Summer 2026 | E40: $500K | F40: standard YC deal ($125K for 7% + $375K uncapped SAFE); the startup's own round is not public | G40: Gurugram, HR, India | H40: India | I40: yes | J40: https://www.waybill.to/ | K40: https://www.ycombinator.com/companies/waybill | L40: high
A41: Green-hydrogen engines for aviation and shipping. | B41: Green Aero Propulsion | C41: Antler India | D41: Portfolio shown on antler.co/india (read 2026-10-13) | E41: up to ₹4 crore (~$425K-$470K) | F41: standard Antler India deal for 11%; amount per startup not disclosed | G41: India | H41: India | I41: yes | K41: https://www.antler.co/india | L41: high
A42: Sensors and AI that monitor air quality and water levels street by street. | B42: Aurassure | C42: Google for Startups Accelerator: India | D42: 2026 cohort (announced 2026-07-08) | E42: no cash | F42: equity-free 3-month program with mentoring and credits; most companies here already have a product and earlier funding | G42: Bhubaneswar, India | H42: India | I42: yes | K42: https://inc42.com/buzz/meet-the-20-startups-selected-for-googles-india-startup-accelerator-2026/ | L42: medium
A43: AI that helps companies measure and cut their carbon emissions. | B43: Fitsol | C43: Google for Startups Accelerator: India | D43: 2026 cohort (announced 2026-07-08) | E43: no cash | F43: equity-free 3-month program with mentoring and credits; most companies here already have a product and earlier funding | G43: Delhi NCR, India | H43: India | I43: yes | K43: https://inc42.com/buzz/meet-the-20-startups-selected-for-googles-india-startup-accelerator-2026/ | L43: medium
A44: Cameras and AI that inspect products for defects on factory lines. | B44: Jidoka | C44: Google for Startups Accelerator: India | D44: 2026 cohort (announced 2026-07-08) | E44: no cash | F44: equity-free 3-month program with mentoring and credits; most companies here already have a product and earlier funding | G44: Chennai, India | H44: India | I44: yes | K44: https://inc42.com/buzz/meet-the-20-startups-selected-for-googles-india-startup-accelerator-2026/ | L44: medium
A45: Smart wearables and safety gear for frontline industrial workers. | B45: Proxgy | C45: Google for Startups Accelerator: India | D45: 2026 cohort (announced 2026-07-08) | E45: no cash | F45: equity-free 3-month program with mentoring and credits; most companies here already have a product and earlier funding | G45: Delhi NCR, India | H45: India | I45: yes | K45: https://inc42.com/buzz/meet-the-20-startups-selected-for-googles-india-startup-accelerator-2026/ | L45: medium
A46: A desktop machine that places components on circuit boards for hardware prototyping. | B46: Placestation | C46: WTFund (Nikhil Kamath) | D46: Cohort 3, Class of 2026 | E46: ₹20 lakh | F46: grant, no equity taken | G46: India (city not stated) | H46: India | I46: yes | K46: https://odisha.plus/2026/01/nikhil-kamath-wtfund-young-founders-deeptech-healthcare-india/ | L46: medium
A47: Handles global payments, billing and tax for software companies selling across borders. Also in Google's 2026 India accelerator. | B47: Dodo Payments | C47: Antler India | D47: Portfolio shown on antler.co/india (read 2026-10-13) | E47: up to ₹4 crore (~$425K-$470K) | F47: standard Antler India deal for 11%; amount per startup not disclosed | G47: India | H47: India | I47: yes | K47: https://www.antler.co/india | L47: high
A48: An AI personal finance app that shows income, spending, investments and loans together. | B48: Tribe Money | C48: Peak XV Surge | D48: Surge 12 (Sep 2026) | E48: $1M | F48: Surge invests up to $5M per startup; the figure shown is funding as listed by Inc42, the Surge share is not disclosed | G48: Delhi NCR, India | H48: India | I48: yes | K48: https://inc42.com/buzz/meet-the-startups-from-peak-xvs-surge-12/ | L48: medium
A49: A digital platform for reselling homes. | B49: HouseEazy | C49: Antler India | D49: Portfolio shown on antler.co/india (read 2026-10-13) | E49: up to ₹4 crore (~$425K-$470K) | F49: standard Antler India deal for 11%; amount per startup not disclosed | G49: India | H49: India | I49: yes | K49: https://www.antler.co/india | L49: high
A50: A wearable that gives on-demand stress relief using sound-based nerve stimulation. | B50: InnerGize | C50: Antler India | D50: Portfolio shown on antler.co/india (read 2026-10-13) | E50: up to ₹4 crore (~$425K-$470K) | F50: standard Antler India deal for 11%; amount per startup not disclosed | G50: India | H50: India | I50: yes | K50: https://www.antler.co/india | L50: high
A51: At-home beauty consultations where you pay only for the products you keep. | B51: Wingit | C51: Peak XV Surge | D51: Surge 12 (Sep 2026) | E51: $7M | F51: Surge invests up to $5M per startup; the figure shown is funding as listed by Inc42, the Surge share is not disclosed | G51: Gurugram, India | H51: India | I51: yes | K51: https://inc42.com/buzz/meet-the-startups-from-peak-xvs-surge-12/ | L51: medium
